Workbook

Sheet INTRO
A1: INTRO — US Faker Dataset Validation Workbook
A3: Purpose: provide a self-contained front sheet for the synthetic US dataset, its schema metadata, normalization rules, regex library, and validation outputs.
A5: Dataset records | B5: 35
A6: Dataset columns | B6: 105
A7: TestMatrix columns | B7: 100
A8: Coverage gap | B8: 5
A10: How to read this workbook
A11: 1) Start with fakerUSDataset for raw synthetic values. 2) Use ColumnMetaData to understand the schema contract for each column. 3) Use RegexPatterns and ValidationRules to see how values are normalized and checked. 4) Use TestMatrix for step-1 format / regex validation. 5) Use TestMatrixStep2 for allowed-values validation after step 1 passes.
A15: Workbook map
A16: Sheet | C16: Role | E16: Primary contents | G16: How to use
A17: fakerUSDataset | C17: Source data | E17: Synthetic US dataset with one header row and sample records. | G17: Inspect raw values before interpreting validation results.
A18: RowMetaData | C18: Row contract | E18: Special row intent, including negative-control behavior. | G18: Use to understand why a row is expected to fail or pass.
A19: ColumnMetaData | C19: Schema contract | E19: Per-column type, pattern, bounds, allowed values, normalization, notes. | G19: Treat as the authoritative schema definition.
A20: ValidationRules | C20: Normalization library | E20: Named cleanup operations such as TRIM, LOWERCASE, DIGITS_ONLY. | G20: Read before modifying validation logic.
A21: RegexPatterns | C21: Pattern library | E21: Reusable named regex patterns referenced by columns. | G21: Check here before adding or renaming patterns.
A22: ValidationFormula | C22: Formula spec | E22: Plain-language record of the validation formulas used by the workbook. | G22: Use as the logic summary for step 1 and step 2.
A23: TestMatrix | C23: Validation step 1 | E23: Cell-by-cell regex / format validation output. | G23: TRUE = pass; returned raw value = inspect failure.
A24: TestMatrixStep2 | C24: Validation step 2 | E24: Allowed-values validation layered after step-1 success. | G24: Read alongside the output legend below.
A26: Validation pipeline
A27: Step 1 — TestMatrix: Normalize the raw value according to ColumnMetaData.normalize, then test the result against the named regex pattern. Step 2 — TestMatrixStep2: If step 1 passes, evaluate allowed_values for the column. If the column has no allowed-values list, the value is treated as passing that gate. Design intent: Return TRUE when the cell passes the relevant check. Return the original raw value when a reviewer should inspect the failing cell content.
A33: Output legend
A34: TRUE | C34: Validation pass at the current step.
A35: raw cell value returned | C35: Validation failure; inspect the original source value.
A36: TRUE, TRUE | C36: Passed step 1 and passed allowed-values validation in step 2.
A37: TRUE, <raw value> | C37: Passed structural / regex validation but failed allowed-values validation.
A38: FALSE | C38: Step 2 was blocked because the earlier gate did not pass.
A40: Coverage notes
A41: Observed coverage gap: fakerUSDataset currently contains more columns than TestMatrix / TestMatrixStep2. At present, the final five dataset fields are not represented in the validation matrices: date_separator_slash, date_separator_dash, grouping_separator, decimal_separator, and fraction_separator. Practical effect: the workbook is understandable, but validation coverage is not applied to those final 5 columns.
A46: Conventions
A47: Keywords: dataset, metadata, validation, regex, allowed_values, normalize, negative_control, test matrix. This workbook behaves like a schema-driven QA harness, not just a flat data sample. ColumnMetaData is the contract layer; ValidationRules and RegexPatterns are support libraries; TestMatrix sheets are executable review surfaces.
A52: Recommended maintenance rule: update this INTRO sheet whenever observable workbook behavior or validation coverage changes.

Sheet fakerUSDataset
A1: uuid4 | B1: name | C1: first_name | D1: last_name | E1: prefix | F1: suffix | G1: user_name | H1: job | I1: company | J1: company_suffix | K1: email | L1: ascii_email | M1: company_email | N1: phone_number | O1: basic_phone_number | P1: address | Q1: street_address | R1: street_name | S1: building_number | T1: city | U1: city_prefix | V1: city_suffix | W1: state | X1: state_abbr | Y1: country | Z1: country_code | AA1: zipcode | AB1: postalcode | AC1: domain_name | AD1: domain_word | AE1: url | AF1: uri | AG1: uri_path | AH1: uri_page | AI1: uri_extension | AJ1: ipv4 | AK1: ipv6 | AL1: mac_address | AM1: hostname | AN1: user_agent | AO1: credit_card_number | AP1: credit_card_provider | AQ1: credit_card_expire | AR1: credit_card_security_code | AS1: currency_code | AT1: currency_name | AU1: currency_symbol | AV1: latitude | AW1: longitude | AX1: coordinate | AY1: word | AZ1: words | BA1: sentence | BB1: paragraph | BC1: slug | BD1: text | BE1: color_name | BF1: hex_color | BG1: mime_type | BH1: file_name | BI1: file_extension | BJ1: date_mdy_slash_yyyy | BK1: date_mdy_dash_yyyy | BL1: date_mdy_slash_yy | BM1: date_mdy_dash_yy | BN1: timestamp_mdy_slash_minute | BO1: timestamp_mdy_dash_minute | BP1: timestamp_mdy_slash_second | BQ1: timestamp_mdy_dash_second | BR1: time_hh_mm | BS1: time_hh_mm_ss | BT1: time_hh_mm_ss_mmm | BU1: time_hh_mm_am_pm | BV1: time_hh_mm_ss_am_pm | BW1: time_hh_mm_ss_mmm_am_pm | BX1: timestamp_unix_s | BY1: timestamp_unix_ms | BZ1: year_yyyy | CA1: year_yy | CB1: month_mm | CC1: day_dd | CD1: day_of_week | CE1: decimal_1 | CF1: decimal_2 | CG1: decimal_3 | CH1: decimal_grouped_2 | CI1: ones | CJ1: tens | CK1: hundreds | CL1: thousands | CM1: ten_thousands | CN1: hundred_thousands | CO1: millions | CP1: number_plain | CQ1: number_grouped | CR1: number_scientific | CS1: currency_usd | CT1: currency_usd_plain | CU1: percent | CV1: percent_decimal | CW1: date_separator_slash | CX1: date_separator_dash | CY1: grouping_separator | CZ1: decimal_separator | DA1: fraction_separator
A2: bdd640fb-0667-4ad1-9c80-317fa3b1799d | B2: Daniel Doyle | C2: Erica | D2: Mcclain | E2: Mr. | F2: MD | G2: davisjesse | H2: Town planner | I2: Hoffman Ltd | J2: Ltd | K2: lrobinson@example.com | L2: helenpeterson@lewis.com | M2: jamesmichael@munoz-roman.info | N2: +1-516-318-4959 | O2: 7344131647 | P2: 419 Amanda Gardens South Noah, SC 90699 | Q2: 503 Linda Locks | R2: Jones Port | S2: 537 | T2: Wilkersonmouth | U2: East | V2: view | W2: Washington | X2: WA | Y2: United States | Z2: US | AA2: 71145 | AB2: 34939 | AC2: richards.com | AD2: hicks | AE2: http://www.burton.biz/ | AF2: http://frazier.net/tags/tagpost.asp | AG2: posts/category | AH2: post | AI2: php | AJ2: 104.13.74.245 | AK2: b83c:fe0b:e037:e5ed:b8db:673:f42d:47cc | AL2: 26:86:5b:36:98:65 | AM2: desktop-28.sellers.com | AN2: Mozilla/5.0 (compatible; MSIE 7.0; Windows CE; Trident/3.0) | AO2: 3543534624751075 | AP2: JCB 16 digit | AQ2: 10/35 | AR2: 118 | AS2: USD | AT2: US Dollar | AU2: $ | AV2: 62.921079 | AW2: -47.814142 | AX2: 62.921079,-47.814142 | AY2: down | AZ2: push, dog, build | BA2: Detail audience piece director town teacher audience draw. | BB2: Much rich think office drug. Space couple best issue interest level rock. Art rock song body. | BC2: dark-customer-not | BD2: Contain leg themselves away space task. Anything yourself structure why. Image loss ten total. Her world enter six. | BE2: Wheat | BF2: #284d83 | BG2: text/csv | BH2: particular-phone.csv | BI2: .csv | BJ2: 42753 | BK2: 42753 | BL2: 42753 | BM2: 42753 | BN2: 42753.455 | BO2: 42753.455 | BP2: 42753.455 | BQ2: 42753.455 | BR2: 0.45486111 | BS2: 0.45547454 | BT2: 0.45548545 | BU2: 0.45486111 | BV2: 0.45547454 | BW2: 0.45548545 | BX2: 1484736953 | BY2: 1484736953943 | BZ2: 2017 | CA2: 17 | CB2: 1 | CC2: 18 | CD2: Wednesday | CE2: 223987.5 | CF2: 223987.53 | CG2: 223987.53 | CH2: 223987.53 | CI2: 2 | CJ2: 20 | CK2: 200 | CL2: 2000 | CM2: 20000 | CN2: 200000 | CO2: 2000000 | CP2: 1720583 | CQ2: 1720583 | CR2: 1720000 | CS2: 3383.82 | CT2: 3383.82 | CU2: 0.8922 | CV2: 0.8922 | CW2: / | CX2: - | CY2: , | CZ2: . | DA2: .
A3: 21e8ac68-43e4-4caf-8181-a8cc369147eb | B3: Shirley Suarez | C3: Mike | D3: Moore | E3: Mx. | F3: DDS | G3: contrerasangela | H3: Civil Service administrator | I3: Baker Inc | J3: Ltd | K3: josephjacobs@example.net | L3: gracefarrell@hotmail.com | M3: dking@walters.com | N3: 2523427868 | O3: 4282059826 | P3: 3315 Dickson Summit East Michelle, AS 23707 | Q3: 25634 Kristin Coves Suite 073 | R3: Lisa Mount | S3: 4330 | T3: South Mark | U3: Port | V3: land | W3: Texas | X3: TX | Y3: United States | Z3: US | AA3: 67269 | AB3: 52887 | AC3: zavala.com | AD3: white-estes | AE3: https://www.carlson.com/ | AF3: https://www.meyer.com/list/wp-contentindex.php | AG3: tag/explore | AH3: homepage | AI3: html | AJ3: 135.249.220.117 | AK3: 81d2:c7de:4ce1:eb90:e669:7834:b841:d0a0 | AL3: 8c:9e:d1:a7:ce:97 | AM3: srv-36.bentley.org | AN3: Mozilla/5.0 (Macintosh; U; Intel Mac OS X 10_12_7 rv:5.0; iu-CA) AppleWebKit/533.26.5 (KHTML, like Gecko) Version/4.0.3 Safari/533.26.5 | AO3: 4170805310033092328 | AP3: VISA 19 digit | AQ3: 04/34 | AR3: 193 | AS3: USD | AT3: US Dollar | AU3: $ | AV3: 32.057421 | AW3: -4.525993 | AX3: 32.057421,-4.525993 | AY3: rise | AZ3: consider, employee, force | BA3: Sing despite sound receive. | BB3: Newspaper true building. Soon property write other. Partner rest measure store natural today. | BC3: six-training-may | BD3: Style everyone sing machine dream. Back experience even floor music catch. Really relationship ask imagine my indeed. Strategy hope show watch affect. | BE3: White | BF3: #06e746 | BG3: image/jpeg | BH3: green-sort-until.jpg | BI3: .jpg | BJ3: 37273 | BK3: 37273 | BL3: 37273 | BM3: 37273 | BN3: 37273.233 | BO3: 37273.233 | BP3: 37273.234 | BQ3: 37273.234 | BR3: 0.23333333 | BS3: 0.23396991 | BT3: 0.23397022 | BU3: 0.23333333 | BV3: 0.23396991 | BW3: 0.23397022 | BX3: 1011245815 | BY3: 1011245815027 | BZ3: 2002 | CA3: 2 | CB3: 1 | CC3: 17 | CD3: Thursday | CE3: 94601.5 | CF3: 94601.54 | CG3: 94601.545 | CH3: 94601.54 | CI3: 4 | CJ3: 40 | CK3: 400 | CL3: 4000 | CM3: 40000 | CN3: 400000 | CO3: 4000000 | CP3: 3904402 | CQ3: 3904402 | CR3: 3900000 | CS3: 2527.27 | CT3: 2527.27 | CU3: 0.0265 | CV3: 0.0265 | CW3: / | CX3: - | CY3: , | CZ3: . | DA3: .
A4: c4536f1d-4199-4fdf-b310-22f0770c7798 | B4: Larry Stuart | C4: Jennifer | D4: Strickland | E4: Mr. | F4: MD | G4: hickmanbarbara | H4: Mining engineer | I4: David-Gonzalez | J4: PLC | K4: curtisbarton@example.net | L4: reedross@jones-holland.com | M4: gshort@yu-reid.info | N4: 001-626-728-4987x769 | O4: 7142737996 | P4: 73545 Beard Squares Suite 808 North John, MT 64539 | Q4: 777 Christopher Forges | R4: Holt Inlet | S4: 957 | T4: Ronaldside | U4: West | V4: stad | W4: Washington | X4: WA | Y4: United States | Z4: US | AA4: 33452 | AB4: 30718 | AC4: griffith.com | AD4: herrera | AE4: http://hardy-bray.net/ | AF4: https://www.turner.net/categorymain.php | AG4: category | AH4: index | AI4: html | AJ4: 5.2.158.210 | AK4: 7daa:39f0:c0b6:fce2:de53:790b:a34b:6cf6 | AL4: 70:34:06:91:f0:f5 | AM4: desktop-20.everett-woods.com | AN4: Opera/9.20.(Windows 98; st-ZA) Presto/2.9.164 Version/10.00 | AO4: 639077034820 | AP4: Maestro | AQ4: 02/31 | AR4: 771 | AS4: USD | AT4: US Dollar | AU4: $ | AV4: -89.691013 | AW4: 173.07873 | AX4: -89.691013,173.078729 | AY4: recent | AZ4: wife, identify, method | BA4: Able late order fact. | BB4: Religious reflect law reach under. Operation sound cup boy different chance enter central. | BC4: as-company | BD4: See notice eye buy read record wall matter. Just our threat same page ago director. | BE4: PaleGoldenRod | BF4: #d045de | BG4: video/mp4 | BH4: true-occur-maintain.mp4 | BI4: .mp4 | BJ4: 42114 | BK4: 42114 | BL4: 42114 | BM4: 42114 | BN4: 42114.404 | BO4: 42114.404 | BP4: 42114.405 | BQ4: 42114.405 | BR4: 0.40416667 | BS4: 0.4046412 | BT4: 0.4046419 | BU4: 0.40416667 | BV4: 0.4046412 | BW4: 0.4046419 | BX4: 1429522961 | BY4: 1429522961060 | BZ4: 2015 | CA4: 15 | CB4: 4 | CC4: 20 | CD4: Monday | CE4: 449759.8 | CF4: 449759.84 | CG4: 449759.84 | CH4: 449759.84 | CI4: 3 | CJ4: 30 | CK4: 300 | CL4: 3000 | CM4: 30000 | CN4: 300000 | CO4: 3000000 | CP4: 4668265 | CQ4: 4668265 | CR4: 4670000 | CS4: 4047.34 | CT4: 4047.34 | CU4: 0.0065 | CV4: 0.0065 | CW4: / | CX4: - | CY4: , | CZ4: . | DA4: .
A5: 9bdf0377-a149-43c2-b920-264c0763fcd0 | B5: Michelle Collins | C5: Alexander | D5: Russell | E5: Mr. | F5: PhD | G5: murraydavid | H5: Designer, exhibition/display | I5: Cantu-Carter | J5: Ltd | K5: robert77@example.org | L5: patrickweeks@hotmail.com | M5: michellehill@morgan-french.com | N5: 9447997278 | O5: 888-567-5339 | P5: 57662 Hanna Crossroad Suite 171 Smithberg, MT 86324 | Q5: 74596 Melissa Walk | R5: Finley Road | S5: 780 | T5: East Crystalport | U5: East | V5: land | W5: Georgia | X5: GA | Y5: United States | Z5: US | AA5: 92761 | AB5: 13674 | AC5: jackson-evans.com | AD5: nguyen | AE5: https://jordan-sanchez.biz/ | AF5: http://www.vega.com/mainfaq.php | AG5: tags/tag | AH5: about | AI5: html | AJ5: 222.227.90.202 | AK5: 8bed:db12:ad77:e82f:49a2:3a8a:e6b5:a92c | AL5: a2:50:25:e2:b0:99 | AM5: laptop-47.gonzalez-cruz.info | AN5: Mozilla/5.0 (Windows NT 6.0) AppleWebKit/532.1 (KHTML, like Gecko) Chrome/56.0.899.0 Safari/532.1 | AO5: 370240268117755 | AP5: American Express | AQ5: 12/34 | AR5: CID: 9178 | AS5: USD | AT5: US Dollar | AU5: $ | AV5: -60.491872 | AW5: 174.90262 | AX5: -60.491872,174.902617 | AY5: bag | AZ5: would, music, sometimes | BA5: Whose source hand so add Mr. | BB5: Pull public once state wait board. Likely people wall foreign particular. Play less red power. | BC5: but-challenge | BD5: You break doctor Mr home. Industry score choice increase between majority impact. Allow have kitchen wear talk. Wonder happen top population. | BE5: IndianRed | BF5: #d0243e | BG5: image/png | BH5: trial-agree-catch.png | BI5: .png | BJ5: 40466 | BK5: 40466 | BL5: 40466 | BM5: 40466 | BN5: 40466.924 | BO5: 40466.924 | BP5: 40466.924 | BQ5: 40466.924 | BR5: 0.92430556 | BS5: 0.92435185 | BT5: 0.9243601 | BU5: 0.92430556 | BV5: 0.92435185 | BW5: 0.9243601 | BX5: 1287180664 | BY5: 1287180664713 | BZ5: 2010 | CA5: 10 | CB5: 10 | CC5: 15 | CD5: Friday | CE5: 216098.4 | CF5: 216098.45 | CG5: 216098.45 | CH5: 216098.45 | CI5: 6 | CJ5: 60 | CK5: 600 | CL5: 6000 | CM5: 60000 | CN5: 600000 | CO5: 6000000 | CP5: 5648119 | CQ5: 5648119 | CR5: 5650000 | CS5: 511.95 | CT5: 511.95 | CU5: 0.3799 | CV5: 0.3799 | CW5: / | CX5: - | CY5: , | CZ5: . | DA5: .
A6: 0b19f88e-9d77-445e-b206-c26938b77c07 | B6: Susan Hopkins | C6: Kevin | D6: Schneider | E6: Mr. | F6: DVM | G6: gsimmons | H6: Recycling officer | I6: Browning, Jones and Miller | J6: PLC | K6: cameronhill@example.net | L6: hvang@yahoo.com | M6: bwagner@mcguire.net | N6: 001-736-673-6576x6156 | O6: 727-411-1161 | P6: 165 Parrish Stravenue Apt. 494 Dalehaven, IL 20781 | Q6: 15851 Andrews Valley Suite 899 | R6: Chelsea Shoals | S6: 402 | T6: Jacquelineport | U6: West | V6: stad | W6: Florida | X6: FL | Y6: United States | Z6: US | AA6: 74729 | AB6: 86660 | AC6: jones-figueroa.com | AD6: reese | AE6: https://peterson-wood.com/ | AF6: http://www.miller.org/wp-contentprivacy.html | AG6: category/wp-content | AH6: login | AI6: html | AJ6: 39.24.209.106 | AK6: 97d7:a560:adb1:4670:ad9f:b00e:4882:d73c | AL6: fc:f9:9d:17:70:ca | AM6: lt-00.turner.com | AN6: Mozilla/5.0 (compatible; MSIE 7.0; Windows NT 5.0; Trident/3.0) | AO6: 3515186449251924 | AP6: JCB 16 digit | AQ6: 02/32 | AR6: 462 | AS6: USD | AT6: US Dollar | AU6: $ | AV6: -14.061333 | AW6: 27.992683 | AX6: -14.061333,27.992683 | AY6: building | AZ6: model, particular, hair | BA6: Least ready gun join black job hundred bad. | BB6: Develop single baby plan most create. Go when population challenge bill eight. | BC6: consumer-play-claim | BD6: Week physical less nor. Large under north play person ten physical character. Kind field ever argue medical financial later. Hard expert popular within. | BE6: MediumSpringGreen | BF6: #fb7da0 | BG6: application/pdf | BH6: issue-stage-ground.pdf | BI6: .pdf | BJ6: 37659 | BK6: 37659 | BL6: 37659 | BM6: 37659 | BN6: 37659.748 | BO6: 37659.748 | BP6: 37659.748 | BQ6: 37659.748 | BR6: 0.74791667 | BS6: 0.74849537 | BT6: 0.74849628 | BU6: 0.74791667 | BV6: 0.74849537 | BW6: 0.74849628 | BX6: 1044640670 | BY6: 1044640670079 | BZ6: 2003 | CA6: 3 | CB6: 2 | CC6: 7 | CD6: Friday | CE6: 730002.1 | CF6: 730002.05 | CG6: 730002.06 | CH6: 730002.05 | CI6: 2 | CJ6: 20 | CK6: 200 | CL6: 2000 | CM6: 20000 | CN6: 200000 | CO6: 2000000 | CP6: 8997414 | CQ6: 8997414 | CR6: 9000000 | CS6: 625.01 | CT6: 625.01 | CU6: 0.9223 | CV6: 0.9223 | CW6: / | CX6: - | CY6: , | CZ6: . | DA6: .
A7: 15b02530-f020-4992-b576-255e98549f22 | B7: James Conner | C7: Lisa | D7: Santiago | E7: Mx. | F7: DDS | G7: lucasrodney | H7: Medical illustrator | I7: Cox and Sons | J7: and Sons | K7: stacey73@example.org | L7: chrisrichard@romero.net | M7: stanleynancy@anderson.org | N7: (970)565-3794 | O7: (634)873-5977 | P7: 39240 Sawyer Plaza Apt. 814 Port Ethanmouth, MH 67787 | Q7: 1375 Robert Locks | R7: Young Common | S7: 3051 | T7: Laceyberg | U7: North | V7: port | W7: New York | X7: NY | Y7: United States | Z7: US | AA7: 92977 | AB7: 61988 | AC7: gilbert-bullock.com | AD7: lewis-hernandez | AE7: https://www.young-martinez.com/ | AF7: https://herrera.com/mainauthor.jsp | AG7: tag/tags | AH7: main | AI7: php | AJ7: 96.175.86.94 | AK7: 1153:6e99:5c50:8720:f982:f4e1:8603:156a | AL7: fa:0a:c7:f0:16:c6 | AM7: desktop-40.kramer-cooper.com | AN7: Mozilla/5.0 (Windows; U; Windows NT 6.2) AppleWebKit/533.9.1 (KHTML, like Gecko) Version/5.0 Safari/533.9.1 | AO7: 213191146786694 | AP7: JCB 15 digit | AQ7: 46200 | AR7: 251 | AS7: USD | AT7: US Dollar | AU7: $ | AV7: -52.720524 | AW7: -52.90323 | AX7: -52.720524,-52.903230 | AY7: role | AZ7: meeting, building, cut | BA7: Risk bad own state. | BB7: Fly bag produce fill owner. Coach know language risk treatment past. Ever woman way avoid point guy. | BC7: suddenly-so-respond | BD7: Support question just call. Gun we allow check last he. Several off morning huge power economic. Save material hit. Brother simple region Democrat partner really your. | BE7: Coral | BF7: #8ccc9d | BG7: application/pdf | BH7: street-minute-agree.pdf | BI7: .pdf | BJ7: 45765 | BK7: 45765 | BL7: 45765 | BM7: 45765 | BN7: 45765.235 | BO7: 45765.235 | BP7: 45765.236 | BQ7: 45765.236 | BR7: 0.23541667 | BS7: 0.23555556 | BT7: 0.23556372 | BU7: 0.23541667 | BV7: 0.23555556 | BW7: 0.23556372 | BX7: 1744954752 | BY7: 1744954752705 | BZ7: 2025 | CA7: 25 | CB7: 4 | CC7: 18 | CD7: Friday | CE7: 577774.8 | CF7: 577774.79 | CG7: 577774.79 | CH7: 577774.79 | CI7: 5 | CJ7: 50 | CK7: 500 | CL7: 5000 | CM7: 50000 | CN7: 500000 | CO7: 5000000 | CP7: 1167941 | CQ7: 1167941 | CR7: 1170000 | CS7: 230.08 | CT7: 230.08 | CU7: 0.2279 | CV7: 0.2279 | CW7: / | CX7: - | CY7: , | CZ7: . | DA7: .
A8: 8471b4b0-ae1b-4f69-b740-d83173318749 | B8: Shawn Deleon | C8: Danielle | D8: White | E8: Misc. | F8: MD | G8: guerraapril | H8: Industrial buyer | I8: Martin Ltd | J8: and Sons | K8: stacey84@example.org | L8: cynthiapierce@gmail.com | M8: christina18@jackson.org | N8: 001-295-990-0109x4396 | O8: (384)247-3647 | P8: 7359 Larry Stravenue Suite 562 Zacharyville, MD 32186 | Q8: 47321 Kelly Lights Suite 325 | R8: Lee Estate | S8: 8774 | T8: Johnsonfurt | U8: New | V8: mouth | W8: Alaska | X8: AK | Y8: United States | Z8: US | AA8: 6878 | AB8: 7125 | AC8: simpson-khan.info | AD8: herrera-boone | AE8: https://www.luna-gallagher.com/ | AF8: http://tran-jones.net/postslogin.htm | AG8: posts/search | AH8: faq | AI8: html | AJ8: 70.48.7.138 | AK8: fc9e:1dcb:cb7e:6268:5f89:ed13:64d6:dfbf | AL8: 80:ad:bb:49:65:cd | AM8: db-00.reeves.net | AN8: Opera/9.30.(Windows NT 6.0; ru-RU) Presto/2.9.170 Version/12.00 | AO8: 30454019380263 | AP8: Diners Club / Carte Blanche | AQ8: 46110 | AR8: 67 | AS8: USD | AT8: US Dollar | AU8: $ | AV8: -47.603015 | AW8: 38.456775 | AX8: -47.603015,38.456775 | AY8: media | AZ8: side, accept, nearly | BA8: Challenge quite all way body affect. | BB8: Charge real improve simple turn their. Relationship million night your. Moment finish community treatment garden great sign. | BC8: set-responsibility | BD8: Machine whatever everything fear walk word side relate. First give value somebody event business quality. | BE8: Lavender | BF8: #0d700f | BG8: application/xml | BH8: read-worry-up-unit.xml | BI8: .xml | BJ8: 39104 | BK8: 39104 | BL8: 39104 | BM8: 39104 | BN8: 39104.297 | BO8: 39104.297 | BP8: 39104.297 | BQ8: 39104.297 | BR8: 0.29652778 | BS8: 0.29688657 | BT8: 0.29688799 | BU8: 0.29652778 | BV8: 0.29688657 | BW8: 0.29688799 | BX8: 1169449651 | BY8: 1169449651122 | BZ8: 2007 | CA8: 7 | CB8: 1 | CC8: 22 | CD8: Monday | CE8: 380746.1 | CF8: 380746.1 | CG8: 380746.1 | CH8: 380746.1 | CI8: 6 | CJ8: 60 | CK8: 600 | CL8: 6000 | CM8: 60000 | CN8: 600000 | CO8: 6000000 | CP8: 7607962 | CQ8: 7607962 | CR8: 7610000 | CS8: 3178.79 | CT8: 3178.79 | CU8: 0.3648 | CV8: 0.3648 | CW8: / | CX8: - | CY8: , | CZ8: . | DA8: .
A9: f64e3dfc-bfbe-4c7a-afc5-97382fb21e66 | B9: Donna Johnson | C9: Kenneth | D9: Morrison | E9: Ind. | F9: MD | G9: ihays | H9: Scientist, research (physical sciences) | I9: Small-Anderson | J9: PLC | K9: znelson@example.org | L9: jessicawong@hotmail.com | M9: alexisrogers@bradley-todd.com | N9: +1-566-285-1612x275 | O9: 263-674-5499 | P9: 17426 Vaughn Route Michaelbury, IN 18008 | Q9: 79568 Todd Unions Apt. 391 | R9: Rice Lake | S9: 91088 | T9: New Amanda | U9: East | V9: mouth | W9: Florida | X9: FL | Y9: United States | Z9: US | AA9: 27423 | AB9: 94468 | AC9: burns.com | AD9: anderson-perry | AE9: http://roman.com/ | AF9: http://www.mcknight.info/categorieshomepage.html | AG9: category | AH9: category | AI9: html | AJ9: 189.115.154.227 | AK9: 61ea:2f30:e42e:707a:fe2b:d988:5fdc:abbf | AL9: a6:e5:c1:c0:29:44 | AM9: web-51.haney.net | AN9: Mozilla/5.0 (X11; Linux i686; rv:1.9.5.20) Gecko/9254-09-20 06:44:41 Firefox/4.0 | AO9: 30522872808016 | AP9: Diners Club / Carte Blanche | AQ9: 46049 | AR9: 62 | AS9: USD | AT9: US Dollar | AU9: $ | AV9: -20.924376 | AW9: 82.326452 | AX9: -20.924376,82.326452 | AY9: produce | AZ9: material, pressure, range | BA9: Walk provide skill five indicate chance. | BB9: Senior list support feeling. South trip none whose. Morning home effort form bad last he. | BC9: north-shake | BD9: Environmental purpose owner. Could seven right next. Thank four whatever address view. Section senior trial receive. However dream focus executive letter. | BE9: PapayaWhip | BF9: #4b91b9 | BG9: application/xml | BH9: several-quality.xml | BI9: .xml | BJ9: 43319 | BK9: 43319 | BL9: 43319 | BM9: 43319 | BN9: 43319.911 | BO9: 43319.911 | BP9: 43319.911 | BQ9: 43319.911 | BR9: 0.91111111 | BS9: 0.91125 | BT9: 0.91125819 | BU9: 0.91111111 | BV9: 0.91125 | BW9: 0.91125819 | BX9: 1533678732 | BY9: 1533678732708 | BZ9: 2018 | CA9: 18 | CB9: 8 | CC9: 7 | CD9: Tuesday | CE9: 702118.5 | CF9: 702118.49 | CG9: 702118.49 | CH9: 702118.49 | CI9: 4 | CJ9: 40 | CK9: 400 | CL9: 4000 | CM9: 40000 | CN9: 400000 | CO9: 4000000 | CP9: 1198935 | CQ9: 1198935 | CR9: 1200000 | CS9: 3046.05 | CT9: 3046.05 | CU9: 0.1711 | CV9: 0.1711 | CW9: / | CX9: - | CY9: , | CZ9: . | DA9: .
A10: 116658ce-3b3f-4800-a175-a9c3d7b102a9 | B10: Alexa Wagner | C10: Nathaniel | D10: Williamson | E10: Miss | F10: DDS | G10: bhopkins | H10: Accounting technician | I10: Arnold, Smith and Moreno | J10: LLC | K10: andre62@example.org | L10: johnharvey@ochoa-adams.biz | M10: watsonrichard@sanchez.com | N10: +1-801-766-6870x0217 | O10: (218)303-3974 | P10: 902 Smith Fords Apt. 614 New John, MP 51508 | Q10: 2185 Connor Fort Apt. 599 | R10: Novak Islands | S10: 47735 | T10: Reynoldsshire | U10: Lake | V10: furt | W10: Arizona | X10: AZ | Y10: United States | Z10: US | AA10: 32803 | AB10: 93969 | AC10: miller.biz | AD10: bowers | AE10: https://www.smith.info/ | AF10: https://cole-peters.biz/wp-contenthome.html | AG10: app | AH10: home | AI10: php | AJ10: 3.76.55.118 | AK10: 4ab6:821c:328:c136:629e:f3d9:dd1c:a267 | AL10: ae:d3:c6:2b:7c:56 | AM10: laptop-22.turner-snyder.com | AN10: Mozilla/5.0 (Android 4.3.1; Mobile; rv:42.0) Gecko/42.0 Firefox/42.0 | AO10: 6557924991251344 | AP10: Discover | AQ10: 46109 | AR10: 252 | AS10: USD | AT10: US Dollar | AU10: $ | AV10: 41.394855 | AW10: 103.31484 | AX10: 41.394855,103.314840 | AY10: institution | AZ10: hand, culture, box | BA10: Myself so growth time Mr point. | BB10: Shoulder price great positive. None population position. | BC10: soldier-glass-style | BD10: Better develop section. Oil offer knowledge hospital sign open matter. Lot far turn. Break wait center find. Six miss give best reveal laugh attack. Against gas body son. | BE10: HotPink | BF10: #34ae4b | BG10: audio/mpeg | BH10: purpose-form.mp3 | BI10: .mp3 | BJ10: 43404 | BK10: 43404 | BL10: 43404 | BM10: 43404 | BN10: 43404.88 | BO10: 43404.88 | BP10: 43404.88 | BQ10: 43404.88 | BR10: 0.87986111 | BS10: 0.88003472 | BT10: 0.88004138 | BU10: 0.87986111 | BV10: 0.88003472 | BW10: 0.88004138 | BX10: 1541020035 | BY10: 1541020035575 | BZ10: 2018 | CA10: 18 | CB10: 10 | CC10: 31 | CD10: Wednesday | CE10: 989533.8 | CF10: 989533.83 | CG10: 989533.83 | CH10: 989533.83 | CI10: 1 | CJ10: 10 | CK10: 100 | CL10: 1000 | CM10: 10000 | CN10: 100000 | CO10: 1000000 | CP10: 9345066 | CQ10: 9345066 | CR10: 9350000 | CS10: 1098.86 | CT10: 1098.86 | CU10: 0.3243 | CV10: 0.3243 | CW10: / | CX10: - | CY10: , | CZ10: . | DA10: .
A11: 98af5cca-6b11-47cb-a372-542482c56b21 | B11: James Lopez | C11: Cynthia | D11: Steele | E11: Ms. | F11: DVM | G11: tracytaylor | H11: International aid/development worker | I11: Harvey-Glenn | J11: Inc | K11: ytaylor@example.net | L11: acohen@hotmail.com | M11: fburns@johnson.com | N11: 384.327.9788 | O11: 385-580-7836 | P11: 4517 Kimberly Freeway Port Joan, UT 46458 | Q11: 92330 Patel Ranch Apt. 544 | R11: Farley Passage | S11: 126 | T11: West Michelleberg | U11: Lake | V11: berg | W11: California | X11: CA | Y11: United States | Z11: US | AA11: 32948 | AB11: 89136 | AC11: burns-ray.com | AD11: perry | AE11: http://brady.info/ | AF11: https://beck.net/app/posts/blogterms.jsp | AG11: wp-content/tag | AH11: main | AI11: jsp | AJ11: 122.68.204.114 | AK11: 216e:9fe5:93f3:7596:8c1c:8b06:5677:1f36 | AL11: a0:f8:af:18:17:32 | AM11: web-70.noble.info | AN11: Opera/9.30.(Windows NT 5.01; ga-IE) Presto/2.9.188 Version/12.00 | AO11: 4141832856914633 | AP11: VISA 16 digit | AQ11: 46108 | AR11: 316 | AS11: USD | AT11: US Dollar | AU11: $ | AV11: 21.516676 | AW11: 47.405221 | AX11: 21.516676,47.405221 | AY11: drop | AZ11: media, pick, may | BA11: Happen federal him spend themselves political. | BB11: Most across practice key. Physical character in rather team. | BC11: before-watch-black | BD11: Role goal investment social easy popular easy over. Expect wait agree suggest then day parent country. | BE11: Cornsilk | BF11: #0445c2 | BG11: text/plain | BH11: science-interest.txt | BI11: .txt | BJ11: 44569 | BK11: 44569 | BL11: 44569 | BM11: 44569 | BN11: 44569.372 | BO11: 44569.372 | BP11: 44569.372 | BQ11: 44569.372 | BR11: 0.37222222 | BS11: 0.3724537 | BT11: 0.37245424 | BU11: 0.37222222 | BV11: 0.3724537 | BW11: 0.37245424 | BX11: 1641632180 | BY11: 1641632180046 | BZ11: 2022 | CA11: 22 | CB11: 1 | CC11: 8 | CD11: Saturday | CE11: 401763.6 | CF11: 401763.62 | CG11: 401763.62 | CH11: 401763.62 | CI11: 6 | CJ11: 60 | CK11: 600 | CL11: 6000 | CM11: 60000 | CN11: 600000 | CO11: 6000000 | CP11: 1111460 | CQ11: 1111460 | CR11: 1110000 | CS11: 1055.7 | CT11: 1055.7 | CU11: 0.9429 | CV11: 0.9429 | CW11: / | CX11: - | CY11: , | CZ11: . | DA11: .
A12: 9bdc70d1-9cbf-4b8c-b410-2d5d1db14bfc | B12: Maxwell Barrett | C12: Gregory | D12: Smith | E12: Mr. | F12: Jr. | G12: hbenton | H12: Scientist, forensic | I12: Green, Watson and Brady | J12: LLC | K12: wiseanthony@example.com | L12: bakertheresa@hotmail.com | M12: crawfordwilliam@porter.com | N12: (224)919-1380x003 | O12: 562-820-8635 | P12: PSC 5419, Box 5180 APO AE 29754 | Q12: 1744 Miller Motorway | R12: Miguel Highway | S12: 493 | T12: Richardsonfort | U12: Port | V12: borough | W12: California | X12: CA | Y12: United States | Z12: US | AA12: 32630 | AB12: 20236 | AC12: randolph.com | AD12: reed | AE12: https://www.bennett.com/ | AF12: http://williams.net/explore/exploresearch.htm | AG12: blog/category | AH12: terms | AI12: html | AJ12: 136.139.125.169 | AK12: 1328:1726:64f4:34d6:d1e9:1692:a320:9116 | AL12: 42:1f:de:42:79:95 | AM12: web-56.decker.com | AN12: Mozilla/5.0 (Windows 98) AppleWebKit/532.0 (KHTML, like Gecko) Chrome/47.0.845.0 Safari/532.0 | AO12: 30325250029217 | AP12: Diners Club / Carte Blanche | AQ12: 02/35 | AR12: 515 | AS12: USD | AT12: US Dollar | AU12: $ | AV12: -74.922522 | AW12: -55.111288 | AX12: -74.922522,-55.111288 | AY12: hotel | AZ12: my, compare, also | BA12: Else spend against ask total kitchen can toward. | BB12: Amount leave collection off. Many him interview government traditional every. Third alone people early far include nearly. | BC12: ask-begin-far | BD12: Current this moment piece soon some. Site grow name machine tree maybe. Conference five despite time sing. Speak line group once. Wind beyond prevent entire staff. | BE12: Black | BF12: #b4157d | BG12: audio/mpeg | BH12: play-discuss-again.mp3 | BI12: .mp3 | BJ12: 40177 | BK12: 40177 | BL12: 40177 | BM12: 40177 | BN12: 40177.659 | BO12: 40177.659 | BP12: 40177.659 | BQ12: 40177.659 | BR12: 0.65902778 | BS12: 0.6593287 | BT12: 0.65933233 | BU12: 0.65902778 | BV12: 0.6593287 | BW12: 0.65933233 | BX12: 1262188166 | BY12: 1262188166313 | BZ12: 2009 | CA12: 9 | CB12: 12 | CC12: 30 | CD12: Wednesday | CE12: 265615.3 | CF12: 265615.29 | CG12: 265615.29 | CH12: 265615.29 | CI12: 7 | CJ12: 70 | CK12: 700 | CL12: 7000 | CM12: 70000 | CN12: 700000 | CO12: 7000000 | CP12: 4138722 | CQ12: 4138722 | CR12: 4140000 | CS12: 3725.2 | CT12: 3725.2 | CU12: 0.539 | CV12: 0.539 | CW12: / | CX12: - | CY12: , | CZ12: . | DA12: .
A13: 6545c030-a981-4a54-b121-e129b45c9a54 | B13: Gabrielle Morris | C13: Theresa | D13: Oconnor | E13: Mrs. | F13: DDS | G13: lbanks | H13: Surveyor, planning and development | I13: Preston, Austin and Kelly | J13: Ltd | K13: nicholasgross@example.com | L13: jessicarush@myers.com | M13: carriemccall@walker.com | N13: 713-655-2157x04331 | O13: 8007676267 | P13: 9327 Lauren Bypass Andrewview, CT 10226 | Q13: 62181 Wheeler Ridges Suite 062 | R13: Moore Courts | S13: 3368 | T13: Donnaport | U13: East | V13: ville | W13: Texas | X13: TX | Y13: United States | Z13: US | AA13: 64850 | AB13: 20632 | AC13: ward.com | AD13: colon-weber | AE13: https://www.johnson.com/ | AF13: http://burns-guerrero.com/categoryprivacy.php | AG13: categories/wp-content/list | AH13: homepage | AI13: html | AJ13: 24.108.235.171 | AK13: 39eb:38a:436e:3c49:770e:9dc:7092:d401 | AL13: aa:89:1f:4d:31:2b | AM13: desktop-86.perez.net | AN13: Opera/8.60.(X11; Linux x86_64; ss-ZA) Presto/2.9.175 Version/11.00 | AO13: 30241406029334 | AP13: Diners Club / Carte Blanche | AQ13: 46052 | AR13: 346 | AS13: USD | AT13: US Dollar | AU13: $ | AV13: -25.055236 | AW13: 19.966569 | AX13: -25.055236,19.966569 | AY13: only | AZ13: however, type, race | BA13: True actually red onto site both change. | BB13: Old who beyond black single size test they. Enough pressure occur list common idea. Participant really although threat former down second TV. | BC13: watch-hotel-again | BD13: Exactly man receive better than. Feel season similar fly. | BE13: SaddleBrown | BF13: #0cf174 | BG13: image/jpeg | BH13: middle-phone-like.jpg | BI13: .jpg | BJ13: 42111 | BK13: 42111 | BL13: 42111 | BM13: 42111 | BN13: 42111.545 | BO13: 42111.545 | BP13: 42111.545 | BQ13: 42111.545 | BR13: 0.54513889 | BS13: 0.54513889 | BT13: 0.54513953 | BU13: 0.54513889 | BV13: 0.54513889 | BW13: 0.54513953 | BX13: 1429275900 | BY13: 1429275900055 | BZ13: 2015 | CA13: 15 | CB13: 4 | CC13: 17 | CD13: Friday | CE13: 997328.5 | CF13: 997328.45 | CG13: 997328.45 | CH13: 997328.45 | CI13: 1 | CJ13: 10 | CK13: 100 | CL13: 1000 | CM13: 10000 | CN13: 100000 | CO13: 1000000 | CP13: 2321821 | CQ13: 2321821 | CR13: 2320000 | CS13: 2548.12 | CT13: 2548.12 | CU13: 0.0909 | CV13: 0.0909 | CW13: / | CX13: - | CY13: , | CZ13: . | DA13: .
A14: c7c1fb1b-dd58-431b-8522-26b983666636 | B14: Melanie Wells | C14: David | D14: Thompson | E14: Mx. | F14: II | G14: jennifer46 | H14: Mudlogger | I14: Stevens-Robinson | J14: LLC | K14: asilva@example.net | L14: kenneth17@gmail.com | M14: vanessa54@douglas-farley.com | N14: 228.930.9652 | O14: 746-566-0993 | P14: 584 Mary Wells Apt. 417 Lake Jonathan, AS 73774 | Q14: 513 Walker Well | R14: Fisher Isle | S14: 4947 | T14: South Brianshire | U14: New | V14: land | W14: Alaska | X14: PP | Y14: United States | Z14: US | AA14: 16205 | AB14: 89721 | AC14: moreno-gutierrez.com | AD14: gay | AE14: https://stewart.com/ | AF14: http://hayes.com/tags/wp-contentabout.html | AG14: posts/tag/posts | AH14: home | AI14: html | AJ14: 155.123.114.233 | AK14: 7a36:e788:f71f:b9a6:6dd4:9c97:6744:cb9e | AL14: f2:c4:02:13:66:bf | AM14: db-58.smith.com | AN14: Mozilla/5.0 (Android 1.5; Mobile; rv:26.0) Gecko/26.0 Firefox/26.0 | AO14: 3558891637562895 | AP14: JCB 16 digit | AQ14: 46080 | AR14: 28 | AS14: USD | AT14: US Dollar | AU14: $ | AV14: -77.659396 | AW14: -145.99672 | AX14: -77.659396,-145.996720 | AY14: prevent | AZ14: turn, both, in | BA14: Memory pay executive size. | BB14: Participant sing story win group. Far always many debate value former. Actually become book. | BC14: painting | BD14: We single avoid rich. Popular lead with enough anyone. Them system growth quality. Believe serve animal system. Forget thus western environmental. Head garden box hundred. | BE14: Purple | BF14: #2e6718 | BG14: application/json | BH14: every-real-former.json | BI14: .json | BJ14: 40583 | BK14: 40583 | BL14: 40583 | BM14: 40583 | BN14: 40583.722 | BO14: 40583.722 | BP14: 40583.722 | BQ14: 40583.722 | BR14: 0.72222222 | BS14: 0.72234954 | BT14: 0.7223519 | BU14: 0.72222222 | BV14: 0.72234954 | BW14: 0.7223519 | BX14: 1297272011 | BY14: 1297272011204 | BZ14: 2011 | CA14: 11 | CB14: 2 | CC14: 9 | CD14: Wednesday | CE14: 792287.3 | CF14: 792287.28 | CG14: 792287.29 | CH14: 792287.28 | CI14: 8 | CJ14: 80 | CK14: 800 | CL14: 8000 | CM14: 80000 | CN14: 800000 | CO14: 8000000 | CP14: 7083668 | CQ14: 7083668 | CR14: 7080000 | CS14: 2982.45 | CT14: 2982.45 | CU14: 0.3848 | CV14: 0.3848 | CW14: / | CX14: - | CY14: , | CZ14: . | DA14: .
A15: 7eef09ab-da14-4a47-b823-51d9d94df188 | B15: Angela Vasquez | C15: John | D15: Cordova | E15: Mr. | F15: II | G15: ppowell | H15: Careers information officer | I15: Wallace-Berry | J15: Inc | K15: hwest@example.com | L15: powellbarry@smith.org | M15: pamela83@powers.com | N15: 375.389.9757 | O15: (330)255-4885 | P15: PSC 7261, Box 4933 APO AE 51998 | Q15: 3516 Sara Villages | R15: Kelsey Mission | S15: 9827 | T15: New Jillside | U15: South | V15: shire | W15: New York | X15: NY | Y15: United States | Z15: US | AA15: 91178 | AB15: 76333 | AC15: cross.com | AD15: sandoval-obrien | AE15: https://petty-moon.com/ | AF15: https://morrison-tanner.net/explore/tagsearch.html | AG15: list/categories | AH15: homepage | AI15: asp | AJ15: 140.219.93.225 | AK15: 4a63:6af5:b6e1:e7ac:9fc9:7265:35af:bb2d | AL15: c2:b0:43:5b:a5:3b | AM15: desktop-87.duncan.net | AN15: Mozilla/5.0 (compatible; MSIE 8.0; Windows NT 10.0; Trident/3.0) | AO15: 588877043582 | AP15: Maestro | AQ15: 46261 | AR15: 128 | AS15: USD | AT15: US Dollar | AU15: $ | AV15: -59.56639 | AW15: 27.165566 | AX15: -59.566390,27.165566 | AY15: trip | AZ15: where, radio, fly | BA15: Home memory someone receive realize another high. | BB15: Whole approach season data than team. Stop treatment relate positive sense national. Cultural right cover large work avoid while same. | BC15: call-huge-amount | BD15: Enough claim suffer accept letter visit always. Others similar personal successful feeling so. | BE15: Sienna | BF15: #ff2337 | BG15: application/pdf | BH15: establish-now-shake.pdf | BI15: .pdf | BJ15: 39445 | BK15: 39445 | BL15: 39445 | BM15: 39445 | BN15: 39445.022 | BO15: 39445.022 | BP15: 39445.023 | BQ15: 39445.023 | BR15: 0.022222222 | BS15: 0.022905093 | BT15: 0.022914734 | BU15: 0.022222222 | BV15: 0.022905093 | BW15: 0.022914734 | BX15: 1198888379 | BY15: 1198888379833 | BZ15: 2007 | CA15: 7 | CB15: 12 | CC15: 29 | CD15: Saturday | CE15: 682028.7 | CF15: 682028.66 | CG15: 682028.66 | CH15: 682028.66 | CI15: 6 | CJ15: 60 | CK15: 600 | CL15: 6000 | CM15: 60000 | CN15: 600000 | CO15: 6000000 | CP15: 9009867 | CQ15: 9009867 | CR15: 9010000 | CS15: 3754.64 | CT15: 3754.64 | CU15: 0.7686 | CV15: 0.7686 | CW15: / | CX15: - | CY15: , | CZ15: . | DA15: .
A16: 10c2c2e5-a07e-4fb1-81e0-6ad888802d4d | B16: Mark Lewis | C16: Gina | D16: Houston | E16: Mr. | F16: PhD | G16: elucas | H16: Designer, exhibition/display | I16: Stevens LLC | J16: Inc | K16: jonesgregory@example.com | L16: rhondarussell@mccoy-hamilton.com | M16: inunez@may.com | N16: 001-890-215-8144x91476 | O16: 628-732-6842 | P16: USS Spencer FPO AP 19031 | Q16: 09968 Kevin Summit | R16: Lewis Rue | S16: 222 | T16: New Mary | U16: East | V16: ville | W16: Alaska | X16: AK | Y16: United States | Z16: US | AA16: 7629 | AB16: 98941 | AC16: murray.com | AD16: garcia-swanson | AE16: https://anderson-rios.com/ | AF16: https://www.jensen-torres.org/tagregister.jsp | AG16: posts | AH16: faq | AI16: php | AJ16: 166.218.88.218 | AK16: 3f05:557c:502e:d818:13c:a999:2b2b:f58c | AL16: ac:71:df:8d:b8:44 | AM16: email-57.griffin-hampton.info | AN16: Mozilla/5.0 (iPod; U; CPU iPhone OS 3_3 like Mac OS X; dv-MV) AppleWebKit/531.12.6 (KHTML, like Gecko) Version/3.0.5 Mobile/8B111 Safari/6531.12.6 | AO16: 6011799088117297 | AP16: Discover | AQ16: 05/35 | AR16: 68 | AS16: USD | AT16: US Dollar | AU16: $ | AV16: -35.682475 | AW16: 100.62851 | AX16: -35.682475,100.628515 | AY16: wrong | AZ16: discover, history, board | BA16: Enough doctor protect military. | BB16: Like lawyer another wonder food region. Plant event score official now heavy her. President structure might heavy trade might good test. | BC16: message-structure | BD16: Maybe catch close. Method exactly change church. Response brother discover specific result loss long decision. Positive improve during campaign. | BE16: Teal | BF16: #43b7a1 | BG16: application/pdf | BH16: trade-where-mother.pdf | BI16: .pdf | BJ16: 40524 | BK16: 40524 | BL16: 40524 | BM16: 40524 | BN16: 40524.433 | BO16: 40524.433 | BP16: 40524.434 | BQ16: 40524.434 | BR16: 0.43333333 | BS16: 0.43386574 | BT16: 0.43386845 | BU16: 0.43333333 | BV16: 0.43386574 | BW16: 0.43386845 | BX16: 1292149486 | BY16: 1292149486234 | BZ16: 2010 | CA16: 10 | CB16: 12 | CC16: 12 | CD16: Sunday | CE16: 454270 | CF16: 454269.98 | CG16: 454269.98 | CH16: 454269.98 | CI16: 9 | CJ16: 90 | CK16: 900 | CL16: 9000 | CM16: 90000 | CN16: 900000 | CO16: 9000000 | CP16: 4419934 | CQ16: 4419934 | CR16: 4420000 | CS16: 4859.47 | CT16: 4859.47 | CU16: 0.762 | CV16: 0.762 | CW16: / | CX16: - | CY16: , | CZ16: . | DA16: .
A17: 0b1ec578-dff4-4c51-9ed1-0e7f6bb1f2bc | B17: Jessica Mays | C17: Timothy | D17: Mack | E17: Dr. | F17: PhD | G17: colemanjonathan | H17: Exhibitions officer, museum/gallery | I17: Campbell PLC | J17: Group | K17: jacob09@example.net | L17: brooksjamie@ortiz-rodriguez.biz | M17: jose86@diaz.com | N17: (488)372-5887x44956 | O17: (237)421-3865 | P17: 27961 Jose Land New Benjaminfurt, MO 80974 | Q17: 902 Gonzales Flats Suite 309 | R17: Christina Spring | S17: 53021 | T17: Kimberlystad | U17: Lake | V17: furt | W17: Alaska | X17: AK | Y17: United States | Z17: US | AA17: 2515 | AB17: 97091 | AC17: jones.net | AD17: bailey | AE17: http://andrews-green.biz/ | AF17: http://www.wright.info/search/explore/postspost.asp | AG17: tag | AH17: privacy | AI17: jsp | AJ17: 129.192.29.38 | AK17: 114b:3c79:4200:79f5:1dc3:c26f:7b62:659e | AL17: f4:c3:70:75:a1:d3 | AM17: desktop-88.haynes.com | AN17: Mozilla/5.0 (compatible; MSIE 5.0; Windows NT 5.01; Trident/5.1) | AO17: 6011125355449645 | AP17: Discover | AQ17: 10/33 | AR17: 598 | AS17: USD | AT17: US Dollar | AU17: $ | AV17: -51.117571 | AW17: -90.03357 | AX17: -51.117571,-90.033570 | AY17: wife | AZ17: high, expert, place | BA17: Share must amount. | BB17: Per manage world to than make. Exactly develop office approach son long must. Girl team simply lead build million firm. | BC17: across-actually | BD17: Ok foot party employee nature down. When gas contain interest industry sell half. Late number without rather sport. Sound new task cultural son. List act instead care. | BE17: LightSkyBlue | BF17: #5ae86e | BG17: application/pdf | BH17: push-system-without.pdf | BI17: .pdf | BJ17: 40413 | BK17: 40413 | BL17: 40413 | BM17: 40413 | BN17: 40413.289 | BO17: 40413.289 | BP17: 40413.289 | BQ17: 40413.289 | BR17: 0.28888889 | BS17: 0.28894676 | BT17: 0.28895566 | BU17: 0.28888889 | BV17: 0.28894676 | BW17: 0.28895566 | BX17: 1282546565 | BY17: 1282546565769 | BZ17: 2010 | CA17: 10 | CB17: 8 | CC17: 23 | CD17: Monday | CE17: 374539.9 | CF17: 374539.94 | CG17: 374539.94 | CH17: 374539.94 | CI17: 9 | CJ17: 90 | CK17: 900 | CL17: 9000 | CM17: 90000 | CN17: 900000 | CO17: 9000000 | CP17: 2711343 | CQ17: 2711343 | CR17: 2710000 | CS17: 2697.36 | CT17: 2697.36 | CU17: 0.7786 | CV17: 0.7786 | CW17: / | CX17: - | CY17: , | CZ17: . | DA17: .
A18: 2ad55c0b-69fb-4fe6-b346-1e07f72cb6c8 | B18: Alexander Luna | C18: Ebony | D18: Shepard | E18: Miss | F18: Jr. | G18: randydavis | H18: Public librarian | I18: Brown, Wise and Warren | J18: Inc | K18: bakereric@example.net | L18: jerome47@hotmail.com | M18: davidroberson@johnson.com | N18: 878.648.7282x9979 | O18: 678-431-7456 | P18: 254 Nichols Spurs Arroyofort, ME 01698 | Q18: 9308 Lopez Points Suite 632 | R18: Clayton Forges | S18: 1638 | T18: Justinside | U18: Port | V18: view | W18: Alabama | X18: AL | Y18: United States | Z18: US | AA18: 24409 | AB18: 18408 | AC18: rodriguez-gibson.info | AD18: graves-vasquez | AE18: https://www.williams.com/ | AF18: http://www.davis.info/search/blogterms.html | AG18: tag | AH18: category | AI18: htm | AJ18: 167.249.109.211 | AK18: b26a:51a5:76b4:672:5f13:e10c:ff7a:884d | AL18: 44:10:a9:29:4a:1c | AM18: web-61.harrison.biz | AN18: Mozilla/5.0 (Linux; Android 4.4) AppleWebKit/531.2 (KHTML, like Gecko) Chrome/23.0.880.0 Safari/531.2 | AO18: 2461228685289758 | AP18: Mastercard | AQ18: 46234 | AR18: 855 | AS18: USD | AT18: US Dollar | AU18: $ | AV18: 77.859414 | AW18: -83.954926 | AX18: 77.859414,-83.954926 | AY18: benefit | AZ18: country, moment, eat | BA18: Art green child movie blue maintain first next. | BB18: Run again help right economy always. Next my majority note myself food. Every story trial never attention choice fast. | BC18: everyone-number-hit | BD18: Here control affect task simply draw return. Couple raise she child executive important. Book model at strong candidate them. Blood court all politics home. | BE18: Crimson | BF18: #f1d189 | BG18: image/png | BH18: open-so-open-just.png | BI18: .png | BJ18: 36997 | BK18: 36997 | BL18: 36997 | BM18: 36997 | BN18: 36997.681 | BO18: 36997.681 | BP18: 36997.681 | BQ18: 36997.681 | BR18: 0.68055556 | BS18: 0.68114583 | BT18: 0.68114821 | BU18: 0.68055556 | BV18: 0.68114583 | BW18: 0.68114821 | BX18: 987438051 | BY18: 987438051205 | BZ18: 2001 | CA18: 1 | CB18: 4 | CC18: 16 | CD18: Monday | CE18: 112755.9 | CF18: 112755.86 | CG18: 112755.86 | CH18: 112755.86 | CI18: 5 | CJ18: 50 | CK18: 500 | CL18: 5000 | CM18: 50000 | CN18: 500000 | CO18: 5000000 | CP18: 6090806 | CQ18: 6090806 | CR18: 6090000 | CS18: 4393.73 | CT18: 4393.73 | CU18: 0.8317 | CV18: 0.8317 | CW18: / | CX18: - | CY18: , | CZ18: . | DA18: .
A19: 6e3b0507-a21c-4209-83a1-962d698f546d | B19: Erica Allen | C19: Amy | D19: Brooks | E19: Mrs. | F19: DDS | G19: suzanne76 | H19: Academic librarian | I19: Johnson, Mitchell and Smith | J19: and Sons | K19: adam33@example.com | L19: samantha88@howe.com | M19: devonrichardson@wright.org | N19: (893)315-7279x1940 | O19: 8552661390 | P19: 8925 Eric Spring Maddoxshire, NY 12308 | Q19: 4622 Miller Ports | R19: Amy Greens | S19: 68622 | T19: Hansenfort | U19: South | V19: shire | W19: California | X19: CA | Y19: United States | Z19: US | AA19: 69215 | AB19: 32776 | AC19: jones.com | AD19: glass | AE19: https://lee-cooper.com/ | AF19: https://www.williams-meyers.com/tags/exploreregister.html | AG19: category/posts/list | AH19: home | AI19: html | AJ19: 114.92.226.162 | AK19: 49a5:baeb:d1f4:4c8d:d51b:1975:de66:8dd0 | AL19: 78:07:af:38:9c:e6 | AM19: db-53.medina.com | AN19: Mozilla/5.0 (Windows; U; Windows NT 4.0) AppleWebKit/534.40.6 (KHTML, like Gecko) Version/4.0.1 Safari/534.40.6 | AO19: 4279757366096569 | AP19: VISA 16 digit | AQ19: 12/35 | AR19: 988 | AS19: USD | AT19: US Dollar | AU19: $ | AV19: -85.969642 | AW19: -35.120713 | AX19: -85.969642,-35.120713 | AY19: might | AZ19: cover, allow, share | BA19: Green few you without every artist. | BB19: Three spring ahead never exactly charge. Prevent because him whether partner personal. | BC19: dream-key-effect | BD19: Wife travel forget my deal catch. Range dark catch read together travel involve. True fish newspaper we brother fish they. She they increase. | BE19: SeaShell | BF19: #b646e3 | BG19: text/plain | BH19: itself-doctor.txt | BI19: .txt | BJ19: 38667 | BK19: 38667 | BL19: 38667 | BM19: 38667 | BN19: 38667.456 | BO19: 38667.456 | BP19: 38667.457 | BQ19: 38667.457 | BR19: 0.45625 | BS19: 0.45662037 | BT19: 0.45662823 | BU19: 0.45625 | BV19: 0.45662037 | BW19: 0.45662823 | BX19: 1131706652 | BY19: 1131706652679 | BZ19: 2005 | CA19: 5 | CB19: 11 | CC19: 11 | CD19: Friday | CE19: 732175.7 | CF19: 732175.69 | CG19: 732175.69 | CH19: 732175.69 | CI19: 3 | CJ19: 30 | CK19: 300 | CL19: 3000 | CM19: 30000 | CN19: 300000 | CO19: 3000000 | CP19: 1162193 | CQ19: 1162193 | CR19: 1160000 | CS19: 4889.94 | CT19: 4889.94 | CU19: 0.5327 | CV19: 0.5327 | CW19: / | CX19: - | CY19: , | CZ19: . | DA19: .
A20: c9739495-b440-4852-a033-500ea43262b3 | B20: Brian Bryant | C20: Natalie | D20: Rich | E20: Mr. | F20: MD | G20: grantzachary | H20: Artist | I20: Carter Group | J20: LLC | K20: steven64@example.net | L20: stevenlucas@sharp.com | M20: phillipmorris@white.com | N20: 814.452.1117x518 | O20: 486-402-5922 | P20: 4474 David Curve North Cindy, KS 02101 | Q20: 7809 Young Radial Suite 767 | R20: Carolyn Avenue | S20: 84983 | T20: East Eddiestad | U20: North | V20: berg | W20: Arizona | X20: AZ | Y20: United States | Z20: US | AA20: 39618 | AB20: 43900 | AC20: williams.com | AD20: powers | AE20: http://riley.com/ | AF20: https://carter.com/posts/postsauthor.asp | AG20: list/search/category | AH20: main | AI20: htm | AJ20: 134.254.206.207 | AK20: a104:bdce:fab6:ad91:bacf:7cfd:9245:1cc4 | AL20: 42:2c:f7:93:da:a2 | AM20: lt-99.ho-mendez.info | AN20: Mozilla/5.0 (Macintosh; Intel Mac OS X 10_12_1 rv:3.0; fur-IT) AppleWebKit/534.32.7 (KHTML, like Gecko) Version/4.1 Safari/534.32.7 | AO20: 5409881385854244 | AP20: Mastercard | AQ20: 12/35 | AR20: 321 | AS20: USD | AT20: US Dollar | AU20: $ | AV20: -13.075155 | AW20: -31.474911 | AX20: -13.075155,-31.474911 | AY20: these | AZ20: police, decide, customer | BA20: Population loss physical. | BB20: Leg sport until argue minute north. New affect officer forward trouble somebody. Wide exactly all worker. | BC20: produce-nor | BD20: Paper cost bring site final tax report. Including market down later week. Few born size sing tree kitchen agent. Toward child future low them financial force. | BE20: SeaGreen | BF20: #e3a1b0 | BG20: audio/mpeg | BH20: no-from-spring-let.mp3 | BI20: .mp3 | BJ20: 43245 | BK20: 43245 | BL20: 43245 | BM20: 43245 | BN20: 43245.094 | BO20: 43245.094 | BP20: 43245.095 | BQ20: 43245.095 | BR20: 0.094444444 | BS20: 0.094895833 | BT20: 0.094905683 | BU20: 0.094444444 | BV20: 0.094895833 | BW20: 0.094905683 | BX20: 1527214599 | BY20: 1527214599851 | BZ20: 2018 | CA20: 18 | CB20: 5 | CC20: 25 | CD20: Friday | CE20: 528146.1 | CF20: 528146.11 | CG20: 528146.11 | CH20: 528146.11 | CI20: 4 | CJ20: 40 | CK20: 400 | CL20: 4000 | CM20: 40000 | CN20: 400000 | CO20: 4000000 | CP20: 7100076 | CQ20: 7100076 | CR20: 7100000 | CS20: 4821.85 | CT20: 4821.85 | CU20: 0.9289 | CV20: 0.9289 | CW20: / | CX20: - | CY20: , | CZ20: . | DA20: .
A21: 56b7979e-e46a-4b42-9cfe-cbd84fb67094 | B21: Amber Johnson | C21: Rebecca | D21: Williams | E21: Dr. | F21: Jr. | G21: mwhite | H21: Therapist, drama | I21: Huff, Lyons and Jensen | J21: LLC | K21: lisa81@example.com | L21: hesssamantha@davis-collins.info | M21: ohall@callahan.com | N21: (962)955-7701x715 | O21: 3457992816 | P21: 8769 Allen Gardens South Patrick, MA 27795 | Q21: 9583 Elaine Club Suite 199 | R21: Nguyen Court | S21: 2461 | T21: Lake Lisafurt | U21: West | V21: fort | W21: Colorado | X21: CO | Y21: United States | Z21: US | AA21: 29023 | AB21: 18709 | AC21: berger.com | AD21: hernandez | AE21: https://www.maldonado.com/ | AF21: https://abbott-phelps.com/explore/category/mainindex.asp | AG21: list/explore | AH21: index | AI21: asp | AJ21: 174.223.187.166 | AK21: dd9d:2e4d:483e:dd69:dc7a:bd17:1c15:3057 | AL21: b6:0f:78:dd:c9:a2 | AM21: laptop-66.gardner-bates.info | AN21: Mozilla/5.0 (Windows NT 10.0; ms-MY; rv:1.9.2.20) Gecko/4480-10-31 12:31:56 Firefox/3.8 | AO21: 2439385258001066 | AP21: Mastercard | AQ21: 46353 | AR21: 817 | AS21: USD | AT21: US Dollar | AU21: $ | AV21: -16.82702 | AW21: -0.165743 | AX21: -16.827020,-0.165743 | AY21: behavior | AZ21: what, it, truth | BA21: Range much often party. | BB21: Sing light mention light safe inside whether. Eye along type see risk. Employee picture official of prevent factor say. | BC21: agreement-few | BD21: Measure surface everyone car. Every either scientist page travel. Have compare site door Congress month almost. Whose other start study. | BE21: RosyBrown | BF21: #61cb06 | BG21: image/jpeg | BH21: expect-example.jpg | BI21: .jpg | BJ21: 46052 | BK21: 46052 | BL21: 46052 | BM21: 46052 | BN21: 46052.967 | BO21: 46052.967 | BP21: 46052.967 | BQ21: 46052.967 | BR21: 0.96666667 | BS21: 0.96710648 | BT21: 0.96711275 | BU21: 0.96666667 | BV21: 0.96710648 | BW21: 0.96711275 | BX21: 1769814758 | BY21: 1769814758542 | BZ21: 2026 | CA21: 26 | CB21: 1 | CC21: 30 | CD21: Friday | CE21: 438662 | CF21: 438661.98 | CG21: 438661.98 | CH21: 438661.98 | CI21: 2 | CJ21: 20 | CK21: 200 | CL21: 2000 | CM21: 20000 | CN21: 200000 | CO21: 2000000 | CP21: 8684481 | CQ21: 8684481 | CR21: 8680000 | CS21: 2257.98 | CT21: 2257.98 | CU21: 0.2479 | CV21: 0.2479 | CW21: / | CX21: - | CY21: , | CZ21: . | DA21: .
A22: 4886274c-b9aa-46f5-b82b-ab1159fcfaeb | B22: Andrew Harvey | C22: Brian | D22: Wheeler | E22: Mx. | F22: II | G22: ericksondavid | H22: Trade union research officer | I22: Bennett Ltd | J22: PLC | K22: pauladominguez@example.com | L22: eguerrero@hotmail.com | M22: rlivingston@schwartz-contreras.com | N22: 921-340-6650x442 | O22: 839-562-7128 | P22: 4101 Ashley Glen Smithfort, FL 86073 | Q22: 64256 Zachary Trail | R22: Mendoza Lodge | S22: 183 | T22: South Stephaniefort | U22: North | V22: shire | W22: Florida | X22: FL | Y22: United States | Z22: US | AA22: 40193 | AB22: 53010 | AC22: chen.com | AD22: nichols-woodward | AE22: http://holland-thompson.com/ | AF22: https://www.miller-chen.com/blog/listabout.php | AG22: app | AH22: main | AI22: html | AJ22: 183.161.171.145 | AK22: caf0:f442:1020:48e6:6386:44e1:7d3e:5830 | AL22: 56:9d:ff:e6:08:12 | AM22: db-50.wilson-roman.net | AN22: Opera/8.28.(X11; Linux i686; sv-FI) Presto/2.9.189 Version/10.00 | AO22: 4137995635315319 | AP22: VISA 16 digit | AQ22: 46111 | AR22: 636 | AS22: USD | AT22: US Dollar | AU22: $ | AV22: 31.640891 | AW22: -156.7441 | AX22: 31.640891,-156.744104 | AY22: last | AZ22: decide, edge, pattern | BA22: Food wish office case student soldier. | BB22: Community as event serious collection have close during. | BC22: party-amount-cell | BD22: Heavy citizen they ball account unit religious order. Indicate southern significant realize deal. Mission include visit particular also. Response partner because step. | BE22: Sienna | BF22: #7f5d22 | BG22: text/plain | BH22: body-sit-area-wish.txt | BI22: .txt | BJ22: 36686 | BK22: 36686 | BL22: 36686 | BM22: 36686 | BN22: 36686.078 | BO22: 36686.078 | BP22: 36686.078 | BQ22: 36686.078 | BR22: 0.077777778 | BS22: 0.07787037 | BT22: 0.077874699 | BU22: 0.077777778 | BV22: 0.07787037 | BW22: 0.077874699 | BX22: 960515528 | BY22: 960515528374 | BZ22: 2000 | CA22: 0 | CB22: 6 | CC22: 9 | CD22: Friday | CE22: 71922.1 | CF22: 71922.09 | CG22: 71922.093 | CH22: 71922.09 | CI22: 6 | CJ22: 60 | CK22: 600 | CL22: 6000 | CM22: 60000 | CN22: 600000 | CO22: 6000000 | CP22: 988737 | CQ22: 988737 | CR22: 989000 | CS22: 1145.48 | CT22: 1145.48 | CU22: 0.9054 | CV22: 0.9054 | CW22: / | CX22: - | CY22: , | CZ22: . | DA22: .
A23: 7892d145-12d2-47e6-b87d-5adde43081aa | B23: Amy Graham | C23: Javier | D23: Lynch | E23: Mr. | F23: MD | G23: ocortez | H23: Mechanical engineer | I23: Harris-Martinez | J23: Ltd | K23: ramirezdaniel@example.com | L23: vjackson@gmail.com | M23: cassandra92@cordova.net | N23: 539.477.4063x3569 | O23: (806)900-7806 | P23: 7318 Heather Lodge East Michael, IA 85388 | Q23: 74279 Tiffany Mountain | R23: Morgan Lodge | S23: 57016 | T23: Alyssaport | U23: South | V23: view | W23: Alaska | X23: AK | Y23: United States | Z23: US | AA23: 27652 | AB23: 90241 | AC23: oliver.com | AD23: dougherty | AE23: http://marshall-williams.com/ | AF23: http://www.banks.org/blog/wp-content/exploremain.asp | AG23: wp-content/blog/wp-content | AH23: homepage | AI23: htm | AJ23: 14.196.81.84 | AK23: 5f70:b951:1038:f676:df1:172b:46f2:ff38 | AL23: b4:b0:e7:f8:3e:f0 | AM23: lt-84.oliver-marsh.com | AN23: Mozilla/5.0 (Android 4.0.1; Mobile; rv:47.0) Gecko/47.0 Firefox/47.0 | AO23: 4049478730024471 | AP23: VISA 16 digit | AQ23: 46140 | AR23: 462 | AS23: USD | AT23: US Dollar | AU23: $ | AV23: 34.049383 | AW23: 124.89776 | AX23: 34.049383,124.897755 | AY23: color | AZ23: police, event, company | BA23: Kid hard day religious. | BB23: Challenge large wish move building agent. Shoulder way until choose wife national medical. Listen face want wonder off. | BC23: choice-successful | BD23: Ready rule too cause nearly final. Pay detail group for part crime. Develop very everyone against Mrs knowledge public. Hour make owner memory argue project huge. Hard health expect goal within them. | BE23: Violet | BF23: #fc9455 | BG23: video/mp4 | BH23: someone-who-certain.mp4 | BI23: .mp4 | BJ23: 43596 | BK23: 43596 | BL23: 43596 | BM23: 43596 | BN23: 43596.689 | BO23: 43596.689 | BP23: 43596.69 | BQ23: 43596.69 | BR23: 0.68888889 | BS23: 0.68956019 | BT23: 0.689562 | BU23: 0.68888889 | BV23: 0.68956019 | BW23: 0.689562 | BX23: 1557592378 | BY23: 1557592378157 | BZ23: 2019 | CA23: 19 | CB23: 5 | CC23: 11 | CD23: Saturday | CE23: 669308.8 | CF23: 669308.8 | CG23: 669308.8 | CH23: 669308.8 | CI23: 8 | CJ23: 80 | CK23: 800 | CL23: 8000 | CM23: 80000 | CN23: 800000 | CO23: 8000000 | CP23: 3595297 | CQ23: 3595297 | CR23: 3600000 | CS23: 2696.63 | CT23: 2696.63 | CU23: 0.7234 | CV23: 0.7234 | CW23: / | CX23: - | CY23: , | CZ23: . | DA23: .
A24: a510af65-b016-4db8-a823-99437dec4605 | B24: Bryan Ramirez | C24: Virginia | D24: Jones | E24: Mx. | F24: MD | G24: ooneill | H24: Publishing copy | I24: Cardenas, Brooks and Quinn | J24: Inc | K24: francisco02@example.com | L24: michaelbrown@yahoo.com | M24: wfields@roberts.com | N24: 732.419.2855x44518 | O24: 3285457652 | P24: 89888 Robert Club Port Davidtown, NJ 46141 | Q24: 527 Jackson Hollow Apt. 132 | R24: Hailey Inlet | S24: 32161 | T24: North Kimchester | U24: North | V24: borough | W24: California | X24: CA | Y24: United States | Z24: US | AA24: 67803 | AB24: 78249 | AC24: harrison.com | AD24: turner | AE24: http://www.harris.com/ | AF24: http://www.martin-mason.org/explorepost.php | AG24: blog | AH24: faq | AI24: html | AJ24: 64.229.30.112 | AK24: 3109:4211:b73f:6e64:378d:2f8e:8761:f9da | AL24: ea:90:57:02:32:6d | AM24: lt-75.lawrence.com | AN24: Mozilla/5.0 (compatible; MSIE 8.0; Windows NT 5.01; Trident/3.0) | AO24: 630416756777 | AP24: Maestro | AQ24: 46321 | AR24: 28 | AS24: USD | AT24: US Dollar | AU24: $ | AV24: 55.609623 | AW24: 4.477244 | AX24: 55.609623,4.477244 | AY24: involve | AZ24: family, marriage, measure | BA24: Thus sort voice happen. | BB24: Public how mission put budget house reason. | BC24: blue-site-wish-wait | BD24: Window full organization wrong but study. Everything require old event smile popular hundred. | BE24: DeepSkyBlue | BF24: #4d8132 | BG24: audio/mpeg | BH24: table-trade-now.mp3 | BI24: .mp3 | BJ24: 46905 | BK24: 46905 | BL24: 46905 | BM24: 46905 | BN24: 46905.876 | BO24: 46905.876 | BP24: 46905.877 | BQ24: 46905.877 | BR24: 0.87638889 | BS24: 0.87696759 | BT24: 0.87697663 | BU24: 0.87638889 | BV24: 0.87696759 | BW24: 0.87697663 | BX24: 1843506170 | BY24: 1843506170781 | BZ24: 2028 | CA24: 28 | CB24: 6 | CC24: 1 | CD24: Thursday | CE24: 191219.5 | CF24: 191219.5 | CG24: 191219.5 | CH24: 191219.5 | CI24: 7 | CJ24: 70 | CK24: 700 | CL24: 7000 | CM24: 70000 | CN24: 700000 | CO24: 7000000 | CP24: 1627229 | CQ24: 1627229 | CR24: 1630000 | CS24: 3295.25 | CT24: 3295.25 | CU24: 0.3543 | CV24: 0.3543 | CW24: / | CX24: - | CY24: , | CZ24: . | DA24: .
A25: 4d945434-c785-4c05-9c40-9942a8cf2936 | B25: Carly Jordan | C25: Larry | D25: Price | E25: Mx. | F25: MD | G25: rkeller | H25: Solicitor, Scotland | I25: Harrison, Hart and Moore | J25: Inc | K25: lbaker@example.com | L25: luke09@gmail.com | M25: marybailey@silva.biz | N25: 565-656-5033 | O25: (711)241-5208 | P25: 864 Heather Radial Apt. 569 Morrisville, AS 64511 | Q25: 357 Jackson Hills | R25: Montes Flats | S25: 1834 | T25: Brandonshire | U25: South | V25: bury | W25: Illinois | X25: IL | Y25: United States | Z25: US | AA25: 76285 | AB25: 12917 | AC25: rogers.info | AD25: clark-flynn | AE25: https://alvarado-edwards.biz/ | AF25: https://ray.info/categories/blog/categoriesindex.asp | AG25: explore/categories | AH25: faq | AI25: php | AJ25: 204.122.163.60 | AK25: 7665:8707:5d41:1ac5:335d:ab47:85b3:75aa | AL25: 68:4b:7b:4d:99:de | AM25: desktop-13.adams-mitchell.com | AN25: Mozilla/5.0 (compatible; MSIE 9.0; Windows CE; Trident/4.0) | AO25: 3570027206345917 | AP25: JCB 16 digit | AQ25: 46050 | AR25: 238 | AS25: USD | AT25: US Dollar | AU25: $ | AV25: -46.95816 | AW25: -39.89276 | AX25: -46.958160,-39.892760 | AY25: play | AZ25: response, theory, star | BA25: Public though however style successful door. | BB25: Usually miss stock wear use edge this. Outside significant finish strategy say. Very design blood degree ever. | BC25: issue-environmental | BD25: Make hear we first. Little east everyone six certain little. Start again whom paper success production. Real small dream. | BE25: PaleTurquoise | BF25: #ca10b5 | BG25: text/plain | BH25: move-attorney-he.txt | BI25: .txt | BJ25: 38071 | BK25: 38071 | BL25: 38071 | BM25: 38071 | BN25: 38071.91 | BO25: 38071.91 | BP25: 38071.911 | BQ25: 38071.911 | BR25: 0.91041667 | BS25: 0.91072917 | BT25: 0.91073757 | BU25: 0.91041667 | BV25: 0.91072917 | BW25: 0.91073757 | BX25: 1080251487 | BY25: 1080251487726 | BZ25: 2004 | CA25: 4 | CB25: 3 | CC25: 25 | CD25: Thursday | CE25: 403218.7 | CF25: 403218.66 | CG25: 403218.66 | CH25: 403218.66 | CI25: 4 | CJ25: 40 | CK25: 400 | CL25: 4000 | CM25: 40000 | CN25: 400000 | CO25: 4000000 | CP25: 5693553 | CQ25: 5693553 | CR25: 5690000 | CS25: 4003.16 | CT25: 4003.16 | CU25: 0.1093 | CV25: 0.1093 | CW25: / | CX25: - | CY25: , | CZ25: . | DA25: .
A26: d4a39a51-c481-4a69-b83b-f029b6ac2048 | B26: Beverly Wheeler | C26: Robert | D26: Ayers | E26: Mrs. | F26: PhD | G26: jorgemcdaniel | H26: Land | I26: Gonzalez-Perry | J26: and Sons | K26: kwalter@example.org | L26: leblancdeborah@perez.com | M26: brandonwilliamson@green.org | N26: 508-667-7133 | O26: 576-826-3934 | P26: 44397 Mike Spur Millerfort, DC 42869 | Q26: 366 Jones Point Apt. 053 | R26: Odonnell Rest | S26: 900 | T26: Williamfurt | U26: West | V26: furt | W26: California | X26: CA | Y26: United States | Z26: US | AA26: 5891 | AB26: 76586 | AC26: green.info | AD26: humphrey-anderson | AE26: https://green.com/ | AF26: http://gallegos.biz/blog/explorepost.htm | AG26: tag | AH26: terms | AI26: jsp | AJ26: 180.215.41.42 | AK26: a84c:a488:ec40:14c6:da60:69f4:8e40:b294 | AL26: 3a:e1:1b:60:4c:1b | AM26: srv-07.martin-mcdonald.com | AN26: Opera/8.28.(Windows NT 5.1; ln-CD) Presto/2.9.174 Version/11.00 | AO26: 2422601645977944 | AP26: Mastercard | AQ26: 01/32 | AR26: 232 | AS26: USD | AT26: US Dollar | AU26: $ | AV26: 62.599706 | AW26: -43.96747 | AX26: 62.599706,-43.967470 | AY26: indeed | AZ26: interesting, behind, produce | BA26: Child ball store process law western. | BB26: Forget analysis performance. Foot rule same whatever notice deep any. Follow area audience weight high. Effort drive side human after decade. | BC26: important-state | BD26: Building make it south. Tough page grow benefit happen. Knowledge hold environmental outside bed institution happy. Its international American game. | BE26: Pink | BF26: #4ba4b0 | BG26: video/mp4 | BH26: hear-environmental.mp4 | BI26: .mp4 | BJ26: 40077 | BK26: 40077 | BL26: 40077 | BM26: 40077 | BN26: 40077.729 | BO26: 40077.729 | BP26: 40077.73 | BQ26: 40077.73 | BR26: 0.72916667 | BS26: 0.72983796 | BT26: 0.72984441 | BU26: 0.72916667 | BV26: 0.72983796 | BW26: 0.72984441 | BX26: 1253554258 | BY26: 1253554258557 | BZ26: 2009 | CA26: 9 | CB26: 9 | CC26: 21 | CD26: Monday | CE26: 422459.8 | CF26: 422459.76 | CG26: 422459.76 | CH26: 422459.76 | CI26: 2 | CJ26: 20 | CK26: 200 | CL26: 2000 | CM26: 20000 | CN26: 200000 | CO26: 2000000 | CP26: 4674212 | CQ26: 4674212 | CR26: 4670000 | CS26: 2313.68 | CT26: 2313.68 | CU26: 0.8745 | CV26: 0.8745 | CW26: / | CX26: - | CY26: , | CZ26: . | DA26: .
A27: 9aa33580-fb70-4dd7-bf3d-5023140642a8 | B27: Michael Hamilton | C27: Andrew | D27: Foster | E27: Mr. | F27: DDS | G27: qholt | H27: Town planner | I27: Tucker, Montgomery and Dickson | J27: LLC | K27: fballard@example.org | L27: leelisa@waller.com | M27: ryangarrett@lee.info | N27: (801)222-7770x79334 | O27: 601-266-7998 | P27: 997 Jennifer Pines Apt. 695 West Patriciachester, FM 62542 | Q27: 9576 Evan Stream | R27: Taylor Mill | S27: 83959 | T27: Andersonport | U27: Lake | V27: furt | W27: Illinois | X27: IL | Y27: United States | Z27: US | AA27: 86025 | AB27: 96784 | AC27: flynn-marsh.com | AD27: clark | AE27: https://www.gonzalez.info/ | AF27: http://ibarra-kelly.com/search/wp-contentindex.html | AG27: blog | AH27: index | AI27: html | AJ27: 39.75.69.220 | AK27: 8fde:42a:1ee5:6930:3a08:5f6b:9e18:9a98 | AL27: c4:72:f9:84:ae:b5 | AM27: db-84.castaneda.org | AN27: Mozilla/5.0 (Macintosh; Intel Mac OS X 10_8_5) AppleWebKit/536.0 (KHTML, like Gecko) Chrome/23.0.893.0 Safari/536.0 | AO27: 4449268315893572 | AP27: VISA 16 digit | AQ27: 46353 | AR27: 266 | AS27: USD | AT27: US Dollar | AU27: $ | AV27: 66.120402 | AW27: 123.6527 | AX27: 66.120402,123.652696 | AY27: job | AZ27: law, work, south | BA27: Some gun ahead certainly act south want. | BB27: Fire word clearly article service produce. Total around place require. | BC27: recent-type-nature | BD27: Though red them return finish general. Too particular chair identify popular. Person peace kind generation speech possible simple. Already free rise science. Minute must degree memory. | BE27: Tan | BF27: #5abec4 | BG27: video/mp4 | BH27: send-wall-writer.mp4 | BI27: .mp4 | BJ27: 37773 | BK27: 37773 | BL27: 37773 | BM27: 37773 | BN27: 37773.624 | BO27: 37773.624 | BP27: 37773.624 | BQ27: 37773.624 | BR27: 0.62361111 | BS27: 0.62380787 | BT27: 0.62381006 | BU27: 0.62361111 | BV27: 0.62380787 | BW27: 0.62381006 | BX27: 1054479497 | BY27: 1054479497189 | BZ27: 2003 | CA27: 3 | CB27: 6 | CC27: 1 | CD27: Sunday | CE27: 652492.7 | CF27: 652492.75 | CG27: 652492.75 | CH27: 652492.75 | CI27: 4 | CJ27: 40 | CK27: 400 | CL27: 4000 | CM27: 40000 | CN27: 400000 | CO27: 4000000 | CP27: 9070560 | CQ27: 9070560 | CR27: 9070000 | CS27: 4180.3 | CT27: 4180.3 | CU27: 0.969 | CV27: 0.969 | CW27: / | CX27: - | CY27: , | CZ27: . | DA27: .
A28: 6cc56071-0feb-4cad-979d-9ae314fa7d50 | B28: Karen Griffin | C28: Mike | D28: Fox | E28: Mrs. | F28: MD | G28: lwiggins | H28: Research scientist (physical sciences) | I28: Henderson, Alexander and Galvan | J28: Group | K28: jcolon@example.net | L28: idawson@palmer.info | M28: kjohnson@wood.biz | N28: 715-694-0821 | O28: 244-670-2296 | P28: 70185 Monica Mall Berryshire, NV 44780 | Q28: 9228 Gill Shores Suite 251 | R28: Hughes Locks | S28: 8074 | T28: Port Gabrieltown | U28: New | V28: port | W28: Arizona | X28: AZ | Y28: United States | Z28: US | AA28: 73816 | AB28: 11662 | AC28: friedman.org | AD28: bernard | AE28: http://prince.com/ | AF28: http://roman.com/searchauthor.jsp | AG28: tags/tag | AH28: index | AI28: php | AJ28: 29.71.40.192 | AK28: 513f:f9a9:8724:91ca:dc11:eb14:628:9878 | AL28: 8a:c3:83:2e:3a:32 | AM28: srv-42.scott.com | AN28: Mozilla/5.0 (compatible; MSIE 8.0; Windows NT 6.1; Trident/3.0) | AO28: 6011807156956205 | AP28: Discover | AQ28: 46140 | AR28: 753 | AS28: USD | AT28: US Dollar | AU28: $ | AV28: 20.907606 | AW28: 118.38783 | AX28: 20.907606,118.387832 | AY28: ask | AZ28: live, top, pull | BA28: Imagine do though. | BB28: White push east never size fight image. Suffer matter situation central. | BC28: now-concern-station | BD28: Which new among spend which per. A value lot our. Yourself successful defense subject example claim. | BE28: HoneyDew | BF28: #75b569 | BG28: image/jpeg | BH28: want-same-score.jpg | BI28: .jpg | BJ28: 48778 | BK28: 48778 | BL28: 12253 | BM28: 12253 | BN28: 48778.867 | BO28: 48778.867 | BP28: 48778.868 | BQ28: 48778.868 | BR28: 0.86736111 | BS28: 0.86767361 | BT28: 0.86768027 | BU28: 0.86736111 | BV28: 0.86767361 | BW28: 0.86768027 | BX28: 2005332567 | BY28: 2005332567575 | BZ28: 2033 | CA28: 33 | CB28: 7 | CC28: 18 | CD28: Monday | CE28: 214533.6 | CF28: 214533.55 | CG28: 214533.55 | CH28: 214533.55 | CI28: 1 | CJ28: 10 | CK28: 100 | CL28: 1000 | CM28: 10000 | CN28: 100000 | CO28: 1000000 | CP28: 6729339 | CQ28: 6729339 | CR28: 6730000 | CS28: 4512.31 | CT28: 4512.31 | CU28: 0.1646 | CV28: 0.1646 | CW28: / | CX28: - | CY28: , | CZ28: . | DA28: .
A29: be3eb6f7-38b5-45b9-8265-a22371cfd772 | B29: Douglas Morse | C29: Michael | D29: Davis | E29: Mrs. | F29: MD | G29: jimsnyder | H29: Medical laboratory scientific officer | I29: Campbell Ltd | J29: Ltd | K29: adrianjoyce@example.net | L29: kaneashley@yahoo.com | M29: andreakeller@chambers.org | N29: (212)649-3843 | O29: (687)306-0566 | P29: 5803 Joshua Manor Suite 506 West Christopher, OK 03826 | Q29: 613 Frank Inlet | R29: Connie Court | S29: 76095 | T29: Johnfort | U29: East | V29: mouth | W29: Georgia | X29: GA | Y29: United States | Z29: US | AA29: 31531 | AB29: 10057 | AC29: harvey.org | AD29: miller | AE29: http://wu-steele.com/ | AF29: http://garcia.net/categoryfaq.php | AG29: category | AH29: author | AI29: php | AJ29: 58.79.151.243 | AK29: c997:f2fa:997d:cd9a:dd55:4b7e:3bad:3a0d | AL29: e0:05:e8:c4:ed:db | AM29: lt-91.curtis-lowe.com | AN29: Opera/8.86.(X11; Linux x86_64; szl-PL) Presto/2.9.163 Version/10.00 | AO29: 213104289731799 | AP29: JCB 15 digit | AQ29: 46139 | AR29: 286 | AS29: USD | AT29: US Dollar | AU29: $ | AV29: -24.354207 | AW29: -155.19915 | AX29: -24.354207,-155.199147 | AY29: stand | AZ29: hear, outside, with | BA29: Hard account only question arm. | BB29: Teach instead crime customer training size game. Reason word outside former official white pattern. Forget bit then treat many turn. | BC29: purpose-dog-room | BD29: Defense lose shoulder spring southern heavy hundred step. Guy available air. Central key place tree. Wish current exist. Those responsibility fund never condition. Compare energy big. | BE29: Coral | BF29: #1e5595 | BG29: application/pdf | BH29: source-power-people.pdf | BI29: .pdf | BJ29: 48097 | BK29: 48097 | BL29: 11572 | BM29: 11572 | BN29: 48097.811 | BO29: 48097.811 | BP29: 48097.812 | BQ29: 48097.812 | BR29: 0.81111111 | BS29: 0.81153935 | BT29: 0.81154608 | BU29: 0.81111111 | BV29: 0.81153935 | BW29: 0.81154608 | BX29: 1946489317 | BY29: 1946489317581 | BZ29: 2031 | CA29: 31 | CB29: 9 | CC29: 6 | CD29: Saturday | CE29: 285964 | CF29: 285963.98 | CG29: 285963.98 | CH29: 285963.98 | CI29: 4 | CJ29: 40 | CK29: 400 | CL29: 4000 | CM29: 40000 | CN29: 400000 | CO29: 4000000 | CP29: 9325245 | CQ29: 9325245 | CR29: 9330000 | CS29: 3309.69 | CT29: 3309.69 | CU29: 0.4867 | CV29: 0.4867 | CW29: / | CX29: - | CY29: , | CZ29: . | DA29: .
A30: c04a7761-a523-48e3-a1e6-69e5c055b921 | B30: Kathleen Marshall | C30: Marc | D30: Brooks | E30: Miss | F30: DDS | G30: lwells | H30: Oncologist | I30: Morse, Silva and Johnson | J30: and Sons | K30: shannonyoung@example.org | L30: koneal@gmail.com | M30: jonathan12@phillips.com | N30: 990.878.9567 | O30: 557-654-6027 | P30: 48881 House Courts Apt. 150 West James, MA 33272 | Q30: 439 Yesenia Terrace Suite 044 | R30: Logan Lodge | S30: 9078 | T30: Port Raymond | U30: East | V30: borough | W30: Colorado | X30: CO | Y30: United States | Z30: US | AA30: 72933 | AB30: 99803 | AC30: sharp-murray.com | AD30: singleton-patterson | AE30: https://www.cole-hansen.com/ | AF30: http://www.perez-simmons.biz/explore/appprivacy.php | AG30: categories/search/app | AH30: privacy | AI30: html | AJ30: 212.235.9.227 | AK30: 548b:4c63:fe87:a6bc:f3e0:dc6:fa2c:9e79 | AL30: 88:c8:c3:68:c8:20 | AM30: laptop-37.murphy.com | AN30: Mozilla/5.0 (Linux; Android 2.2) AppleWebKit/532.0 (KHTML, like Gecko) Chrome/36.0.866.0 Safari/532.0 | AO30: 4816470900633539 | AP30: VISA 16 digit | AQ30: 46263 | AR30: 106 | AS30: USD | AT30: US Dollar | AU30: $ | AV30: 6.123245 | AW30: -84.469065 | AX30: 6.123245,-84.469065 | AY30: thank | AZ30: shake, quality, child | BA30: These least office say explain thing lead. | BB30: Party special compare eat tonight run. His probably recognize believe recognize analysis those. | BC30: coach-eye-us | BD30: Project at risk total training. Yeah need yet baby black short. Improve close debate and ago police. | BE30: DarkGreen | BF30: #2d5f61 | BG30: application/xml | BH30: direction-send.xml | BI30: .xml | BJ30: 38015 | BK30: 38015 | BL30: 38015 | BM30: 38015 | BN30: 38015.752 | BO30: 38015.752 | BP30: 38015.753 | BQ30: 38015.753 | BR30: 0.75208333 | BS30: 0.75261574 | BT30: 0.75262303 | BU30: 0.75208333 | BV30: 0.75261574 | BW30: 0.75262303 | BX30: 1075399426 | BY30: 1075399426630 | BZ30: 2004 | CA30: 4 | CB30: 1 | CC30: 29 | CD30: Thursday | CE30: 579601.1 | CF30: 579601.11 | CG30: 579601.11 | CH30: 579601.11 | CI30: 1 | CJ30: 10 | CK30: 100 | CL30: 1000 | CM30: 10000 | CN30: 100000 | CO30: 1000000 | CP30: 9097526 | CQ30: 9097526 | CR30: 9100000 | CS30: 305.73 | CT30: 305.73 | CU30: 0.3136 | CV30: 0.3136 | CW30: / | CX30: - | CY30: , | CZ30: . | DA30: .
A31: 564d46aa-03ba-43a0-bd42-269c07275940 | B31: Melanie Brown | C31: Susan | D31: Davis | E31: Mx. | F31: DDS | G31: bradleyhunt | H31: Journalist, newspaper | I31: Hart-Lopez | J31: and Sons | K31: hmcmillan@example.org | L31: kellyglenn@valdez-smith.com | M31: qrobinson@santos-wood.com | N31: 664.397.1892 | O31: (756)225-2571 | P31: 8389 Jesse Ridges Apt. 436 New Christopher, DC 49590 | Q31: 3263 John Stream Suite 524 | R31: Schneider Trace | S31: 86403 | T31: Matthewborough | U31: New | V31: ton | W31: Texas | X31: TX | Y31: United States | Z31: US | AA31: 91763 | AB31: 94807 | AC31: franklin.net | AD31: white-soto | AE31: http://mckay.com/ | AF31: http://www.young.biz/wp-contentfaq.asp | AG31: tag/main/wp-content | AH31: category | AI31: html | AJ31: 147.102.0.128 | AK31: f7bc:e0ef:72c1:e68e:9390:6194:490c:e315 | AL31: 64:67:8b:f6:28:b8 | AM31: laptop-27.henderson-lynch.biz | AN31: Mozilla/5.0 (Macintosh; PPC Mac OS X 10_5_0; rv:1.9.6.20) Gecko/2806-10-01 00:24:20 Firefox/3.8 | AO31: 345510762091843 | AP31: American Express | AQ31: 46203 | AR31: CID: 5797 | AS31: USD | AT31: US Dollar | AU31: $ | AV31: 9.531873 | AW31: 4.1883 | AX31: 9.531873,4.188300 | AY31: program | AZ31: list, front, investment | BA31: End lay race effect. | BB31: Weight success activity side popular true huge only. Million country institution stop. Reality may mouth though only. Sell under thank body of something. | BC31: teach-character | BD31: Recognize according collection man best similar. Modern pressure run color hear region. Consider way late sport control arrive consumer. Else total impact phone person. | BE31: BlueViolet | BF31: #18caa1 | BG31: audio/mpeg | BH31: forward-technology.mp3 | BI31: .mp3 | BJ31: 37975 | BK31: 37975 | BL31: 37975 | BM31: 37975 | BN31: 37975.424 | BO31: 37975.424 | BP31: 37975.424 | BQ31: 37975.424 | BR31: 0.42361111 | BS31: 0.42384259 | BT31: 0.42384265 | BU31: 0.42361111 | BV31: 0.42384259 | BW31: 0.42384265 | BX31: 1071915020 | BY31: 1071915020005 | BZ31: 2003 | CA31: 3 | CB31: 12 | CC31: 20 | CD31: Saturday | CE31: 960818.1 | CF31: 960818.12 | CG31: 960818.12 | CH31: 960818.12 | CI31: 2 | CJ31: 20 | CK31: 200 | CL31: 2000 | CM31: 20000 | CN31: 200000 | CO31: 2000000 | CP31: 1345047 | CQ31: 1345047 | CR31: 1350000 | CS31: 4256.86 | CT31: 4256.86 | CU31: 0.0685 | CV31: 0.0685 | CW31: / | CX31: - | CY31: , | CZ31: . | DA31: .
A32: 301c8108-a904-4abd-a9c2-aa1783d1677a | B32: Mark Mcmahon | C32: Marco | D32: Schultz | E32: Mx. | F32: DVM | G32: erica39 | H32: Radio producer | I32: Stevenson-Bauer | J32: LLC | K32: ecrosby@example.net | L32: mcarter@thomas.net | M32: andersonlaura@collier-davies.info | N32: (371)378-3332 | O32: 302-456-4347 | P32: PSC 7153, Box 9915 APO AA 94537 | Q32: 863 Jonathon Highway Apt. 115 | R32: Julie Crescent | S32: 525 | T32: Raytown | U32: West | V32: ton | W32: Washington | X32: WA | Y32: United States | Z32: US | AA32: 56036 | AB32: 42397 | AC32: salinas-peck.com | AD32: alvarado | AE32: http://thomas-hahn.com/ | AF32: https://ortega.org/postspost.html | AG32: search/explore | AH32: home | AI32: html | AJ32: 198.250.112.188 | AK32: 7eb9:fe2d:3738:7270:d424:d9f4:a18e:4440 | AL32: d2:95:c0:1e:aa:4e | AM32: email-33.fitzgerald.info | AN32: Opera/9.53.(Windows NT 11.0; ur-IN) Presto/2.9.160 Version/12.00 | AO32: 5211845826034086 | AP32: Mastercard | AQ32: 46112 | AR32: 872 | AS32: USD | AT32: US Dollar | AU32: $ | AV32: -79.492587 | AW32: -110.84244 | AX32: -79.492587,-110.842442 | AY32: determine | AZ32: accept, language, fire | BA32: Gun task big. | BB32: Wear interview success unit benefit wind. War bring middle full. | BC32: leader-church | BD32: Alone drive major read west. Simply yard provide bed less stand. Every president happen build bar majority. | BE32: Tomato | BF32: #d64f11 | BG32: application/xml | BH32: paper-design-read.xml | BI32: .xml | BJ32: 39578 | BK32: 39578 | BL32: 39578 | BM32: 39578 | BN32: 39578.398 | BO32: 39578.398 | BP32: 39578.398 | BQ32: 39578.398 | BR32: 0.39791667 | BS32: 0.39822917 | BT32: 0.39823906 | BU32: 0.39791667 | BV32: 0.39822917 | BW32: 0.39823906 | BX32: 1210412007 | BY32: 1210412007855 | BZ32: 2008 | CA32: 8 | CB32: 5 | CC32: 10 | CD32: Saturday | CE32: 941654.5 | CF32: 941654.53 | CG32: 941654.53 | CH32: 941654.53 | CI32: 2 | CJ32: 20 | CK32: 200 | CL32: 2000 | CM32: 20000 | CN32: 200000 | CO32: 2000000 | CP32: 9558567 | CQ32: 9558567 | CR32: 9560000 | CS32: 1231.83 | CT32: 1231.83 | CU32: 0.5945 | CV32: 0.5945 | CW32: / | CX32: - | CY32: , | CZ32: . | DA32: .
A33: 501c93a3-b1f2-4be5-bd8d-a92b93baf4a3 | B33: Victoria Bell | C33: Amanda | D33: Clark | E33: Mr. | F33: PhD | G33: benjaminthomas | H33: Engineer, structural | I33: Guzman and Sons | J33: PLC | K33: joshua96@example.org | L33: patrick26@yahoo.com | M33: duffyerica@thomas.com | N33: +1-535-398-9262x5660 | O33: 718-718-6151 | P33: 40163 Lynn Tunnel East Alishaport, OR 64676 | Q33: 594 Lawson Causeway | R33: Louis Terrace | S33: 2588 | T33: Woodsberg | U33: West | V33: town | W33: Georgia | X33: GA | Y33: United States | Z33: US | AA33: 86689 | AB33: 17064 | AC33: gray.com | AD33: sellers | AE33: https://www.franklin.com/ | AF33: https://reid-miller.com/explore/categoriesterms.htm | AG33: posts/list | AH33: about | AI33: html | AJ33: 79.92.195.14 | AK33: 9347:f486:2a44:da88:17f8:5f5c:f1e2:cce7 | AL33: f6:1d:2b:92:fc:05 | AM33: laptop-82.jimenez-jennings.net | AN33: Mozilla/5.0 (X11; Linux x86_64) AppleWebKit/534.0 (KHTML, like Gecko) Chrome/28.0.894.0 Safari/534.0 | AO33: 4371892392312604328 | AP33: VISA 19 digit | AQ33: 06/33 | AR33: 93 | AS33: USD | AT33: US Dollar | AU33: $ | AV33: 47.234899 | AW33: -79.680173 | AX33: 47.234899,-79.680173 | AY33: art | AZ33: set, easy, check | BA33: Blue glass reveal I across issue. | BB33: More together improve tree. Choose prevent difficult. | BC33: indicate-house-firm | BD33: Movie especially writer prevent. Class government its grow that cup. Expect card inside former all. Where work budget major many race camera. Maybe type successful home body blue. | BE33: MediumSpringGreen | BF33: #6dfe88 | BG33: video/mp4 | BH33: enjoy-fast-speak.mp4 | BI33: .mp4 | BJ33: 41708 | BK33: 41708 | BL33: 41708 | BM33: 41708 | BN33: 41708.831 | BO33: 41708.831 | BP33: 41708.831 | BQ33: 41708.831 | BR33: 0.83055556 | BS33: 0.83076389 | BT33: 0.83077447 | BU33: 0.83055556 | BV33: 0.83076389 | BW33: 0.83077447 | BX33: 1394481378 | BY33: 1394481378914 | BZ33: 2014 | CA33: 14 | CB33: 3 | CC33: 10 | CD33: Monday | CE33: 670056.2 | CF33: 670056.25 | CG33: 670056.25 | CH33: 670056.25 | CI33: 5 | CJ33: 50 | CK33: 500 | CL33: 5000 | CM33: 50000 | CN33: 500000 | CO33: 5000000 | CP33: 5272130 | CQ33: 5272130 | CR33: 5270000 | CS33: 1194.19 | CT33: 1194.19 | CU33: 0.3958 | CV33: 0.3958 | CW33: / | CX33: - | CY33: , | CZ33: . | DA33: .
A34: 615eca80-0d0b-4920-9d46-0c9117478b5c | B34: Eric Schultz | C34: Jesse | D34: Rogers | E34: Mrs. | F34: MD | G34: torresjoseph | H34: Health visitor | I34: Dawson-Wright | J34: Inc | K34: blakewilliams@example.net | L34: justinramirez@hotmail.com | M34: jordanjohnny@cox-torres.com | N34: +1-808-325-5598x95343 | O34: 3293109337 | P34: USNV Turner FPO AA 26977 | Q34: 23684 Jacobson Mission | R34: Rhonda Cliff | S34: 6880 | T34: New Joshua | U34: East | V34: port | W34: Illinois | X34: IL | Y34: United States | Z34: US | AA34: 25429 | AB34: 97588 | AC34: simpson-patel.net | AD34: martin | AE34: https://lawson-clark.com/ | AF34: http://www.le.com/blog/list/postsregister.asp | AG34: search/main/wp-content | AH34: login | AI34: html | AJ34: 41.123.29.249 | AK34: ed60:1f49:471b:cc7:e233:c598:f129:ed2f | AL34: 88:44:8a:1a:7f:6b | AM34: db-05.jacobs.net | AN34: Mozilla/5.0 (compatible; MSIE 6.0; Windows NT 5.01; Trident/5.1) | AO34: 180024945147546 | AP34: JCB 15 digit | AQ34: 46230 | AR34: 22 | AS34: USD | AT34: US Dollar | AU34: $ | AV34: -67.235518 | AW34: -156.72834 | AX34: -67.235518,-156.728345 | AY34: like | AZ34: ground, past, brother | BA34: Behavior consider continue television country make role. | BB34: Financial those stage. Could century interview lawyer population I right case. | BC34: social-system | BD34: Help again step shake. Car show environment. Outside society act social my stand system be. Lose none know clear. | BE34: OliveDrab | BF34: #afcfeb | BG34: image/png | BH34: point-city-could.png | BI34: .png | BJ34: 38411 | BK34: 38411 | BL34: 38411 | BM34: 38411 | BN34: 38411.795 | BO34: 38411.795 | BP34: 38411.796 | BQ34: 38411.796 | BR34: 0.79513889 | BS34: 0.7955787 | BT34: 0.79558031 | BU34: 0.79513889 | BV34: 0.7955787 | BW34: 0.79558031 | BX34: 1109617538 | BY34: 1109617538139 | BZ34: 2005 | CA34: 5 | CB34: 2 | CC34: 28 | CD34: Monday | CE34: 10306.1 | CF34: 10306.14 | CG34: 10306.141 | CH34: 10306.14 | CI34: 4 | CJ34: 40 | CK34: 400 | CL34: 4000 | CM34: 40000 | CN34: 400000 | CO34: 4000000 | CP34: 9446465 | CQ34: 9446465 | CR34: 9450000 | CS34: 4980.49 | CT34: 4980.49 | CU34: 0.0733 | CV34: 0.0733 | CW34: / | CX34: - | CY34: , | CZ34: . | DA34: .
A35: 725aa10d-63fe-457c-a5d4-ec1951fc4c23 | B35: Rachel Mendoza | C35: Carlos | D35: Lane | E35: Misc. | F35: III | G35: morrisdavid | H35: Musician | I35: Flores-Coleman | J35: Ltd | K35: oguzman@example.com | L35: patrickdunn@ferguson.biz | M35: carpenterrobert@frank.com | N35: 350.230.5872 | O35: 552-547-2863 | P35: 26065 Jacqueline Shore South Maryburgh, AK 19753 | Q35: 13109 Hernandez Falls Suite 284 | R35: Jenkins Junction | S35: 412 | T35: Lake Antonioburgh | U35: New | V35: burgh | W35: New York | X35: NY | Y35: United States | Z35: US | AA35: 89617 | AB35: 60046 | AC35: dawson.com | AD35: perez | AE35: http://paul.org/ | AF35: http://www.mcdonald.biz/wp-content/bloglogin.html | AG35: app | AH35: privacy | AI35: php | AJ35: 140.118.119.76 | AK35: 13eb:4358:1ab9:f662:1bc0:2913:4519:72c4 | AL35: 28:b9:ab:0e:7a:90 | AM35: lt-11.harper.com | AN35: Mozilla/5.0 (Macintosh; U; PPC Mac OS X 10_5_0 rv:4.0; sr-ME) AppleWebKit/532.41.1 (KHTML, like Gecko) Version/5.0 Safari/532.41.1 | AO35: 3505673030644213 | AP35: JCB 16 digit | AQ35: 46262 | AR35: 146 | AS35: USD | AT35: US Dollar | AU35: $ | AV35: 36.155953 | AW35: -101.87787 | AX35: 36.155953,-101.877873 | AY35: better | AZ35: everything, although, choose | BA35: Shoulder claim white might. | BB35: Us game size fund growth task issue. Dream young parent when note yes. Source central that natural. Material lawyer college fast. | BC35: author-far-part | BD35: Author represent leave worry. Shake kind under vote will. Always teacher husband tax true can happen. | BE35: Coral | BF35: #513995 | BG35: application/pdf | BH35: push-different.pdf | BI35: .pdf | BJ35: 45933 | BK35: 45933 | BL35: 45933 | BM35: 45933 | BN35: 45933.384 | BO35: 45933.384 | BP35: 45933.384 | BQ35: 45933.384 | BR35: 0.38402778 | BS35: 0.38439815 | BT35: 0.38440412 | BU35: 0.38402778 | BV35: 0.38439815 | BW35: 0.38440412 | BX35: 1759482812 | BY35: 1759482812516 | BZ35: 2025 | CA35: 25 | CB35: 10 | CC35: 3 | CD35: Friday | CE35: 285702.4 | CF35: 285702.4 | CG35: 285702.4 | CH35: 285702.4 | CI35: 9 | CJ35: 90 | CK35: 900 | CL35: 9000 | CM35: 90000 | CN35: 900000 | CO35: 9000000 | CP35: 7352517 | CQ35: 7352517 | CR35: 7350000 | CS35: 4168.89 | CT35: 4168.89 | CU35: 0.7035 | CV35: 0.7035 | CW35: / | CX35: - | CY35: , | CZ35: . | DA35: .
A36: ↓d☺e☻b♥♦♣u♠•◘g○ | B36: ↓d☺e☻b♥♦♣u♠•◘g○ | C36: ↓d☺e☻b♥♦♣u♠•◘g○ | D36: ↓d☺e☻b♥♦♣u♠•◘g○ | E36: ↓d☺e☻b♥♦♣u♠•◘g○ | F36: ↓d☺e☻b♥♦♣u♠•◘g○ | G36: ↓d☺e☻b♥♦♣u♠•◘g○ | H36: ↓d☺e☻b♥♦♣u♠•◘g○ | I36: ↓d☺e☻b♥♦♣u♠•◘g○ | J36: ↓d☺e☻b♥♦♣u♠•◘g○ | K36: ↓d☺e☻b♥♦♣u♠•◘g○ | L36: ↓d☺e☻b♥♦♣u♠•◘g○ | M36: ↓d☺e☻b♥♦♣u♠•◘g○ | N36: ↓d☺e☻b♥♦♣u♠•◘g○ | O36: ↓d☺e☻b♥♦♣u♠•◘g○ | P36: ↓d☺e☻b♥♦♣u♠•◘g○ | Q36: ↓d☺e☻b♥♦♣u♠•◘g○ | R36: ↓d☺e☻b♥♦♣u♠•◘g○ | S36: ↓d☺e☻b♥♦♣u♠•◘g○ | T36: ↓d☺e☻b♥♦♣u♠•◘g○ | U36: ↓d☺e☻b♥♦♣u♠•◘g○ | V36: ↓d☺e☻b♥♦♣u♠•◘g○ | W36: ↓d☺e☻b♥♦♣u♠•◘g○ | X36: ↓d☺e☻b♥♦♣u♠•◘g○ | Y36: ↓d☺e☻b♥♦♣u♠•◘g○ | Z36: ↓d☺e☻b♥♦♣u♠•◘g○ | AA36: ↓d☺e☻b♥♦♣u♠•◘g○ | AB36: ↓d☺e☻b♥♦♣u♠•◘g○ | AC36: ↓d☺e☻b♥♦♣u♠•◘g○ | AD36: ↓d☺e☻b♥♦♣u♠•◘g○ | AE36: ↓d☺e☻b♥♦♣u♠•◘g○ | AF36: ↓d☺e☻b♥♦♣u♠•◘g○ | AG36: ↓d☺e☻b♥♦♣u♠•◘g○ | AH36: ↓d☺e☻b♥♦♣u♠•◘g○ | AI36: ↓d☺e☻b♥♦♣u♠•◘g○ | AJ36: ↓d☺e☻b♥♦♣u♠•◘g○ | AK36: ↓d☺e☻b♥♦♣u♠•◘g○ | AL36: ↓d☺e☻b♥♦♣u♠•◘g○ | AM36: ↓d☺e☻b♥♦♣u♠•◘g○ | AN36: ↓d☺e☻b♥♦♣u♠•◘g○ | AO36: ↓d☺e☻b♥♦♣u♠•◘g○ | AP36: ↓d☺e☻b♥♦♣u♠•◘g○ | AQ36: ↓d☺e☻b♥♦♣u♠•◘g○ | AR36: ↓d☺e☻b♥♦♣u♠•◘g○ | AS36: ↓d☺e☻b♥♦♣u♠•◘g○ | AT36: ↓d☺e☻b♥♦♣u♠•◘g○ | AU36: ↓d☺e☻b♥♦♣u♠•◘g○ | AV36: ↓d☺e☻b♥♦♣u♠•◘g○ | AW36: ↓d☺e☻b♥♦♣u♠•◘g○ | AX36: ↓d☺e☻b♥♦♣u♠•◘g○ | AY36: ↓d☺e☻b♥♦♣u♠•◘g○ | AZ36: ↓d☺e☻b♥♦♣u♠•◘g○ | BA36: ↓d☺e☻b♥♦♣u♠•◘g○ | BB36: ↓d☺e☻b♥♦♣u♠•◘g○ | BC36: ↓d☺e☻b♥♦♣u♠•◘g○ | BD36: ↓d☺e☻b♥♦♣u♠•◘g○ | BE36: ↓d☺e☻b♥♦♣u♠•◘g○ | BF36: ↓d☺e☻b♥♦♣u♠•◘g○ | BG36: ↓d☺e☻b♥♦♣u♠•◘g○ | BH36: ↓d☺e☻b♥♦♣u♠•◘g○ | BI36: ↓d☺e☻b♥♦♣u♠•◘g○ | BJ36: ↓d☺e☻b♥♦♣u♠•◘g○ | BK36: ↓d☺e☻b♥♦♣u♠•◘g○ | BL36: ↓d☺e☻b♥♦♣u♠•◘g○ | BM36: ↓d☺e☻b♥♦♣u♠•◘g○ | BN36: ↓d☺e☻b♥♦♣u♠•◘g○ | BO36: ↓d☺e☻b♥♦♣u♠•◘g○ | BP36: ↓d☺e☻b♥♦♣u♠•◘g○ | BQ36: ↓d☺e☻b♥♦♣u♠•◘g○ | BR36: ↓d☺e☻b♥♦♣u♠•◘g○ | BS36: ↓d☺e☻b♥♦♣u♠•◘g○ | BT36: ↓d☺e☻b♥♦♣u♠•◘g○ | BU36: ↓d☺e☻b♥♦♣u♠•◘g○ | BV36: ↓d☺e☻b♥♦♣u♠•◘g○ | BW36: ↓d☺e☻b♥♦♣u♠•◘g○ | BX36: ↓d☺e☻b♥♦♣u♠•◘g○ | BY36: ↓d☺e☻b♥♦♣u♠•◘g○ | BZ36: ↓d☺e☻b♥♦♣u♠•◘g○ | CA36: ↓d☺e☻b♥♦♣u♠•◘g○ | CB36: ↓d☺e☻b♥♦♣u♠•◘g○ | CC36: ↓d☺e☻b♥♦♣u♠•◘g○ | CD36: ↓d☺e☻b♥♦♣u♠•◘g○ | CE36: ↓d☺e☻b♥♦♣u♠•◘g○ | CF36: ↓d☺e☻b♥♦♣u♠•◘g○ | CG36: ↓d☺e☻b♥♦♣u♠•◘g○ | CH36: ↓d☺e☻b♥♦♣u♠•◘g○ | CI36: ↓d☺e☻b♥♦♣u♠•◘g○ | CJ36: ↓d☺e☻b♥♦♣u♠•◘g○ | CK36: ↓d☺e☻b♥♦♣u♠•◘g○ | CL36: ↓d☺e☻b♥♦♣u♠•◘g○ | CM36: ↓d☺e☻b♥♦♣u♠•◘g○ | CN36: ↓d☺e☻b♥♦♣u♠•◘g○ | CO36: ↓d☺e☻b♥♦♣u♠•◘g○ | CP36: ↓d☺e☻b♥♦♣u♠•◘g○ | CQ36: ↓d☺e☻b♥♦♣u♠•◘g○ | CR36: ↓d☺e☻b♥♦♣u♠•◘g○ | CS36: ↓d☺e☻b♥♦♣u♠•◘g○ | CT36: ↓d☺e☻b♥♦♣u♠•◘g○ | CU36: ↓d☺e☻b♥♦♣u♠•◘g○ | CV36: ↓d☺e☻b♥♦♣u♠•◘g○ | CW36: ↓d☺e☻b♥♦♣u♠•◘g○ | CX36: ↓d☺e☻b♥♦♣u♠•◘g○ | CY36: ↓d☺e☻b♥♦♣u♠•◘g○ | CZ36: ↓d☺e☻b♥♦♣u♠•◘g○ | DA36: ↓d☺e☻b♥♦♣u♠•◘g○

Sheet RowMetaData
A1: source_row | B1: row_kind | C1: expected_result | D1: note
A2: 36 | B2: NEGATIVE_CONTROL | C2: EXPECTED_FAILURES_PRESENT | D2: Intentional dev row with malformed values

Sheet ColumnMetaData
A1: group | B1: data_type | C1: column_name | D1: pattern_name | E1: example_value | F1: min | G1: max | H1: allowed_values | I1: normalize | J1: notes | K1: participates_in_validation
A2: STRING | B2: STRING | C2: uuid4 | D2: UUID_V4 | E2: bdd640fb-0667-4ad1-9c80-317fa3b1799d | F2: 36 | G2: 36 | H2: null | I2: TRIM | J2: Trim whitespace before validating UUID format | K2: =TRUE() -> TRUE
A3: USCONTACT | B3: STRING | C3: name | D3: NAME_STANDARD | E3: Daniel Doyle | F3: 1 | G3: 120 | H3: null | I3: TRIM | J3: Remove leading/trailing spaces before validating name characters | K3: =TRUE() -> TRUE
A4: USCONTACT | B4: STRING | C4: first_name | D4: NAME_STANDARD | E4: Erica | F4: 1 | G4: 80 | H4: null | I4: TRIM | J4: Trim whitespace before validation | K4: =TRUE() -> TRUE
A5: USCONTACT | B5: STRING | C5: last_name | D5: NAME_STANDARD | E5: Mcclain | F5: 1 | G5: 80 | H5: null | I5: TRIM | J5: Trim whitespace before validation | K5: =TRUE() -> TRUE
A6: USCONTACT | B6: STRING | C6: prefix | D6: NAME_STANDARD | E6: Mr. | F6: 1 | G6: 10 | H6: null | I6: TRIM | J6: Trim whitespace before validation | K6: =TRUE() -> TRUE
A7: USCONTACT | B7: STRING | C7: suffix | D7: NAME_STANDARD | E7: MD | F7: 1 | G7: 10 | H7: null | I7: TRIM | J7: Trim whitespace before validation | K7: =TRUE() -> TRUE
A8: USCONTACT | B8: STRING | C8: user_name | D8: USERNAME_STANDARD | E8: davisjesse | F8: 3 | G8: 40 | H8: null | I8: LOWERCASE|TRIM | J8: Convert to lowercase and trim spaces before username validation | K8: =TRUE() -> TRUE
A9: USCONTACT | B9: STRING | C9: job | D9: TITLE_STANDARD | E9: Town planner | F9: 1 | G9: 120 | H9: null | I9: TRIM | J9: Trim whitespace before validation | K9: =TRUE() -> TRUE
A10: USCONTACT | B10: STRING | C10: company | D10: ORG_NAME_STANDARD | E10: Hoffman Ltd | F10: 1 | G10: 120 | H10: null | I10: TRIM | J10: Trim whitespace before validation | K10: =TRUE() -> TRUE
A11: USCONTACT | B11: STRING | C11: company_suffix | D11: NAME_STANDARD | E11: Ltd | F11: 1 | G11: 20 | H11: Inc|LLC|Ltd|Corp|Co | I11: UPPERCASE|TRIM | J11: Convert suffix to uppercase and trim spaces before enumeration check | K11: =TRUE() -> TRUE
A12: NETWORK | B12: STRING | C12: email | D12: EMAIL_STANDARD | E12: lrobinson@example.com | F12: 5 | G12: 254 | H12: null | I12: LOWERCASE|TRIM | J12: Convert email to lowercase and remove leading/trailing spaces | K12: =TRUE() -> TRUE
A13: NETWORK | B13: STRING | C13: ascii_email | D13: EMAIL_STANDARD | E13: helenpeterson@lewis.com | F13: 5 | G13: 254 | H13: null | I13: LOWERCASE|TRIM | J13: Convert email to lowercase and remove leading/trailing spaces | K13: =TRUE() -> TRUE
... A15: INTCONTACT | B15: STRING | C15: phone_number | D15: PHONE_US | E15: +1-516-318-4959 | F15: 7 | G15: 20 | H15: null | I15: DIGITS_ONLY | J15: Remove all non-numeric characters ( + - ( ) space ) leaving digits only | K15: =TRUE() -> TRUE
A16: USCONTACT | B16: INTEGER | C16: basic_phone_number | D16: INTEGER_NUMBER | E16: 7344131647 | F16: 10 | G16: 15 | H16: null | I16: DIGITS_ONLY | J16: Ensure only digits remain before numeric validation | K16: =TRUE() -> TRUE
A17: USCONTACT | B17: STRING | C17: address | D17: ADDRESS_STANDARD | E17: 419 Amanda Gardens South Noah, SC 90699 | F17: 5 | G17: 200 | H17: null | I17: TRIM | J17: Trim leading/trailing spaces before address validation | K17: =TRUE() -> TRUE
A18: USCONTACT | B18: STRING | C18: street_address | D18: ADDRESS_STANDARD | E18: 503 Linda Locks | F18: 3 | G18: 120 | H18: null | I18: TRIM | J18: Trim whitespace before validation | K18: =TRUE() -> TRUE
A19: USCONTACT | B19: STRING | C19: street_name | D19: NAME_STANDARD | E19: Jones Port | F19: 2 | G19: 120 | H19: null | I19: TRIM | J19: Trim whitespace before validation | K19: =TRUE() -> TRUE
A20: USCONTACT | B20: INTEGER | C20: building_number | D20: INTEGER_NUMBER | E20: 537 | F20: 1 | G20: 999999 | H20: null | I20: TRIM | J20: Trim whitespace before numeric conversion | K20: =TRUE() -> TRUE
A21: USCONTACT | B21: STRING | C21: city | D21: CITY_NAME | E21: Wilkersonmouth | F21: 2 | G21: 120 | H21: null | I21: TRIM | J21: Trim whitespace before validation | K21: =TRUE() -> TRUE
A22: USCONTACT | B22: STRING | C22: city_prefix | D22: WORD | E22: East | F22: 2 | G22: 20 | H22: North|South|East|West | I22: TRIM | J22: Trim whitespace before enumeration validation | K22: =TRUE() -> TRUE
A23: USCONTACT | B23: STRING | C23: city_suffix | D23: WORD | E23: view | F23: 2 | G23: 20 | H23: view|ville|town|ton|land|berg|mouth|port|shire | I23: TRIM | J23: Trim whitespace before enumeration validation | K23: =TRUE() -> TRUE
A24: USCONTACT | B24: STRING | C24: state | D24: NAME_STANDARD | E24: Washington | F24: 2 | G24: 50 | H24: null | I24: TRIM | J24: Trim whitespace before validation | K24: =TRUE() -> TRUE
A25: USCONTACT | B25: STRING | C25: state_abbr | D25: STATE_ABBR | E25: WA | F25: 2 | G25: 2 | H25: AL|AK|AZ|AR|CA|CO|CT|DE|FL|GA|HI|ID|IL|IN|IA|KS|KY|LA|ME|MD|MA|MI|MN|MS|MO|MT|NE|NV|NH|NJ|NM|NY|NC|ND|OH|OK|OR|PA|RI|SC|SD|TN|TX|UT|VT|VA|WA|WV|WI|WY | I25: UPPERCASE|TRIM | J25: Convert to uppercase then trim spaces before enumeration validation | K25: =TRUE() -> TRUE
A26: USCONTACT | B26: STRING | C26: country | D26: NAME_STANDARD | E26: United States | F26: 2 | G26: 60 | H26: null | I26: TRIM | J26: Trim whitespace before validation | K26: =TRUE() -> TRUE
A27: USCONTACT | B27: STRING | C27: country_code | D27: COUNTRY_CODE | E27: US | F27: 2 | G27: 2 | H27: US | I27: UPPERCASE|TRIM | J27: Convert to uppercase then trim spaces | K27: =TRUE() -> TRUE
A28: USCONTACT | B28: STRING | C28: zipcode | D28: ZIPCODE_US | E28: 71145 | F28: 5 | G28: 5 | H28: null | I28: DIGITS_ONLY | J28: Remove non-numeric characters before validation | K28: =TRUE() -> TRUE
A29: USCONTACT | B29: STRING | C29: postalcode | D29: ZIPCODE_US | E29: 34939 | F29: 5 | G29: 5 | H29: null | I29: DIGITS_ONLY | J29: Remove non-numeric characters before validation | K29: =TRUE() -> TRUE
A30: NETWORK | B30: STRING | C30: domain_name | D30: DOMAIN_NAME | E30: richards.com | F30: 3 | G30: 255 | H30: null | I30: LOWERCASE|TRIM | J30: Convert to lowercase and trim spaces | K30: =TRUE() -> TRUE
A31: NETWORK | B31: STRING | C31: domain_word | D31: SLUG | E31: hicks | F31: 2 | G31: 50 | H31: null | I31: LOWERCASE|TRIM | J31: Convert to lowercase and trim spaces | K31: =TRUE() -> TRUE
A32: NETWORK | B32: STRING | C32: url | D32: URL_HTTP | E32: http://www.burton.biz/ | F32: 5 | G32: 2048 | H32: null | I32: TRIM | J32: Trim whitespace before URL validation | K32: =TRUE() -> TRUE
A33: NETWORK | B33: STRING | C33: uri | D33: URL_HTTP | E33: http://frazier.net/tags/tagpost.asp | F33: 3 | G33: 2048 | H33: null | I33: TRIM | J33: Trim whitespace before validation | K33: =TRUE() -> TRUE
A34: NETWORK | B34: STRING | C34: uri_path | D34: URI_PATH | E34: posts/category | F34: 1 | G34: 512 | H34: null | I34: TRIM | J34: Trim whitespace before validation | K34: =TRUE() -> TRUE
A35: NETWORK | B35: STRING | C35: uri_page | D35: WORD | E35: post | F35: 1 | G35: 120 | H35: null | I35: TRIM | J35: Trim whitespace before validation | K35: =TRUE() -> TRUE
A36: NETWORK | B36: STRING | C36: uri_extension | D36: FILE_EXTENSION_BARE | E36: .php | F36: 2 | G36: 10 | H36: .php|.html|.asp|.json|.xml | I36: LOWERCASE|TRIM | J36: Convert extension to lowercase and trim spaces | K36: =TRUE() -> TRUE
A37: NETWORK | B37: STRING | C37: ipv4 | D37: IPV4_STANDARD | E37: 104.13.74.245 | F37: 7 | G37: 15 | H37: null | I37: TRIM | J37: Trim whitespace before IP validation | K37: =TRUE() -> TRUE
A38: NETWORK | B38: STRING | C38: ipv6 | D38: IPV6_STANDARD | E38: b83c:fe0b:e037:e5ed:b8db:673:f42d:47cc | F38: 2 | G38: 39 | H38: null | I38: LOWERCASE|TRIM | J38: Convert to lowercase then trim spaces | K38: =TRUE() -> TRUE
A39: NETWORK | B39: STRING | C39: mac_address | D39: MAC_ADDRESS | E39: 26:86:5b:36:98:65 | F39: 17 | G39: 17 | H39: null | I39: LOWERCASE|TRIM | J39: Convert hex characters to lowercase then trim spaces | K39: =TRUE() -> TRUE
A40: NETWORK | B40: STRING | C40: hostname | D40: HOSTNAME | E40: desktop-28.sellers.com | F40: 3 | G40: 255 | H40: null | I40: LOWERCASE|TRIM | J40: Convert hostname to lowercase and trim spaces | K40: =TRUE() -> TRUE
A41: NETWORK | B41: STRING | C41: user_agent | D41: TEXT_ANY | E41: Mozilla/5.0 (compatible; MSIE 7.0; Windows CE; Trident/3.0) | F41: 3 | G41: 512 | H41: null | I41: TRIM | J41: Trim whitespace before validation | K41: =TRUE() -> TRUE
... A44: FINANCIAL | B44: DATE | C44: credit_card_expire | D44: CARD_EXPIRY_MMYY | E44: 10/35 | F44: 4 | G44: 5 | H44: null | I44: TRIM | J44: Trim whitespace before validation | K44: =TRUE() -> TRUE
A45: FINANCIAL | B45: INTEGER | C45: credit_card_security_code | D45: INTEGER_NUMBER | E45: 118 | F45: 3 | G45: 4 | H45: null | I45: DIGITS_ONLY | J45: Ensure only digits remain before validation | K45: =TRUE() -> TRUE
A46: FINANCIAL | B46: STRING | C46: currency_code | D46: WORD | E46: USD | F46: 3 | G46: 3 | H46: USD | I46: UPPERCASE|TRIM | J46: Convert currency code to uppercase and trim spaces | K46: =TRUE() -> TRUE
A47: FINANCIAL | B47: STRING | C47: currency_name | D47: NAME_STANDARD | E47: US Dollar | F47: 3 | G47: 40 | H47: US Dollar | I47: TRIM | J47: Trim whitespace before validation | K47: =TRUE() -> TRUE
A48: FINANCIAL | B48: STRING | C48: currency_symbol | D48: TEXT_ANY | E48: $ | F48: 1 | G48: 3 | H48: $ | I48: TRIM | J48: Trim whitespace before validation | K48: =TRUE() -> TRUE
A49: GPS | B49: FLOAT | C49: latitude | D49: FLOAT_NUMBER | E49: 62.921079 | F49: -90 | G49: 90 | H49: null | I49: TRIM | J49: Trim whitespace before numeric conversion | K49: =TRUE() -> TRUE
A50: GPS | B50: FLOAT | C50: longitude | D50: FLOAT_NUMBER | E50: -47.814142 | F50: -180 | G50: 180 | H50: null | I50: TRIM | J50: Trim whitespace before numeric conversion | K50: =TRUE() -> TRUE
A51: GPS | B51: STRING | C51: coordinate | D51: TEXT_ANY | E51: 62.921079,-47.814142 | F51: 3 | G51: 40 | H51: null | I51: TRIM | J51: Trim whitespace before validation | K51: =TRUE() -> TRUE
A52: STRING | B52: STRING | C52: word | D52: WORD | E52: down | F52: 1 | G52: 40 | H52: null | I52: TRIM | J52: Trim whitespace before validation | K52: =TRUE() -> TRUE
A53: STRING | B53: STRING | C53: words | D53: TEXT_ANY | E53: push, dog, build | F53: 1 | G53: 200 | H53: null | I53: TRIM | J53: Trim whitespace before validation | K53: =TRUE() -> TRUE
A54: STRING | B54: STRING | C54: sentence | D54: TEXT_ANY | E54: Detail audience piece director town teacher audience draw. | F54: 5 | G54: 500 | H54: null | I54: TRIM | J54: Trim whitespace before validation | K54: =TRUE() -> TRUE
A55: STRING | B55: STRING | C55: paragraph | D55: TEXT_ANY | E55: Much rich think office drug. Space couple best issue interest level rock. Art rock song body. | F55: 20 | G55: 2000 | H55: null | I55: TRIM | J55: Trim whitespace before validation | K55: =TRUE() -> TRUE
A56: STRING | B56: STRING | C56: slug | D56: SLUG | E56: dark-customer-not | F56: 3 | G56: 120 | H56: null | I56: LOWERCASE|TRIM | J56: Convert slug to lowercase and trim spaces | K56: =TRUE() -> TRUE
A57: STRING | B57: STRING | C57: text | D57: TEXT_ANY | E57: Contain leg themselves away space task. Anything yourself structure why. Image loss ten total. Her world enter six. | F57: 1 | G57: 5000 | H57: null | I57: TRIM | J57: Trim whitespace before validation | K57: =TRUE() -> TRUE
A58: COMPUTER | B58: STRING | C58: color_name | D58: NAME_STANDARD | E58: Wheat | F58: 3 | G58: 40 | H58: Red|Green|Blue|Yellow|Orange|Purple|Black|White|Gray|Brown|Wheat | I58: TRIM | J58: Trim whitespace before validation | K58: =TRUE() -> TRUE
A59: COMPUTER | B59: STRING | C59: hex_color | D59: HEX_COLOR | E59: #284d83 | F59: 4 | G59: 7 | H59: null | I59: UPPERCASE|TRIM | J59: Convert hex color letters to uppercase and trim spaces | K59: =TRUE() -> TRUE
A60: COMPUTER | B60: STRING | C60: mime_type | D60: MIME_TYPE | E60: text/csv | F60: 3 | G60: 120 | H60: text/csv|application/json|text/plain|application/xml | I60: LOWERCASE|TRIM | J60: Convert MIME type to lowercase and trim spaces | K60: =TRUE() -> TRUE
A61: COMPUTER | B61: STRING | C61: file_name | D61: FILE_NAME | E61: particular-phone.csv | F61: 1 | G61: 255 | H61: null | I61: TRIM | J61: Trim whitespace before validation | K61: =TRUE() -> TRUE
A62: COMPUTER | B62: STRING | C62: file_extension | D62: FILE_EXTENSION | E62: csv | F62: 2 | G62: 10 | H62: csv|txt|json|xml|html | I62: LOWERCASE|TRIM|REMOVE_LEADING_DOT | J62: Convert extension to lowercase and trim spaces | K62: =TRUE() -> TRUE
A63: DATEONLY | B63: DATE | C63: date_mdy_slash_yyyy | D63: DATE_MMDDYYYY | E63: 42753 | F63: 10 | G63: 10 | H63: null | I63: TRIM | J63: Trim whitespace before date validation | K63: =TRUE() -> TRUE
A64: DATEONLY | B64: DATE | C64: date_mdy_dash_yyyy | D64: DATE_MMDDYYYY | E64: 42753 | F64: 10 | G64: 10 | H64: null | I64: TRIM | J64: Trim whitespace before date validation | K64: =TRUE() -> TRUE
A65: DATEONLY | B65: DATE | C65: date_mdy_slash_yy | D65: DATE_MMDDYY | E65: 42753 | F65: 8 | G65: 8 | H65: null | I65: TRIM | J65: Trim whitespace before date validation | K65: =TRUE() -> TRUE
A66: DATEONLY | B66: DATE | C66: date_mdy_dash_yy | D66: DATE_MMDDYY | E66: 42753 | F66: 8 | G66: 8 | H66: null | I66: TRIM | J66: Trim whitespace before date validation | K66: =TRUE() -> TRUE
A67: DATETIME | B67: DATETIME | C67: timestamp_mdy_slash_minute | D67: DATETIME_MDY_SLASH_MINUTE_FLEX | E67: 42753.455 | F67: 16 | G67: 16 | H67: null | I67: TRIM | J67: Trim whitespace before datetime validation | K67: =TRUE() -> TRUE
A68: DATETIME | B68: DATETIME | C68: timestamp_mdy_dash_minute | D68: DATETIME_MDY_DASH_MINUTE_FLEX | E68: 42753.455 | F68: 16 | G68: 16 | H68: null | I68: TRIM | J68: Trim whitespace before datetime validation | K68: =TRUE() -> TRUE
A69: DATETIME | B69: DATETIME | C69: timestamp_mdy_slash_second | D69: DATETIME_MDY_SLASH_SECOND_FLEX | E69: 42753.455 | F69: 19 | G69: 19 | H69: null | I69: TRIM | J69: Trim whitespace before datetime validation | K69: =TRUE() -> TRUE
A70: DATETIME | B70: DATETIME | C70: timestamp_mdy_dash_second | D70: DATETIME_MDY_DASH_SECOND_FLEX | E70: 42753.455 | F70: 19 | G70: 19 | H70: null | I70: TRIM | J70: Trim whitespace before datetime validation | K70: =TRUE() -> TRUE
A71: TIMEONLY | B71: TIME | C71: time_hh_mm | D71: TIME_24H | E71: 0.45486111 | F71: 5 | G71: 5 | H71: null | I71: TRIM | J71: Trim whitespace before time validation | K71: =TRUE() -> TRUE
A72: TIMEONLY | B72: TIME | C72: time_hh_mm_ss | D72: TIME_24H | E72: 0.45547454 | F72: 8 | G72: 8 | H72: null | I72: TRIM | J72: Trim whitespace before time validation | K72: =TRUE() -> TRUE
A73: TIMEONLY | B73: TIME | C73: time_hh_mm_ss_mmm | D73: TIME_24H | E73: 0.45548545 | F73: 8 | G73: 12 | H73: null | I73: TRIM | J73: Trim whitespace before time validation | K73: =TRUE() -> TRUE
A74: TIMEONLY | B74: TIME | C74: time_hh_mm_am_pm | D74: TIME_12H | E74: 0.45486111 | F74: 7 | G74: 8 | H74: null | I74: UPPERCASE|TRIM | J74: Convert AM/PM indicator to uppercase and trim spaces | K74: =TRUE() -> TRUE
... A82: DAYONLY | B82: DATE | C82: day_dd | D82: INTEGER_NUMBER | E82: 18 | F82: 1 | G82: 31 | H82: null | I82: TRIM | J82: Trim whitespace before numeric validation | K82: =TRUE() -> TRUE
A83: DAYSTRING | B83: STRING | C83: day_of_week | D83: DAY_OF_WEEK | E83: Wednesday | F83: 6 | G83: 9 | H83: Monday|Tuesday|Wednesday|Thursday|Friday|Saturday|Sunday | I83: TRIM | J83: Trim whitespace before enumeration validation | K83: =TRUE() -> TRUE
A84: ONEDECIMAL | B84: FLOAT | C84: decimal_1 | D84: FLOAT_NUMBER | E84: 223987.5 | F84: -1000000000 | G84: 1000000000 | H84: null | I84: REMOVE_COMMAS|TRIM | J84: Remove grouping commas then trim whitespace before numeric parsing | K84: =TRUE() -> TRUE
A85: TWODECIMAL | B85: FLOAT | C85: decimal_2 | D85: FLOAT_NUMBER | E85: 223987.53 | F85: -1000000000 | G85: 1000000000 | H85: null | I85: REMOVE_COMMAS|TRIM | J85: Remove grouping commas then trim whitespace before numeric parsing | K85: =TRUE() -> TRUE
A86: THREEDECIMAL | B86: FLOAT | C86: decimal_3 | D86: FLOAT_NUMBER | E86: 223987.53 | F86: -1000000000 | G86: 1000000000 | H86: null | I86: REMOVE_COMMAS|TRIM | J86: Remove grouping commas then trim whitespace before numeric parsing | K86: =TRUE() -> TRUE
A87: COMMAWITHDECIMAL | B87: FLOAT | C87: decimal_grouped_2 | D87: FLOAT_NUMBER | E87: 223987.53 | F87: -1000000000 | G87: 1000000000 | H87: null | I87: REMOVE_COMMAS|TRIM | J87: Remove grouping commas then trim whitespace before numeric parsing | K87: =TRUE() -> TRUE
A88: SINGLEDIGIT | B88: FLOAT | C88: ones | D88: INTEGER_NUMBER | E88: 2 | F88: 0 | G88: 9 | H88: null | I88: TRIM | J88: Trim whitespace before numeric validation | K88: =TRUE() -> TRUE
A89: DOUBLEDIGIT | B89: FLOAT | C89: tens | D89: INTEGER_NUMBER | E89: 20 | F89: 0 | G89: 99 | H89: null | I89: TRIM | J89: Trim whitespace before numeric validation | K89: =TRUE() -> TRUE
A90: TRIPLEDIGIT | B90: FLOAT | C90: hundreds | D90: INTEGER_NUMBER | E90: 200 | F90: 0 | G90: 999 | H90: null | I90: TRIM | J90: Trim whitespace before numeric validation | K90: =TRUE() -> TRUE
A91: QUADDIGIT | B91: FLOAT | C91: thousands | D91: INTEGER_NUMBER | E91: 2000 | F91: 0 | G91: 9999 | H91: null | I91: TRIM | J91: Trim whitespace before numeric validation | K91: =TRUE() -> TRUE
A92: PENTADIGIT | B92: FLOAT | C92: ten_thousands | D92: INTEGER_NUMBER | E92: 20000 | F92: 0 | G92: 99999 | H92: null | I92: TRIM | J92: Trim whitespace before numeric validation | K92: =TRUE() -> TRUE
A93: SEPTADIGIT | B93: FLOAT | C93: hundred_thousands | D93: INTEGER_NUMBER | E93: 200000 | F93: 0 | G93: 999999 | H93: null | I93: TRIM | J93: Trim whitespace before numeric validation | K93: =TRUE() -> TRUE
A94: OCTODIGIT | B94: FLOAT | C94: millions | D94: INTEGER_NUMBER | E94: 2000000 | F94: 0 | G94: 9999999 | H94: null | I94: TRIM | J94: Trim whitespace before numeric validation | K94: =TRUE() -> TRUE
A95: SEPTADIGIT | B95: FLOAT | C95: number_plain | D95: INTEGER_NUMBER | E95: 1720583 | F95: -1000000000 | G95: 1000000000 | H95: null | I95: TRIM | J95: Trim whitespace before numeric validation | K95: =TRUE() -> TRUE
... A101: DECIMALPERCENTAGE | B101: FLOAT | C101: percent_decimal | D101: FLOAT_NUMBER | E101: 0.8922 | F101: 0 | G101: 1 | H101: null | I101: TRIM | J101: Trim whitespace before numeric validation | K101: =TRUE() -> TRUE
A102: SPECIALCHARACTOR | B102: STRING | C102: date_separator_slash | D102: TEXT_ANY | E102: / | F102: 1 | G102: 1 | H102: / | I102: TRIM | J102: Trim whitespace before validation | K102: =FALSE() -> FALSE
A103: SPECIALCHARACTOR | B103: STRING | C103: date_separator_dash | D103: TEXT_ANY | E103: - | F103: 1 | G103: 1 | H103: - | I103: TRIM | J103: Trim whitespace before validation | K103: =FALSE() -> FALSE
A104: SPECIALCHARACTOR | B104: STRING | C104: grouping_separator | D104: TEXT_ANY | E104: , | F104: 1 | G104: 1 | I104: TRIM | J104: Trim whitespace before validation | K104: =FALSE() -> FALSE
A105: SPECIALCHARACTOR | B105: STRING | C105: decimal_separator | D105: TEXT_ANY | E105: . | F105: 1 | G105: 1 | H105: . | I105: TRIM | J105: Trim whitespace before validation | K105: =FALSE() -> FALSE
A106: SPECIALCHARACTOR | B106: STRING | C106: fraction_separator | D106: TEXT_ANY | E106: . | F106: 1 | G106: 1 | H106: . | I106: TRIM | J106: Trim whitespace before validation | K106: =FALSE() -> FALSE

Sheet ValidationRules
A1: ValidationProcedure | B1: Operation | C1: Pattern | D1: Replacement | E1: Description
A2: TRIM | B2: TRIM | C2: null | D2: null | E2: Remove leading and trailing whitespace
A3: LOWERCASE | B3: CASE_CONVERT | C3: lower | D3: null | E3: Convert all alphabetic characters to lowercase
A4: UPPERCASE | B4: CASE_CONVERT | C4: upper | D4: null | E4: Convert all alphabetic characters to uppercase
A5: DIGITS_ONLY | B5: REGEX_REPLACE | C5: [^0-9] | E5: Remove all characters except digits
A6: REMOVE_COMMAS | B6: CHAR_REPLACE | E6: Remove comma thousands separators
A7: REMOVE_PERCENT | B7: CHAR_REPLACE | C7: % | E7: Remove percent symbol
A8: REMOVE_CURRENCY_SYMBOL | B8: REGEX_REPLACE | C8: [$€£¥] | E8: Remove common currency symbols
A9: NONE | B9: NONE | C9: null | D9: null | E9: No transformation applied
A10: REMOVE_LEADING_DOT | B10: REGEX_REPLACE | C10: ^\.+ | D10: null | E10: Remove one or more leading dots from file extension input

Sheet RegexPatterns
A1: pattern_name | B1: regex | C1: description
A2: NAME_STANDARD | B2: ^[A-Za-z .'-]+$ | C2: letters spaces apostrophes hyphen
A3: USERNAME_STANDARD | B3: ^[A-Za-z0-9._-]+$ | C3: username characters
A4: EMAIL_STANDARD | B4: ^[A-Za-z0-9._%+-]+@[A-Za-z0-9.-]+\.[A-Za-z]{2,}$ | C4: standard email
A5: PHONE_US | B5: ^[0-9+()\- ]{7,20}$ | C5: US phone format
A6: ZIPCODE_US | B6: ^[0-9]{5}$ | C6: 5 digit zipcode
A7: ZIPCODE_US_PLUS4 | B7: ^[0-9]{5}(-[0-9]{4})?$ | C7: zipcode with optional plus4
A8: ADDRESS_STANDARD | B8: ^[0-9A-Za-z .,#'-]+$ | C8: street address characters
A9: CITY_NAME | B9: ^[A-Za-z .'-]+$ | C9: city name
A10: STATE_ABBR | B10: ^[A-Z]{2}$ | C10: two letter state code
A11: COUNTRY_CODE | B11: ^[A-Z]{2}$ | C11: ISO country code
A12: DOMAIN_NAME | B12: ^[A-Za-z0-9.-]+\.[A-Za-z]{2,}$ | C12: domain name
... A38: TEXT_ANY | B38: ^.*$ | C38: any text
A39: TITLE_STANDARD | B39: ^[A-Za-z][A-Za-z .,'()\/&-]*$
A40: ORG_NAME_STANDARD | B40: ^[A-Za-z0-9][A-Za-z0-9 .,'()\/&-]*$
A41: CARD_EXPIRY_MMYY | B41: ^(0[1-9]|1[0-2])[\/\-][0-9]{2}$
A42: FILE_EXTENSION_BARE | B42: ^[A-Za-z0-9]{1,10}$
A43: DATETIME_MDY_SLASH_MINUTE_FLEX | B43: ^(0[1-9]|1[0-2])\/(0[1-9]|[12][0-9]|3[01])\/[0-9]{4} ([0-9]|1[0-9]|2[0-3]):[0-5][0-9]$
A44: DATETIME_MDY_DASH_MINUTE_FLEX | B44: ^(0[1-9]|1[0-2])\-(0[1-9]|[12][0-9]|3[01])\-[0-9]{4} ([0-9]|1[0-9]|2[0-3]):[0-5][0-9]$
A45: DATETIME_MDY_SLASH_SECOND_FLEX | B45: ^(0[1-9]|1[0-2])\/(0[1-9]|[12][0-9]|3[01])\/[0-9]{4} ([0-9]|1[0-9]|2[0-3]):[0-5][0-9]:[0-5][0-9]$
A46: DATETIME_MDY_DASH_SECOND_FLEX | B46: ^(0[1-9]|1[0-2])\-(0[1-9]|[12][0-9]|3[01])\-[0-9]{4} ([0-9]|1[0-9]|2[0-3]):[0-5][0-9]:[0-5][0-9]$
A47: DATETIME_MDY_SLASH_MILLISECOND_FLEX | B47: ^(0[1-9]|1[0-2])\/(0[1-9]|[12][0-9]|3[01])\/[0-9]{4} ([0-9]|1[0-9]|2[0-3]):[0-5][0-9]:[0-5][0-9]\.[0-9]{3}$
A48: DATETIME_MDY_DASH_MILLISECOND_FLEX | B48: ^(0[1-9]|1[0-2])\-(0[1-9]|[12][0-9]|3[01])\-[0-9]{4} ([0-9]|1[0-9]|2[0-3]):[0-5][0-9]:[0-5][0-9]\.[0-9]{3}$
A49: PERCENT_RATIO | B49: ^(0(\.[0-9]+)?|1(\.0+)?)$

Sheet ValidationFormula
A1: Formula | B1: Sheet Used | C1: RangeApplied | D1: Results Expected | E1: Result Format | F1: Formula Description
A2: "=LET( raw, INDEX(fakerUSDataset!$A:$CX, ROW(), COLUMN()), hdr, INDEX(fakerUSDataset!$1:$1, COLUMN()), norm, INDEX(ColumnMetaData!$I:$I, MATCH(hdr, ColumnMetaData!$C:$C, 0)), patName, INDEX(ColumnMetaData!$D:$D, MATCH(hdr, ColumnMetaData!$C:$C, 0)), rx, INDEX(RegexPatterns!$B:$B, MATCH(patName, RegexPatterns!$A:$A, 0)), txt, TO_TEXT(raw), normed, SWITCH( norm, "TRIM", TRIM(txt), "LOWERCASE|TRIM", LOWER(TRIM(txt)), "UPPERCASE|TRIM", UPPER(TRIM(txt)), "DIGITS_ONLY", REGEXREPLACE(txt, "[^0-9]", ""), "REMOVE_COMMAS|TRIM", TRIM(SUBSTITUTE(txt, ",", "")), "REMOVE_CURRENCY_SYMBOL|REMOVE_COMMAS|TRIM", TRIM(REGEXREPLACE(SUBSTITUTE(txt, ",", ""), "[$€£¥]", "")), "REMOVE_PERCENT|TRIM", TRIM(SUBSTITUTE(txt, "%", "")), txt ), IF(REGEXMATCH(normed, rx), TRUE, raw) )" | B2: TestMatrix | C2: A2:CV36 | D2: Boolean | E2: True or Value of Cell | F2: Determines if the cell being called passes the validation and regex checks for data entered on a cell.
A3: "=LET( step1, TestMatrix!A2, raw, fakerUSDataset!A2, hdr, fakerUSDataset!A$1, allowed, INDEX(ColumnMetaData!$H:$H, MATCH(hdr, ColumnMetaData!$C:$C, 0)), allowedText, TRIM(allowed), rawText, TRIM(TEXT(raw, "@")), listText, "|" & SUBSTITUTE(TRIM(SUBSTITUTE(allowedText, " |", "|")), "| ", "|") & "|", probe, "|" & rawText & "|", IF( step1<>TRUE, "FALSE", IF( OR(allowedText="", LOWER(allowedText)="null"), "TRUE, TRUE", IF( ISNUMBER(SEARCH(probe, listText)), "TRUE, TRUE", "TRUE, " & raw ) ) ) )" | B3: TestMatrix2 | C3: A2:CV36 | D3: Boolean, Boolean | E3: A set of booleans | F3: Determines if the regex from step 1 succeeded if it did, return TRUE, then if it passes the allowed_values test, return TRUE otherwise return the raw value for inspection, ELSE return FALSE

Sheet TestMatrix
A1: uuid4 | B1: name | C1: first_name | D1: last_name | E1: prefix | F1: suffix | G1: user_name | H1: job | I1: company | J1: company_suffix | K1: email | L1: ascii_email | M1: company_email | N1: phone_number | O1: basic_phone_number | P1: address | Q1: street_address | R1: street_name | S1: building_number | T1: city | U1: city_prefix | V1: city_suffix | W1: state | X1: state_abbr | Y1: country | Z1: country_code | AA1: zipcode | AB1: postalcode | AC1: domain_name | AD1: domain_word | AE1: url | AF1: uri | AG1: uri_path | AH1: uri_page | AI1: uri_extension | AJ1: ipv4 | AK1: ipv6 | AL1: mac_address | AM1: hostname | AN1: user_agent | AO1: credit_card_number | AP1: credit_card_provider | AQ1: credit_card_expire | AR1: credit_card_security_code | AS1: currency_code | AT1: currency_name | AU1: currency_symbol | AV1: latitude | AW1: longitude | AX1: coordinate | AY1: word | AZ1: words | BA1: sentence | BB1: paragraph | BC1: slug | BD1: text | BE1: color_name | BF1: hex_color | BG1: mime_type | BH1: file_name | BI1: file_extension | BJ1: date_mdy_slash_yyyy | BK1: date_mdy_dash_yyyy | BL1: date_mdy_slash_yy | BM1: date_mdy_dash_yy | BN1: timestamp_mdy_slash_minute | BO1: timestamp_mdy_dash_minute | BP1: timestamp_mdy_slash_second | BQ1: timestamp_mdy_dash_second | BR1: time_hh_mm | BS1: time_hh_mm_ss | BT1: time_hh_mm_ss_mmm | BU1: time_hh_mm_am_pm | BV1: time_hh_mm_ss_am_pm | BW1: time_hh_mm_ss_mmm_am_pm | BX1: timestamp_unix_s | BY1: timestamp_unix_ms | BZ1: year_yyyy | CA1: year_yy | CB1: month_mm | CC1: day_dd | CD1: day_of_week | CE1: decimal_1 | CF1: decimal_2 | CG1: decimal_3 | CH1: decimal_grouped_2 | CI1: ones | CJ1: tens | CK1: hundreds | CL1: thousands | CM1: ten_thousands | CN1: hundred_thousands | CO1: millions | CP1: number_plain | CQ1: number_grouped | CR1: number_scientific | CS1: currency_usd | CT1: currency_usd_plain | CU1: percent | CV1: percent_decimal
A2: =IFERROR(__xludf.dummyfunction("LET( raw, INDEX(fakerUSDataset!$A:$CX, ROW(), COLUMN()), hdr, INDEX(fakerUSDataset!$1:$1, COLUMN()), norm, INDEX(ColumnMetaData!$I:$I, MATCH(hdr, ColumnMetaData!$C:$C, 0)), patName, INDEX(ColumnMetaData!$D:$D, MATCH(hdr, ColumnMetaData!$C:$C, 0)),"&" rx, INDEX(RegexPatterns!$B:$B, MATCH(patName, RegexPatterns!$A:$A, 0)), txt, TO_TEXT(raw), normed, SWITCH( norm, ""TRIM"", TRIM(txt), ""LOWERCASE|TRIM"", LOWER(TRIM(txt)), ""UPPERCASE|TRIM"", UPPER(TRIM(txt)), ""DIGITS_ONLY"", R"&"EGEXREPLACE(txt, ""[^0-9]"", """"), ""REMOVE_COMMAS|TRIM"", TRIM(SUBSTITUTE(txt, "","", """")), ""REMOVE_CURRENCY_SYMBOL|REMOVE_COMMAS|TRIM"", TRIM(REGEXREPLACE(SUBSTITUTE(txt, "","", """"), ""[$€£¥]"", """")), ""REMOVE_PERCENT|TRIM"", TRIM(SU"&"BSTITUTE(txt, ""%"", """")), txt ), IF(REGEXMATCH(normed, rx), TRUE, raw) )"),TRUE()) -> TRUE | B2: =IFERROR(__xludf.dummyfunction("LET( raw, INDEX(fakerUSDataset!$A:$CX, ROW(), COLUMN()), hdr, INDEX(fakerUSDataset!$1:$1, COLUMN()), norm, INDEX(ColumnMetaData!$I:$I, MATCH(hdr, ColumnMetaData!$C:$C, 0)), patName, INDEX(ColumnMetaData!$D:$D, MATCH(hdr, ColumnMetaData!$C:$C, 0)),"&" rx, INDEX(RegexPatterns!$B:$B, MATCH(patName, RegexPatterns!$A:$A, 0)), txt, TO_TEXT(raw), normed, SWITCH( norm, ""TRIM"", TRIM(txt), ""LOWERCASE|TRIM"", LOWER(TRIM(txt)), ""UPPERCASE|TRIM"", UPPER(TRIM(txt)), ""DIGITS_ONLY"", R"&"EGEXREPLACE(txt, ""[^0-9]"", """"), ""REMOVE_COMMAS|TRIM"", TRIM(SUBSTITUTE(txt, "","", """")), ""REMOVE_CURRENCY_SYMBOL|REMOVE_COMMAS|TRIM"", TRIM(REGEXREPLACE(SUBSTITUTE(txt, "","", """"), ""[$€£¥]"", """")), ""REMOVE_PERCENT|TRIM"", TRIM(SU"&"BSTITUTE(txt, ""%"", """")), txt ), IF(REGEXMATCH(normed, rx), TRUE, raw) )"),TRUE()) -> TRUE | C2: =IFERROR(__xludf.dummyfunction("LET( raw, INDEX(fakerUSDataset!$A:$CX, ROW(), COLUMN()), hdr, INDEX(fakerUSDataset!$1:$1, COLUMN()), norm, INDEX(ColumnMetaData!$I:$I, MATCH(hdr, ColumnMetaData!$C:$C, 0)), patName, INDEX(ColumnMetaData!$D:$D, MATCH(hdr, ColumnMetaData!$C:$C, 0)),"&" rx, INDEX(RegexPatterns!$B:$B, MATCH(patName, RegexPatterns!$A:$A, 0)), txt, TO_TEXT(raw), normed, SWITCH( norm, ""TRIM"", TRIM(txt), ""LOWERCASE|TRIM"", LOWER(TRIM(txt)), ""UPPERCASE|TRIM"", UPPER(TRIM(txt)), ""DIGITS_ONLY"", R"&"EGEXREPLACE(txt, ""[^0-9]"", """"), ""REMOVE_COMMAS|TRIM"", TRIM(SUBSTITUTE(txt, "","", """")), ""REMOVE_CURRENCY_SYMBOL|REMOVE_COMMAS|TRIM"", TRIM(REGEXREPLACE(SUBSTITUTE(txt, "","", """"), ""[$€£¥]"", """")), ""REMOVE_PERCENT|TRIM"", TRIM(SU"&"BSTITUTE(txt, ""%"", """")), txt ), IF(REGEXMATCH(normed, rx), TRUE, raw) )"),TRUE()) -> TRUE | D2: =IFERROR(__xludf.dummyfunction("LET( raw, INDEX(fakerUSDataset!$A:$CX, ROW(), COLUMN()), hdr, INDEX(fakerUSDataset!$1:$1, COLUMN()), norm, INDEX(ColumnMetaData!$I:$I, MATCH(hdr, ColumnMetaData!$C:$C, 0)), patName, INDEX(ColumnMetaData!$D:$D, MATCH(hdr, ColumnMetaData!$C:$C, 0)),"&" rx, INDEX(RegexPatterns!$B:$B, MATCH(patName, RegexPatterns!$A:$A, 0)), txt, TO_TEXT(raw), normed, SWITCH( norm, ""TRIM"", TRIM(txt), ""LOWERCASE|TRIM"", LOWER(TRIM(txt)), ""UPPERCASE|TRIM"", UPPER(TRIM(txt)), ""DIGITS_ONLY"", R"&"EGEXREPLACE(txt, ""[^0-9]"", """"), ""REMOVE_COMMAS|TRIM"", TRIM(SUBSTITUTE(txt, "","", """")), ""REMOVE_CURRENCY_SYMBOL|REMOVE_COMMAS|TRIM"", TRIM(REGEXREPLACE(SUBSTITUTE(txt, "","", """"), ""[$€£¥]"", """")), ""REMOVE_PERCENT|TRIM"", TRIM(SU"&"BSTITUTE(txt, ""%"", """")), txt ), IF(REGEXMATCH(normed, rx), TRUE, raw) )"),TRUE()) -> TRUE | E2: =IFERROR(__xludf.dummyfunction("LET( raw, INDEX(fakerUSDataset!$A:$CX, ROW(), COLUMN()), hdr, INDEX(fakerUSDataset!$1:$1, COLUMN()), norm, INDEX(ColumnMetaData!$I:$I, MATCH(hdr, ColumnMetaData!$C:$C, 0)), patName, INDEX(ColumnMetaData!$D:$D, MATCH(hdr, ColumnMetaData!$C:$C, 0)),"&" rx, INDEX(RegexPatterns!$B:$B, MATCH(patName, RegexPatterns!$A:$A, 0)), txt, TO_TEXT(raw), normed, SWITCH( norm, ""TRIM"", TRIM(txt), ""LOWERCASE|TRIM"", LOWER(TRIM(txt)), ""UPPERCASE|TRIM"", UPPER(TRIM(txt)), ""DIGITS_ONLY"", R"&"EGEXREPLACE(txt, ""[^0-9]"", """"), ""REMOVE_COMMAS|TRIM"", TRIM(SUBSTITUTE(txt, "","", """")), ""REMOVE_CURRENCY_SYMBOL|REMOVE_COMMAS|TRIM"", TRIM(REGEXREPLACE(SUBSTITUTE(txt, "","", """"), ""[$€£¥]"", """")), ""REMOVE_PERCENT|TRIM"", TRIM(SU"&"BSTITUTE(txt, ""%"", """")), txt ), IF(REGEXMATCH(normed, rx), TRUE, raw) )"),TRUE()) -> TRUE | F2: =IFERROR(__xludf.dummyfunction("LET( raw, INDEX(fakerUSDataset!$A:$CX, ROW(), COLUMN()), hdr, INDEX(fakerUSDataset!$1:$1, COLUMN()), norm, INDEX(ColumnMetaData!$I:$I, MATCH(hdr, ColumnMetaData!$C:$C, 0)), patName, INDEX(ColumnMetaData!$D:$D, MATCH(hdr, ColumnMetaData!$C:$C, 0)),"&" rx, INDEX(RegexPatterns!$B:$B, MATCH(patName, RegexPatterns!$A:$A, 0)), txt, TO_TEXT(raw), normed, SWITCH( norm, ""TRIM"", TRIM(txt), ""LOWERCASE|TRIM"", LOWER(TRIM(txt)), ""UPPERCASE|TRIM"", UPPER(TRIM(txt)), ""DIGITS_ONLY"", R"&"EGEXREPLACE(txt, ""[^0-9]"", """"), ""REMOVE_COMMAS|TRIM"", TRIM(SUBSTITUTE(txt, "","", """")), ""REMOVE_CURRENCY_SYMBOL|REMOVE_COMMAS|TRIM"", TRIM(REGEXREPLACE(SUBSTITUTE(txt, "","", """"), ""[$€£¥]"", """")), ""REMOVE_PERCENT|TRIM"", TRIM(SU"&"BSTITUTE(txt, ""%"", """")), txt ), IF(REGEXMATCH(normed, rx), TRUE, raw) )"),TRUE()) -> TRUE | G2: =IFERROR(__xludf.dummyfunction("LET( raw, INDEX(fakerUSDataset!$A:$CX, ROW(), COLUMN()), hdr, INDEX(fakerUSDataset!$1:$1, COLUMN()), norm, INDEX(ColumnMetaData!$I:$I, MATCH(hdr, ColumnMetaData!$C:$C, 0)), patName, INDEX(ColumnMetaData!$D:$D, MATCH(hdr, ColumnMetaData!$C:$C, 0)),"&" rx, INDEX(RegexPatterns!$B:$B, MATCH(patName, RegexPatterns!$A:$A, 0)), txt, TO_TEXT(raw), normed, SWITCH( norm, ""TRIM"", TRIM(txt), ""LOWERCASE|TRIM"", LOWER(TRIM(txt)), ""UPPERCASE|TRIM"", UPPER(TRIM(txt)), ""DIGITS_ONLY"", R"&"EGEXREPLACE(txt, ""[^0-9]"", """"), ""REMOVE_COMMAS|TRIM"", TRIM(SUBSTITUTE(txt, "","", """")), ""REMOVE_CURRENCY_SYMBOL|REMOVE_COMMAS|TRIM"", TRIM(REGEXREPLACE(SUBSTITUTE(txt, "","", """"), ""[$€£¥]"", """")), ""REMOVE_PERCENT|TRIM"", TRIM(SU"&"BSTITUTE(txt, ""%"", """")), txt ), IF(REGEXMATCH(normed, rx), TRUE, raw) )"),TRUE()) -> TRUE | H2: =IFERROR(__xludf.dummyfunction("LET( raw, INDEX(fakerUSDataset!$A:$CX, ROW(), COLUMN()), hdr, INDEX(fakerUSDataset!$1:$1, COLUMN()), norm, INDEX(ColumnMetaData!$I:$I, MATCH(hdr, ColumnMetaData!$C:$C, 0)), patName, INDEX(ColumnMetaData!$D:$D, MATCH(hdr, ColumnMetaData!$C:$C, 0)),"&" rx, INDEX(RegexPatterns!$B:$B, MATCH(patName, RegexPatterns!$A:$A, 0)), txt, TO_TEXT(raw), normed, SWITCH( norm, ""TRIM"", TRIM(txt), ""LOWERCASE|TRIM"", LOWER(TRIM(txt)), ""UPPERCASE|TRIM"", UPPER(TRIM(txt)), ""DIGITS_ONLY"", R"&"EGEXREPLACE(txt, ""[^0-9]"", """"), ""REMOVE_COMMAS|TRIM"", TRIM(SUBSTITUTE(txt, "","", """")), ""REMOVE_CURRENCY_SYMBOL|REMOVE_COMMAS|TRIM"", TRIM(REGEXREPLACE(SUBSTITUTE(txt, "","", """"), ""[$€£¥]"", """")), ""REMOVE_PERCENT|TRIM"", TRIM(SU"&"BSTITUTE(txt, ""%"", """")), txt ), IF(REGEXMATCH(normed, rx), TRUE, raw) )"),TRUE()) -> TRUE | ... CV2: =IFERROR(__xludf.dummyfunction("LET( raw, INDEX(fakerUSDataset!$A:$CX, ROW(), COLUMN()), hdr, INDEX(fakerUSDataset!$1:$1, COLUMN()), norm, INDEX(ColumnMetaData!$I:$I, MATCH(hdr, ColumnMetaData!$C:$C, 0)), patName, INDEX(ColumnMetaData!$D:$D, MATCH(hdr, ColumnMetaData!$C:$C, 0)),"&" rx, INDEX(RegexPatterns!$B:$B, MATCH(patName, RegexPatterns!$A:$A, 0)), txt, TO_TEXT(raw), normed, SWITCH( norm, ""TRIM"", TRIM(txt), ""LOWERCASE|TRIM"", LOWER(TRIM(txt)), ""UPPERCASE|TRIM"", UPPER(TRIM(txt)), ""DIGITS_ONLY"", R"&"EGEXREPLACE(txt, ""[^0-9]"", """"), ""REMOVE_COMMAS|TRIM"", TRIM(SUBSTITUTE(txt, "","", """")), ""REMOVE_CURRENCY_SYMBOL|REMOVE_COMMAS|TRIM"", TRIM(REGEXREPLACE(SUBSTITUTE(txt, "","", """"), ""[$€£¥]"", """")), ""REMOVE_PERCENT|TRIM"", TRIM(SU"&"BSTITUTE(txt, ""%"", """")), txt ), IF(REGEXMATCH(normed, rx), TRUE, raw) )"),TRUE()) -> TRUE
A3: =IFERROR(__xludf.dummyfunction("LET( raw, INDEX(fakerUSDataset!$A:$CX, ROW(), COLUMN()), hdr, INDEX(fakerUSDataset!$1:$1, COLUMN()), norm, INDEX(ColumnMetaData!$I:$I, MATCH(hdr, ColumnMetaData!$C:$C, 0)), patName, INDEX(ColumnMetaData!$D:$D, MATCH(hdr, ColumnMetaData!$C:$C, 0)),"&" rx, INDEX(RegexPatterns!$B:$B, MATCH(patName, RegexPatterns!$A:$A, 0)), txt, TO_TEXT(raw), normed, SWITCH( norm, ""TRIM"", TRIM(txt), ""LOWERCASE|TRIM"", LOWER(TRIM(txt)), ""UPPERCASE|TRIM"", UPPER(TRIM(txt)), ""DIGITS_ONLY"", R"&"EGEXREPLACE(txt, ""[^0-9]"", """"), ""REMOVE_COMMAS|TRIM"", TRIM(SUBSTITUTE(txt, "","", """")), ""REMOVE_CURRENCY_SYMBOL|REMOVE_COMMAS|TRIM"", TRIM(REGEXREPLACE(SUBSTITUTE(txt, "","", """"), ""[$€£¥]"", """")), ""REMOVE_PERCENT|TRIM"", TRIM(SU"&"BSTITUTE(txt, ""%"", """")), txt ), IF(REGEXMATCH(normed, rx), TRUE, raw) )"),TRUE()) -> TRUE | B3: =IFERROR(__xludf.dummyfunction("LET( raw, INDEX(fakerUSDataset!$A:$CX, ROW(), COLUMN()), hdr, INDEX(fakerUSDataset!$1:$1, COLUMN()), norm, INDEX(ColumnMetaData!$I:$I, MATCH(hdr, ColumnMetaData!$C:$C, 0)), patName, INDEX(ColumnMetaData!$D:$D, MATCH(hdr, ColumnMetaData!$C:$C, 0)),"&" rx, INDEX(RegexPatterns!$B:$B, MATCH(patName, RegexPatterns!$A:$A, 0)), txt, TO_TEXT(raw), normed, SWITCH( norm, ""TRIM"", TRIM(txt), ""LOWERCASE|TRIM"", LOWER(TRIM(txt)), ""UPPERCASE|TRIM"", UPPER(TRIM(txt)), ""DIGITS_ONLY"", R"&"EGEXREPLACE(txt, ""[^0-9]"", """"), ""REMOVE_COMMAS|TRIM"", TRIM(SUBSTITUTE(txt, "","", """")), ""REMOVE_CURRENCY_SYMBOL|REMOVE_COMMAS|TRIM"", TRIM(REGEXREPLACE(SUBSTITUTE(txt, "","", """"), ""[$€£¥]"", """")), ""REMOVE_PERCENT|TRIM"", TRIM(SU"&"BSTITUTE(txt, ""%"", """")), txt ), IF(REGEXMATCH(normed, rx), TRUE, raw) )"),TRUE()) -> TRUE | C3: =IFERROR(__xludf.dummyfunction("LET( raw, INDEX(fakerUSDataset!$A:$CX, ROW(), COLUMN()), hdr, INDEX(fakerUSDataset!$1:$1, COLUMN()), norm, INDEX(ColumnMetaData!$I:$I, MATCH(hdr, ColumnMetaData!$C:$C, 0)), patName, INDEX(ColumnMetaData!$D:$D, MATCH(hdr, ColumnMetaData!$C:$C, 0)),"&" rx, INDEX(RegexPatterns!$B:$B, MATCH(patName, RegexPatterns!$A:$A, 0)), txt, TO_TEXT(raw), normed, SWITCH( norm, ""TRIM"", TRIM(txt), ""LOWERCASE|TRIM"", LOWER(TRIM(txt)), ""UPPERCASE|TRIM"", UPPER(TRIM(txt)), ""DIGITS_ONLY"", R"&"EGEXREPLACE(txt, ""[^0-9]"", """"), ""REMOVE_COMMAS|TRIM"", TRIM(SUBSTITUTE(txt, "","", """")), ""REMOVE_CURRENCY_SYMBOL|REMOVE_COMMAS|TRIM"", TRIM(REGEXREPLACE(SUBSTITUTE(txt, "","", """"), ""[$€£¥]"", """")), ""REMOVE_PERCENT|TRIM"", TRIM(SU"&"BSTITUTE(txt, ""%"", """")), txt ), IF(REGEXMATCH(normed, rx), TRUE, raw) )"),TRUE()) -> TRUE | D3: =IFERROR(__xludf.dummyfunction("LET( raw, INDEX(fakerUSDataset!$A:$CX, ROW(), COLUMN()), hdr, INDEX(fakerUSDataset!$1:$1, COLUMN()), norm, INDEX(ColumnMetaData!$I:$I, MATCH(hdr, ColumnMetaData!$C:$C, 0)), patName, INDEX(ColumnMetaData!$D:$D, MATCH(hdr, ColumnMetaData!$C:$C, 0)),"&" rx, INDEX(RegexPatterns!$B:$B, MATCH(patName, RegexPatterns!$A:$A, 0)), txt, TO_TEXT(raw), normed, SWITCH( norm, ""TRIM"", TRIM(txt), ""LOWERCASE|TRIM"", LOWER(TRIM(txt)), ""UPPERCASE|TRIM"", UPPER(TRIM(txt)), ""DIGITS_ONLY"", R"&"EGEXREPLACE(txt, ""[^0-9]"", """"), ""REMOVE_COMMAS|TRIM"", TRIM(SUBSTITUTE(txt, "","", """")), ""REMOVE_CURRENCY_SYMBOL|REMOVE_COMMAS|TRIM"", TRIM(REGEXREPLACE(SUBSTITUTE(txt, "","", """"), ""[$€£¥]"", """")), ""REMOVE_PERCENT|TRIM"", TRIM(SU"&"BSTITUTE(txt, ""%"", """")), txt ), IF(REGEXMATCH(normed, rx), TRUE, raw) )"),TRUE()) -> TRUE | E3: =IFERROR(__xludf.dummyfunction("LET( raw, INDEX(fakerUSDataset!$A:$CX, ROW(), COLUMN()), hdr, INDEX(fakerUSDataset!$1:$1, COLUMN()), norm, INDEX(ColumnMetaData!$I:$I, MATCH(hdr, ColumnMetaData!$C:$C, 0)), patName, INDEX(ColumnMetaData!$D:$D, MATCH(hdr, ColumnMetaData!$C:$C, 0)),"&" rx, INDEX(RegexPatterns!$B:$B, MATCH(patName, RegexPatterns!$A:$A, 0)), txt, TO_TEXT(raw), normed, SWITCH( norm, ""TRIM"", TRIM(txt), ""LOWERCASE|TRIM"", LOWER(TRIM(txt)), ""UPPERCASE|TRIM"", UPPER(TRIM(txt)), ""DIGITS_ONLY"", R"&"EGEXREPLACE(txt, ""[^0-9]"", """"), ""REMOVE_COMMAS|TRIM"", TRIM(SUBSTITUTE(txt, "","", """")), ""REMOVE_CURRENCY_SYMBOL|REMOVE_COMMAS|TRIM"", TRIM(REGEXREPLACE(SUBSTITUTE(txt, "","", """"), ""[$€£¥]"", """")), ""REMOVE_PERCENT|TRIM"", TRIM(SU"&"BSTITUTE(txt, ""%"", """")), txt ), IF(REGEXMATCH(normed, rx), TRUE, raw) )"),TRUE()) -> TRUE | F3: =IFERROR(__xludf.dummyfunction("LET( raw, INDEX(fakerUSDataset!$A:$CX, ROW(), COLUMN()), hdr, INDEX(fakerUSDataset!$1:$1, COLUMN()), norm, INDEX(ColumnMetaData!$I:$I, MATCH(hdr, ColumnMetaData!$C:$C, 0)), patName, INDEX(ColumnMetaData!$D:$D, MATCH(hdr, ColumnMetaData!$C:$C, 0)),"&" rx, INDEX(RegexPatterns!$B:$B, MATCH(patName, RegexPatterns!$A:$A, 0)), txt, TO_TEXT(raw), normed, SWITCH( norm, ""TRIM"", TRIM(txt), ""LOWERCASE|TRIM"", LOWER(TRIM(txt)), ""UPPERCASE|TRIM"", UPPER(TRIM(txt)), ""DIGITS_ONLY"", R"&"EGEXREPLACE(txt, ""[^0-9]"", """"), ""REMOVE_COMMAS|TRIM"", TRIM(SUBSTITUTE(txt, "","", """")), ""REMOVE_CURRENCY_SYMBOL|REMOVE_COMMAS|TRIM"", TRIM(REGEXREPLACE(SUBSTITUTE(txt, "","", """"), ""[$€£¥]"", """")), ""REMOVE_PERCENT|TRIM"", TRIM(SU"&"BSTITUTE(txt, ""%"", """")), txt ), IF(REGEXMATCH(normed, rx), TRUE, raw) )"),TRUE()) -> TRUE | G3: =IFERROR(__xludf.dummyfunction("LET( raw, INDEX(fakerUSDataset!$A:$CX, ROW(), COLUMN()), hdr, INDEX(fakerUSDataset!$1:$1, COLUMN()), norm, INDEX(ColumnMetaData!$I:$I, MATCH(hdr, ColumnMetaData!$C:$C, 0)), patName, INDEX(ColumnMetaData!$D:$D, MATCH(hdr, ColumnMetaData!$C:$C, 0)),"&" rx, INDEX(RegexPatterns!$B:$B, MATCH(patName, RegexPatterns!$A:$A, 0)), txt, TO_TEXT(raw), normed, SWITCH( norm, ""TRIM"", TRIM(txt), ""LOWERCASE|TRIM"", LOWER(TRIM(txt)), ""UPPERCASE|TRIM"", UPPER(TRIM(txt)), ""DIGITS_ONLY"", R"&"EGEXREPLACE(txt, ""[^0-9]"", """"), ""REMOVE_COMMAS|TRIM"", TRIM(SUBSTITUTE(txt, "","", """")), ""REMOVE_CURRENCY_SYMBOL|REMOVE_COMMAS|TRIM"", TRIM(REGEXREPLACE(SUBSTITUTE(txt, "","", """"), ""[$€£¥]"", """")), ""REMOVE_PERCENT|TRIM"", TRIM(SU"&"BSTITUTE(txt, ""%"", """")), txt ), IF(REGEXMATCH(normed, rx), TRUE, raw) )"),TRUE()) -> TRUE | H3: =IFERROR(__xludf.dummyfunction("LET( raw, INDEX(fakerUSDataset!$A:$CX, ROW(), COLUMN()), hdr, INDEX(fakerUSDataset!$1:$1, COLUMN()), norm, INDEX(ColumnMetaData!$I:$I, MATCH(hdr, ColumnMetaData!$C:$C, 0)), patName, INDEX(ColumnMetaData!$D:$D, MATCH(hdr, ColumnMetaData!$C:$C, 0)),"&" rx, INDEX(RegexPatterns!$B:$B, MATCH(patName, RegexPatterns!$A:$A, 0)), txt, TO_TEXT(raw), normed, SWITCH( norm, ""TRIM"", TRIM(txt), ""LOWERCASE|TRIM"", LOWER(TRIM(txt)), ""UPPERCASE|TRIM"", UPPER(TRIM(txt)), ""DIGITS_ONLY"", R"&"EGEXREPLACE(txt, ""[^0-9]"", """"), ""REMOVE_COMMAS|TRIM"", TRIM(SUBSTITUTE(txt, "","", """")), ""REMOVE_CURRENCY_SYMBOL|REMOVE_COMMAS|TRIM"", TRIM(REGEXREPLACE(SUBSTITUTE(txt, "","", """"), ""[$€£¥]"", """")), ""REMOVE_PERCENT|TRIM"", TRIM(SU"&"BSTITUTE(txt, ""%"", """")), txt ), IF(REGEXMATCH(normed, rx), TRUE, raw) )"),TRUE()) -> TRUE | ... CV3: =IFERROR(__xludf.dummyfunction("LET( raw, INDEX(fakerUSDataset!$A:$CX, ROW(), COLUMN()), hdr, INDEX(fakerUSDataset!$1:$1, COLUMN()), norm, INDEX(ColumnMetaData!$I:$I, MATCH(hdr, ColumnMetaData!$C:$C, 0)), patName, INDEX(ColumnMetaData!$D:$D, MATCH(hdr, ColumnMetaData!$C:$C, 0)),"&" rx, INDEX(RegexPatterns!$B:$B, MATCH(patName, RegexPatterns!$A:$A, 0)), txt, TO_TEXT(raw), normed, SWITCH( norm, ""TRIM"", TRIM(txt), ""LOWERCASE|TRIM"", LOWER(TRIM(txt)), ""UPPERCASE|TRIM"", UPPER(TRIM(txt)), ""DIGITS_ONLY"", R"&"EGEXREPLACE(txt, ""[^0-9]"", """"), ""REMOVE_COMMAS|TRIM"", TRIM(SUBSTITUTE(txt, "","", """")), ""REMOVE_CURRENCY_SYMBOL|REMOVE_COMMAS|TRIM"", TRIM(REGEXREPLACE(SUBSTITUTE(txt, "","", """"), ""[$€£¥]"", """")), ""REMOVE_PERCENT|TRIM"", TRIM(SU"&"BSTITUTE(txt, ""%"", """")), txt ), IF(REGEXMATCH(normed, rx), TRUE, raw) )"),TRUE()) -> TRUE
A4: =IFERROR(__xludf.dummyfunction("LET( raw, INDEX(fakerUSDataset!$A:$CX, ROW(), COLUMN()), hdr, INDEX(fakerUSDataset!$1:$1, COLUMN()), norm, INDEX(ColumnMetaData!$I:$I, MATCH(hdr, ColumnMetaData!$C:$C, 0)), patName, INDEX(ColumnMetaData!$D:$D, MATCH(hdr, ColumnMetaData!$C:$C, 0)),"&" rx, INDEX(RegexPatterns!$B:$B, MATCH(patName, RegexPatterns!$A:$A, 0)), txt, TO_TEXT(raw), normed, SWITCH( norm, ""TRIM"", TRIM(txt), ""LOWERCASE|TRIM"", LOWER(TRIM(txt)), ""UPPERCASE|TRIM"", UPPER(TRIM(txt)), ""DIGITS_ONLY"", R"&"EGEXREPLACE(txt, ""[^0-9]"", """"), ""REMOVE_COMMAS|TRIM"", TRIM(SUBSTITUTE(txt, "","", """")), ""REMOVE_CURRENCY_SYMBOL|REMOVE_COMMAS|TRIM"", TRIM(REGEXREPLACE(SUBSTITUTE(txt, "","", """"), ""[$€£¥]"", """")), ""REMOVE_PERCENT|TRIM"", TRIM(SU"&"BSTITUTE(txt, ""%"", """")), txt ), IF(REGEXMATCH(normed, rx), TRUE, raw) )"),TRUE()) -> TRUE | B4: =IFERROR(__xludf.dummyfunction("LET( raw, INDEX(fakerUSDataset!$A:$CX, ROW(), COLUMN()), hdr, INDEX(fakerUSDataset!$1:$1, COLUMN()), norm, INDEX(ColumnMetaData!$I:$I, MATCH(hdr, ColumnMetaData!$C:$C, 0)), patName, INDEX(ColumnMetaData!$D:$D, MATCH(hdr, ColumnMetaData!$C:$C, 0)),"&" rx, INDEX(RegexPatterns!$B:$B, MATCH(patName, RegexPatterns!$A:$A, 0)), txt, TO_TEXT(raw), normed, SWITCH( norm, ""TRIM"", TRIM(txt), ""LOWERCASE|TRIM"", LOWER(TRIM(txt)), ""UPPERCASE|TRIM"", UPPER(TRIM(txt)), ""DIGITS_ONLY"", R"&"EGEXREPLACE(txt, ""[^0-9]"", """"), ""REMOVE_COMMAS|TRIM"", TRIM(SUBSTITUTE(txt, "","", """")), ""REMOVE_CURRENCY_SYMBOL|REMOVE_COMMAS|TRIM"", TRIM(REGEXREPLACE(SUBSTITUTE(txt, "","", """"), ""[$€£¥]"", """")), ""REMOVE_PERCENT|TRIM"", TRIM(SU"&"BSTITUTE(txt, ""%"", """")), txt ), IF(REGEXMATCH(normed, rx), TRUE, raw) )"),TRUE()) -> TRUE | C4: =IFERROR(__xludf.dummyfunction("LET( raw, INDEX(fakerUSDataset!$A:$CX, ROW(), COLUMN()), hdr, INDEX(fakerUSDataset!$1:$1, COLUMN()), norm, INDEX(ColumnMetaData!$I:$I, MATCH(hdr, ColumnMetaData!$C:$C, 0)), patName, INDEX(ColumnMetaData!$D:$D, MATCH(hdr, ColumnMetaData!$C:$C, 0)),"&" rx, INDEX(RegexPatterns!$B:$B, MATCH(patName, RegexPatterns!$A:$A, 0)), txt, TO_TEXT(raw), normed, SWITCH( norm, ""TRIM"", TRIM(txt), ""LOWERCASE|TRIM"", LOWER(TRIM(txt)), ""UPPERCASE|TRIM"", UPPER(TRIM(txt)), ""DIGITS_ONLY"", R"&"EGEXREPLACE(txt, ""[^0-9]"", """"), ""REMOVE_COMMAS|TRIM"", TRIM(SUBSTITUTE(txt, "","", """")), ""REMOVE_CURRENCY_SYMBOL|REMOVE_COMMAS|TRIM"", TRIM(REGEXREPLACE(SUBSTITUTE(txt, "","", """"), ""[$€£¥]"", """")), ""REMOVE_PERCENT|TRIM"", TRIM(SU"&"BSTITUTE(txt, ""%"", """")), txt ), IF(REGEXMATCH(normed, rx), TRUE, raw) )"),TRUE()) -> TRUE | D4: =IFERROR(__xludf.dummyfunction("LET( raw, INDEX(fakerUSDataset!$A:$CX, ROW(), COLUMN()), hdr, INDEX(fakerUSDataset!$1:$1, COLUMN()), norm, INDEX(ColumnMetaData!$I:$I, MATCH(hdr, ColumnMetaData!$C:$C, 0)), patName, INDEX(ColumnMetaData!$D:$D, MATCH(hdr, ColumnMetaData!$C:$C, 0)),"&" rx, INDEX(RegexPatterns!$B:$B, MATCH(patName, RegexPatterns!$A:$A, 0)), txt, TO_TEXT(raw), normed, SWITCH( norm, ""TRIM"", TRIM(txt), ""LOWERCASE|TRIM"", LOWER(TRIM(txt)), ""UPPERCASE|TRIM"", UPPER(TRIM(txt)), ""DIGITS_ONLY"", R"&"EGEXREPLACE(txt, ""[^0-9]"", """"), ""REMOVE_COMMAS|TRIM"", TRIM(SUBSTITUTE(txt, "","", """")), ""REMOVE_CURRENCY_SYMBOL|REMOVE_COMMAS|TRIM"", TRIM(REGEXREPLACE(SUBSTITUTE(txt, "","", """"), ""[$€£¥]"", """")), ""REMOVE_PERCENT|TRIM"", TRIM(SU"&"BSTITUTE(txt, ""%"", """")), txt ), IF(REGEXMATCH(normed, rx), TRUE, raw) )"),TRUE()) -> TRUE | E4: =IFERROR(__xludf.dummyfunction("LET( raw, INDEX(fakerUSDataset!$A:$CX, ROW(), COLUMN()), hdr, INDEX(fakerUSDataset!$1:$1, COLUMN()), norm, INDEX(ColumnMetaData!$I:$I, MATCH(hdr, ColumnMetaData!$C:$C, 0)), patName, INDEX(ColumnMetaData!$D:$D, MATCH(hdr, ColumnMetaData!$C:$C, 0)),"&" rx, INDEX(RegexPatterns!$B:$B, MATCH(patName, RegexPatterns!$A:$A, 0)), txt, TO_TEXT(raw), normed, SWITCH( norm, ""TRIM"", TRIM(txt), ""LOWERCASE|TRIM"", LOWER(TRIM(txt)), ""UPPERCASE|TRIM"", UPPER(TRIM(txt)), ""DIGITS_ONLY"", R"&"EGEXREPLACE(txt, ""[^0-9]"", """"), ""REMOVE_COMMAS|TRIM"", TRIM(SUBSTITUTE(txt, "","", """")), ""REMOVE_CURRENCY_SYMBOL|REMOVE_COMMAS|TRIM"", TRIM(REGEXREPLACE(SUBSTITUTE(txt, "","", """"), ""[$€£¥]"", """")), ""REMOVE_PERCENT|TRIM"", TRIM(SU"&"BSTITUTE(txt, ""%"", """")), txt ), IF(REGEXMATCH(normed, rx), TRUE, raw) )"),TRUE()) -> TRUE | F4: =IFERROR(__xludf.dummyfunction("LET( raw, INDEX(fakerUSDataset!$A:$CX, ROW(), COLUMN()), hdr, INDEX(fakerUSDataset!$1:$1, COLUMN()), norm, INDEX(ColumnMetaData!$I:$I, MATCH(hdr, ColumnMetaData!$C:$C, 0)), patName, INDEX(ColumnMetaData!$D:$D, MATCH(hdr, ColumnMetaData!$C:$C, 0)),"&" rx, INDEX(RegexPatterns!$B:$B, MATCH(patName, RegexPatterns!$A:$A, 0)), txt, TO_TEXT(raw), normed, SWITCH( norm, ""TRIM"", TRIM(txt), ""LOWERCASE|TRIM"", LOWER(TRIM(txt)), ""UPPERCASE|TRIM"", UPPER(TRIM(txt)), ""DIGITS_ONLY"", R"&"EGEXREPLACE(txt, ""[^0-9]"", """"), ""REMOVE_COMMAS|TRIM"", TRIM(SUBSTITUTE(txt, "","", """")), ""REMOVE_CURRENCY_SYMBOL|REMOVE_COMMAS|TRIM"", TRIM(REGEXREPLACE(SUBSTITUTE(txt, "","", """"), ""[$€£¥]"", """")), ""REMOVE_PERCENT|TRIM"", TRIM(SU"&"BSTITUTE(txt, ""%"", """")), txt ), IF(REGEXMATCH(normed, rx), TRUE, raw) )"),TRUE()) -> TRUE | G4: =IFERROR(__xludf.dummyfunction("LET( raw, INDEX(fakerUSDataset!$A:$CX, ROW(), COLUMN()), hdr, INDEX(fakerUSDataset!$1:$1, COLUMN()), norm, INDEX(ColumnMetaData!$I:$I, MATCH(hdr, ColumnMetaData!$C:$C, 0)), patName, INDEX(ColumnMetaData!$D:$D, MATCH(hdr, ColumnMetaData!$C:$C, 0)),"&" rx, INDEX(RegexPatterns!$B:$B, MATCH(patName, RegexPatterns!$A:$A, 0)), txt, TO_TEXT(raw), normed, SWITCH( norm, ""TRIM"", TRIM(txt), ""LOWERCASE|TRIM"", LOWER(TRIM(txt)), ""UPPERCASE|TRIM"", UPPER(TRIM(txt)), ""DIGITS_ONLY"", R"&"EGEXREPLACE(txt, ""[^0-9]"", """"), ""REMOVE_COMMAS|TRIM"", TRIM(SUBSTITUTE(txt, "","", """")), ""REMOVE_CURRENCY_SYMBOL|REMOVE_COMMAS|TRIM"", TRIM(REGEXREPLACE(SUBSTITUTE(txt, "","", """"), ""[$€£¥]"", """")), ""REMOVE_PERCENT|TRIM"", TRIM(SU"&"BSTITUTE(txt, ""%"", """")), txt ), IF(REGEXMATCH(normed, rx), TRUE, raw) )"),TRUE()) -> TRUE | H4: =IFERROR(__xludf.dummyfunction("LET( raw, INDEX(fakerUSDataset!$A:$CX, ROW(), COLUMN()), hdr, INDEX(fakerUSDataset!$1:$1, COLUMN()), norm, INDEX(ColumnMetaData!$I:$I, MATCH(hdr, ColumnMetaData!$C:$C, 0)), patName, INDEX(ColumnMetaData!$D:$D, MATCH(hdr, ColumnMetaData!$C:$C, 0)),"&" rx, INDEX(RegexPatterns!$B:$B, MATCH(patName, RegexPatterns!$A:$A, 0)), txt, TO_TEXT(raw), normed, SWITCH( norm, ""TRIM"", TRIM(txt), ""LOWERCASE|TRIM"", LOWER(TRIM(txt)), ""UPPERCASE|TRIM"", UPPER(TRIM(txt)), ""DIGITS_ONLY"", R"&"EGEXREPLACE(txt, ""[^0-9]"", """"), ""REMOVE_COMMAS|TRIM"", TRIM(SUBSTITUTE(txt, "","", """")), ""REMOVE_CURRENCY_SYMBOL|REMOVE_COMMAS|TRIM"", TRIM(REGEXREPLACE(SUBSTITUTE(txt, "","", """"), ""[$€£¥]"", """")), ""REMOVE_PERCENT|TRIM"", TRIM(SU"&"BSTITUTE(txt, ""%"", """")), txt ), IF(REGEXMATCH(normed, rx), TRUE, raw) )"),TRUE()) -> TRUE | ... CV4: =IFERROR(__xludf.dummyfunction("LET( raw, INDEX(fakerUSDataset!$A:$CX, ROW(), COLUMN()), hdr, INDEX(fakerUSDataset!$1:$1, COLUMN()), norm, INDEX(ColumnMetaData!$I:$I, MATCH(hdr, ColumnMetaData!$C:$C, 0)), patName, INDEX(ColumnMetaData!$D:$D, MATCH(hdr, ColumnMetaData!$C:$C, 0)),"&" rx, INDEX(RegexPatterns!$B:$B, MATCH(patName, RegexPatterns!$A:$A, 0)), txt, TO_TEXT(raw), normed, SWITCH( norm, ""TRIM"", TRIM(txt), ""LOWERCASE|TRIM"", LOWER(TRIM(txt)), ""UPPERCASE|TRIM"", UPPER(TRIM(txt)), ""DIGITS_ONLY"", R"&"EGEXREPLACE(txt, ""[^0-9]"", """"), ""REMOVE_COMMAS|TRIM"", TRIM(SUBSTITUTE(txt, "","", """")), ""REMOVE_CURRENCY_SYMBOL|REMOVE_COMMAS|TRIM"", TRIM(REGEXREPLACE(SUBSTITUTE(txt, "","", """"), ""[$€£¥]"", """")), ""REMOVE_PERCENT|TRIM"", TRIM(SU"&"BSTITUTE(txt, ""%"", """")), txt ), IF(REGEXMATCH(normed, rx), TRUE, raw) )"),TRUE()) -> TRUE
A5: =IFERROR(__xludf.dummyfunction("LET( raw, INDEX(fakerUSDataset!$A:$CX, ROW(), COLUMN()), hdr, INDEX(fakerUSDataset!$1:$1, COLUMN()), norm, INDEX(ColumnMetaData!$I:$I, MATCH(hdr, ColumnMetaData!$C:$C, 0)), patName, INDEX(ColumnMetaData!$D:$D, MATCH(hdr, ColumnMetaData!$C:$C, 0)),"&" rx, INDEX(RegexPatterns!$B:$B, MATCH(patName, RegexPatterns!$A:$A, 0)), txt, TO_TEXT(raw), normed, SWITCH( norm, ""TRIM"", TRIM(txt), ""LOWERCASE|TRIM"", LOWER(TRIM(txt)), ""UPPERCASE|TRIM"", UPPER(TRIM(txt)), ""DIGITS_ONLY"", R"&"EGEXREPLACE(txt, ""[^0-9]"", """"), ""REMOVE_COMMAS|TRIM"", TRIM(SUBSTITUTE(txt, "","", """")), ""REMOVE_CURRENCY_SYMBOL|REMOVE_COMMAS|TRIM"", TRIM(REGEXREPLACE(SUBSTITUTE(txt, "","", """"), ""[$€£¥]"", """")), ""REMOVE_PERCENT|TRIM"", TRIM(SU"&"BSTITUTE(txt, ""%"", """")), txt ), IF(REGEXMATCH(normed, rx), TRUE, raw) )"),TRUE()) -> TRUE | B5: =IFERROR(__xludf.dummyfunction("LET( raw, INDEX(fakerUSDataset!$A:$CX, ROW(), COLUMN()), hdr, INDEX(fakerUSDataset!$1:$1, COLUMN()), norm, INDEX(ColumnMetaData!$I:$I, MATCH(hdr, ColumnMetaData!$C:$C, 0)), patName, INDEX(ColumnMetaData!$D:$D, MATCH(hdr, ColumnMetaData!$C:$C, 0)),"&" rx, INDEX(RegexPatterns!$B:$B, MATCH(patName, RegexPatterns!$A:$A, 0)), txt, TO_TEXT(raw), normed, SWITCH( norm, ""TRIM"", TRIM(txt), ""LOWERCASE|TRIM"", LOWER(TRIM(txt)), ""UPPERCASE|TRIM"", UPPER(TRIM(txt)), ""DIGITS_ONLY"", R"&"EGEXREPLACE(txt, ""[^0-9]"", """"), ""REMOVE_COMMAS|TRIM"", TRIM(SUBSTITUTE(txt, "","", """")), ""REMOVE_CURRENCY_SYMBOL|REMOVE_COMMAS|TRIM"", TRIM(REGEXREPLACE(SUBSTITUTE(txt, "","", """"), ""[$€£¥]"", """")), ""REMOVE_PERCENT|TRIM"", TRIM(SU"&"BSTITUTE(txt, ""%"", """")), txt ), IF(REGEXMATCH(normed, rx), TRUE, raw) )"),TRUE()) -> TRUE | C5: =IFERROR(__xludf.dummyfunction("LET( raw, INDEX(fakerUSDataset!$A:$CX, ROW(), COLUMN()), hdr, INDEX(fakerUSDataset!$1:$1, COLUMN()), norm, INDEX(ColumnMetaData!$I:$I, MATCH(hdr, ColumnMetaData!$C:$C, 0)), patName, INDEX(ColumnMetaData!$D:$D, MATCH(hdr, ColumnMetaData!$C:$C, 0)),"&" rx, INDEX(RegexPatterns!$B:$B, MATCH(patName, RegexPatterns!$A:$A, 0)), txt, TO_TEXT(raw), normed, SWITCH( norm, ""TRIM"", TRIM(txt), ""LOWERCASE|TRIM"", LOWER(TRIM(txt)), ""UPPERCASE|TRIM"", UPPER(TRIM(txt)), ""DIGITS_ONLY"", R"&"EGEXREPLACE(txt, ""[^0-9]"", """"), ""REMOVE_COMMAS|TRIM"", TRIM(SUBSTITUTE(txt, "","", """")), ""REMOVE_CURRENCY_SYMBOL|REMOVE_COMMAS|TRIM"", TRIM(REGEXREPLACE(SUBSTITUTE(txt, "","", """"), ""[$€£¥]"", """")), ""REMOVE_PERCENT|TRIM"", TRIM(SU"&"BSTITUTE(txt, ""%"", """")), txt ), IF(REGEXMATCH(normed, rx), TRUE, raw) )"),TRUE()) -> TRUE | D5: =IFERROR(__xludf.dummyfunction("LET( raw, INDEX(fakerUSDataset!$A:$CX, ROW(), COLUMN()), hdr, INDEX(fakerUSDataset!$1:$1, COLUMN()), norm, INDEX(ColumnMetaData!$I:$I, MATCH(hdr, ColumnMetaData!$C:$C, 0)), patName, INDEX(ColumnMetaData!$D:$D, MATCH(hdr, ColumnMetaData!$C:$C, 0)),"&" rx, INDEX(RegexPatterns!$B:$B, MATCH(patName, RegexPatterns!$A:$A, 0)), txt, TO_TEXT(raw), normed, SWITCH( norm, ""TRIM"", TRIM(txt), ""LOWERCASE|TRIM"", LOWER(TRIM(txt)), ""UPPERCASE|TRIM"", UPPER(TRIM(txt)), ""DIGITS_ONLY"", R"&"EGEXREPLACE(txt, ""[^0-9]"", """"), ""REMOVE_COMMAS|TRIM"", TRIM(SUBSTITUTE(txt, "","", """")), ""REMOVE_CURRENCY_SYMBOL|REMOVE_COMMAS|TRIM"", TRIM(REGEXREPLACE(SUBSTITUTE(txt, "","", """"), ""[$€£¥]"", """")), ""REMOVE_PERCENT|TRIM"", TRIM(SU"&"BSTITUTE(txt, ""%"", """")), txt ), IF(REGEXMATCH(normed, rx), TRUE, raw) )"),TRUE()) -> TRUE | E5: =IFERROR(__xludf.dummyfunction("LET( raw, INDEX(fakerUSDataset!$A:$CX, ROW(), COLUMN()), hdr, INDEX(fakerUSDataset!$1:$1, COLUMN()), norm, INDEX(ColumnMetaData!$I:$I, MATCH(hdr, ColumnMetaData!$C:$C, 0)), patName, INDEX(ColumnMetaData!$D:$D, MATCH(hdr, ColumnMetaData!$C:$C, 0)),"&" rx, INDEX(RegexPatterns!$B:$B, MATCH(patName, RegexPatterns!$A:$A, 0)), txt, TO_TEXT(raw), normed, SWITCH( norm, ""TRIM"", TRIM(txt), ""LOWERCASE|TRIM"", LOWER(TRIM(txt)), ""UPPERCASE|TRIM"", UPPER(TRIM(txt)), ""DIGITS_ONLY"", R"&"EGEXREPLACE(txt, ""[^0-9]"", """"), ""REMOVE_COMMAS|TRIM"", TRIM(SUBSTITUTE(txt, "","", """")), ""REMOVE_CURRENCY_SYMBOL|REMOVE_COMMAS|TRIM"", TRIM(REGEXREPLACE(SUBSTITUTE(txt, "","", """"), ""[$€£¥]"", """")), ""REMOVE_PERCENT|TRIM"", TRIM(SU"&"BSTITUTE(txt, ""%"", """")), txt ), IF(REGEXMATCH(normed, rx), TRUE, raw) )"),TRUE()) -> TRUE | F5: =IFERROR(__xludf.dummyfunction("LET( raw, INDEX(fakerUSDataset!$A:$CX, ROW(), COLUMN()), hdr, INDEX(fakerUSDataset!$1:$1, COLUMN()), norm, INDEX(ColumnMetaData!$I:$I, MATCH(hdr, ColumnMetaData!$C:$C, 0)), patName, INDEX(ColumnMetaData!$D:$D, MATCH(hdr, ColumnMetaData!$C:$C, 0)),"&" rx, INDEX(RegexPatterns!$B:$B, MATCH(patName, RegexPatterns!$A:$A, 0)), txt, TO_TEXT(raw), normed, SWITCH( norm, ""TRIM"", TRIM(txt), ""LOWERCASE|TRIM"", LOWER(TRIM(txt)), ""UPPERCASE|TRIM"", UPPER(TRIM(txt)), ""DIGITS_ONLY"", R"&"EGEXREPLACE(txt, ""[^0-9]"", """"), ""REMOVE_COMMAS|TRIM"", TRIM(SUBSTITUTE(txt, "","", """")), ""REMOVE_CURRENCY_SYMBOL|REMOVE_COMMAS|TRIM"", TRIM(REGEXREPLACE(SUBSTITUTE(txt, "","", """"), ""[$€£¥]"", """")), ""REMOVE_PERCENT|TRIM"", TRIM(SU"&"BSTITUTE(txt, ""%"", """")), txt ), IF(REGEXMATCH(normed, rx), TRUE, raw) )"),TRUE()) -> TRUE | G5: =IFERROR(__xludf.dummyfunction("LET( raw, INDEX(fakerUSDataset!$A:$CX, ROW(), COLUMN()), hdr, INDEX(fakerUSDataset!$1:$1, COLUMN()), norm, INDEX(ColumnMetaData!$I:$I, MATCH(hdr, ColumnMetaData!$C:$C, 0)), patName, INDEX(ColumnMetaData!$D:$D, MATCH(hdr, ColumnMetaData!$C:$C, 0)),"&" rx, INDEX(RegexPatterns!$B:$B, MATCH(patName, RegexPatterns!$A:$A, 0)), txt, TO_TEXT(raw), normed, SWITCH( norm, ""TRIM"", TRIM(txt), ""LOWERCASE|TRIM"", LOWER(TRIM(txt)), ""UPPERCASE|TRIM"", UPPER(TRIM(txt)), ""DIGITS_ONLY"", R"&"EGEXREPLACE(txt, ""[^0-9]"", """"), ""REMOVE_COMMAS|TRIM"", TRIM(SUBSTITUTE(txt, "","", """")), ""REMOVE_CURRENCY_SYMBOL|REMOVE_COMMAS|TRIM"", TRIM(REGEXREPLACE(SUBSTITUTE(txt, "","", """"), ""[$€£¥]"", """")), ""REMOVE_PERCENT|TRIM"", TRIM(SU"&"BSTITUTE(txt, ""%"", """")), txt ), IF(REGEXMATCH(normed, rx), TRUE, raw) )"),TRUE()) -> TRUE | H5: =IFERROR(__xludf.dummyfunction("LET( raw, INDEX(fakerUSDataset!$A:$CX, ROW(), COLUMN()), hdr, INDEX(fakerUSDataset!$1:$1, COLUMN()), norm, INDEX(ColumnMetaData!$I:$I, MATCH(hdr, ColumnMetaData!$C:$C, 0)), patName, INDEX(ColumnMetaData!$D:$D, MATCH(hdr, ColumnMetaData!$C:$C, 0)),"&" rx, INDEX(RegexPatterns!$B:$B, MATCH(patName, RegexPatterns!$A:$A, 0)), txt, TO_TEXT(raw), normed, SWITCH( norm, ""TRIM"", TRIM(txt), ""LOWERCASE|TRIM"", LOWER(TRIM(txt)), ""UPPERCASE|TRIM"", UPPER(TRIM(txt)), ""DIGITS_ONLY"", R"&"EGEXREPLACE(txt, ""[^0-9]"", """"), ""REMOVE_COMMAS|TRIM"", TRIM(SUBSTITUTE(txt, "","", """")), ""REMOVE_CURRENCY_SYMBOL|REMOVE_COMMAS|TRIM"", TRIM(REGEXREPLACE(SUBSTITUTE(txt, "","", """"), ""[$€£¥]"", """")), ""REMOVE_PERCENT|TRIM"", TRIM(SU"&"BSTITUTE(txt, ""%"", """")), txt ), IF(REGEXMATCH(normed, rx), TRUE, raw) )"),TRUE()) -> TRUE | ... CV5: =IFERROR(__xludf.dummyfunction("LET( raw, INDEX(fakerUSDataset!$A:$CX, ROW(), COLUMN()), hdr, INDEX(fakerUSDataset!$1:$1, COLUMN()), norm, INDEX(ColumnMetaData!$I:$I, MATCH(hdr, ColumnMetaData!$C:$C, 0)), patName, INDEX(ColumnMetaData!$D:$D, MATCH(hdr, ColumnMetaData!$C:$C, 0)),"&" rx, INDEX(RegexPatterns!$B:$B, MATCH(patName, RegexPatterns!$A:$A, 0)), txt, TO_TEXT(raw), normed, SWITCH( norm, ""TRIM"", TRIM(txt), ""LOWERCASE|TRIM"", LOWER(TRIM(txt)), ""UPPERCASE|TRIM"", UPPER(TRIM(txt)), ""DIGITS_ONLY"", R"&"EGEXREPLACE(txt, ""[^0-9]"", """"), ""REMOVE_COMMAS|TRIM"", TRIM(SUBSTITUTE(txt, "","", """")), ""REMOVE_CURRENCY_SYMBOL|REMOVE_COMMAS|TRIM"", TRIM(REGEXREPLACE(SUBSTITUTE(txt, "","", """"), ""[$€£¥]"", """")), ""REMOVE_PERCENT|TRIM"", TRIM(SU"&"BSTITUTE(txt, ""%"", """")), txt ), IF(REGEXMATCH(normed, rx), TRUE, raw) )"),TRUE()) -> TRUE
A6: =IFERROR(__xludf.dummyfunction("LET( raw, INDEX(fakerUSDataset!$A:$CX, ROW(), COLUMN()), hdr, INDEX(fakerUSDataset!$1:$1, COLUMN()), norm, INDEX(ColumnMetaData!$I:$I, MATCH(hdr, ColumnMetaData!$C:$C, 0)), patName, INDEX(ColumnMetaData!$D:$D, MATCH(hdr, ColumnMetaData!$C:$C, 0)),"&" rx, INDEX(RegexPatterns!$B:$B, MATCH(patName, RegexPatterns!$A:$A, 0)), txt, TO_TEXT(raw), normed, SWITCH( norm, ""TRIM"", TRIM(txt), ""LOWERCASE|TRIM"", LOWER(TRIM(txt)), ""UPPERCASE|TRIM"", UPPER(TRIM(txt)), ""DIGITS_ONLY"", R"&"EGEXREPLACE(txt, ""[^0-9]"", """"), ""REMOVE_COMMAS|TRIM"", TRIM(SUBSTITUTE(txt, "","", """")), ""REMOVE_CURRENCY_SYMBOL|REMOVE_COMMAS|TRIM"", TRIM(REGEXREPLACE(SUBSTITUTE(txt, "","", """"), ""[$€£¥]"", """")), ""REMOVE_PERCENT|TRIM"", TRIM(SU"&"BSTITUTE(txt, ""%"", """")), txt ), IF(REGEXMATCH(normed, rx), TRUE, raw) )"),TRUE()) -> TRUE | B6: =IFERROR(__xludf.dummyfunction("LET( raw, INDEX(fakerUSDataset!$A:$CX, ROW(), COLUMN()), hdr, INDEX(fakerUSDataset!$1:$1, COLUMN()), norm, INDEX(ColumnMetaData!$I:$I, MATCH(hdr, ColumnMetaData!$C:$C, 0)), patName, INDEX(ColumnMetaData!$D:$D, MATCH(hdr, ColumnMetaData!$C:$C, 0)),"&" rx, INDEX(RegexPatterns!$B:$B, MATCH(patName, RegexPatterns!$A:$A, 0)), txt, TO_TEXT(raw), normed, SWITCH( norm, ""TRIM"", TRIM(txt), ""LOWERCASE|TRIM"", LOWER(TRIM(txt)), ""UPPERCASE|TRIM"", UPPER(TRIM(txt)), ""DIGITS_ONLY"", R"&"EGEXREPLACE(txt, ""[^0-9]"", """"), ""REMOVE_COMMAS|TRIM"", TRIM(SUBSTITUTE(txt, "","", """")), ""REMOVE_CURRENCY_SYMBOL|REMOVE_COMMAS|TRIM"", TRIM(REGEXREPLACE(SUBSTITUTE(txt, "","", """"), ""[$€£¥]"", """")), ""REMOVE_PERCENT|TRIM"", TRIM(SU"&"BSTITUTE(txt, ""%"", """")), txt ), IF(REGEXMATCH(normed, rx), TRUE, raw) )"),TRUE()) -> TRUE | C6: =IFERROR(__xludf.dummyfunction("LET( raw, INDEX(fakerUSDataset!$A:$CX, ROW(), COLUMN()), hdr, INDEX(fakerUSDataset!$1:$1, COLUMN()), norm, INDEX(ColumnMetaData!$I:$I, MATCH(hdr, ColumnMetaData!$C:$C, 0)), patName, INDEX(ColumnMetaData!$D:$D, MATCH(hdr, ColumnMetaData!$C:$C, 0)),"&" rx, INDEX(RegexPatterns!$B:$B, MATCH(patName, RegexPatterns!$A:$A, 0)), txt, TO_TEXT(raw), normed, SWITCH( norm, ""TRIM"", TRIM(txt), ""LOWERCASE|TRIM"", LOWER(TRIM(txt)), ""UPPERCASE|TRIM"", UPPER(TRIM(txt)), ""DIGITS_ONLY"", R"&"EGEXREPLACE(txt, ""[^0-9]"", """"), ""REMOVE_COMMAS|TRIM"", TRIM(SUBSTITUTE(txt, "","", """")), ""REMOVE_CURRENCY_SYMBOL|REMOVE_COMMAS|TRIM"", TRIM(REGEXREPLACE(SUBSTITUTE(txt, "","", """"), ""[$€£¥]"", """")), ""REMOVE_PERCENT|TRIM"", TRIM(SU"&"BSTITUTE(txt, ""%"", """")), txt ), IF(REGEXMATCH(normed, rx), TRUE, raw) )"),TRUE()) -> TRUE | D6: =IFERROR(__xludf.dummyfunction("LET( raw, INDEX(fakerUSDataset!$A:$CX, ROW(), COLUMN()), hdr, INDEX(fakerUSDataset!$1:$1, COLUMN()), norm, INDEX(ColumnMetaData!$I:$I, MATCH(hdr, ColumnMetaData!$C:$C, 0)), patName, INDEX(ColumnMetaData!$D:$D, MATCH(hdr, ColumnMetaData!$C:$C, 0)),"&" rx, INDEX(RegexPatterns!$B:$B, MATCH(patName, RegexPatterns!$A:$A, 0)), txt, TO_TEXT(raw), normed, SWITCH( norm, ""TRIM"", TRIM(txt), ""LOWERCASE|TRIM"", LOWER(TRIM(txt)), ""UPPERCASE|TRIM"", UPPER(TRIM(txt)), ""DIGITS_ONLY"", R"&"EGEXREPLACE(txt, ""[^0-9]"", """"), ""REMOVE_COMMAS|TRIM"", TRIM(SUBSTITUTE(txt, "","", """")), ""REMOVE_CURRENCY_SYMBOL|REMOVE_COMMAS|TRIM"", TRIM(REGEXREPLACE(SUBSTITUTE(txt, "","", """"), ""[$€£¥]"", """")), ""REMOVE_PERCENT|TRIM"", TRIM(SU"&"BSTITUTE(txt, ""%"", """")), txt ), IF(REGEXMATCH(normed, rx), TRUE, raw) )"),TRUE()) -> TRUE | E6: =IFERROR(__xludf.dummyfunction("LET( raw, INDEX(fakerUSDataset!$A:$CX, ROW(), COLUMN()), hdr, INDEX(fakerUSDataset!$1:$1, COLUMN()), norm, INDEX(ColumnMetaData!$I:$I, MATCH(hdr, ColumnMetaData!$C:$C, 0)), patName, INDEX(ColumnMetaData!$D:$D, MATCH(hdr, ColumnMetaData!$C:$C, 0)),"&" rx, INDEX(RegexPatterns!$B:$B, MATCH(patName, RegexPatterns!$A:$A, 0)), txt, TO_TEXT(raw), normed, SWITCH( norm, ""TRIM"", TRIM(txt), ""LOWERCASE|TRIM"", LOWER(TRIM(txt)), ""UPPERCASE|TRIM"", UPPER(TRIM(txt)), ""DIGITS_ONLY"", R"&"EGEXREPLACE(txt, ""[^0-9]"", """"), ""REMOVE_COMMAS|TRIM"", TRIM(SUBSTITUTE(txt, "","", """")), ""REMOVE_CURRENCY_SYMBOL|REMOVE_COMMAS|TRIM"", TRIM(REGEXREPLACE(SUBSTITUTE(txt, "","", """"), ""[$€£¥]"", """")), ""REMOVE_PERCENT|TRIM"", TRIM(SU"&"BSTITUTE(txt, ""%"", """")), txt ), IF(REGEXMATCH(normed, rx), TRUE, raw) )"),TRUE()) -> TRUE | F6: =IFERROR(__xludf.dummyfunction("LET( raw, INDEX(fakerUSDataset!$A:$CX, ROW(), COLUMN()), hdr, INDEX(fakerUSDataset!$1:$1, COLUMN()), norm, INDEX(ColumnMetaData!$I:$I, MATCH(hdr, ColumnMetaData!$C:$C, 0)), patName, INDEX(ColumnMetaData!$D:$D, MATCH(hdr, ColumnMetaData!$C:$C, 0)),"&" rx, INDEX(RegexPatterns!$B:$B, MATCH(patName, RegexPatterns!$A:$A, 0)), txt, TO_TEXT(raw), normed, SWITCH( norm, ""TRIM"", TRIM(txt), ""LOWERCASE|TRIM"", LOWER(TRIM(txt)), ""UPPERCASE|TRIM"", UPPER(TRIM(txt)), ""DIGITS_ONLY"", R"&"EGEXREPLACE(txt, ""[^0-9]"", """"), ""REMOVE_COMMAS|TRIM"", TRIM(SUBSTITUTE(txt, "","", """")), ""REMOVE_CURRENCY_SYMBOL|REMOVE_COMMAS|TRIM"", TRIM(REGEXREPLACE(SUBSTITUTE(txt, "","", """"), ""[$€£¥]"", """")), ""REMOVE_PERCENT|TRIM"", TRIM(SU"&"BSTITUTE(txt, ""%"", """")), txt ), IF(REGEXMATCH(normed, rx), TRUE, raw) )"),TRUE()) -> TRUE | G6: =IFERROR(__xludf.dummyfunction("LET( raw, INDEX(fakerUSDataset!$A:$CX, ROW(), COLUMN()), hdr, INDEX(fakerUSDataset!$1:$1, COLUMN()), norm, INDEX(ColumnMetaData!$I:$I, MATCH(hdr, ColumnMetaData!$C:$C, 0)), patName, INDEX(ColumnMetaData!$D:$D, MATCH(hdr, ColumnMetaData!$C:$C, 0)),"&" rx, INDEX(RegexPatterns!$B:$B, MATCH(patName, RegexPatterns!$A:$A, 0)), txt, TO_TEXT(raw), normed, SWITCH( norm, ""TRIM"", TRIM(txt), ""LOWERCASE|TRIM"", LOWER(TRIM(txt)), ""UPPERCASE|TRIM"", UPPER(TRIM(txt)), ""DIGITS_ONLY"", R"&"EGEXREPLACE(txt, ""[^0-9]"", """"), ""REMOVE_COMMAS|TRIM"", TRIM(SUBSTITUTE(txt, "","", """")), ""REMOVE_CURRENCY_SYMBOL|REMOVE_COMMAS|TRIM"", TRIM(REGEXREPLACE(SUBSTITUTE(txt, "","", """"), ""[$€£¥]"", """")), ""REMOVE_PERCENT|TRIM"", TRIM(SU"&"BSTITUTE(txt, ""%"", """")), txt ), IF(REGEXMATCH(normed, rx), TRUE, raw) )"),TRUE()) -> TRUE | H6: =IFERROR(__xludf.dummyfunction("LET( raw, INDEX(fakerUSDataset!$A:$CX, ROW(), COLUMN()), hdr, INDEX(fakerUSDataset!$1:$1, COLUMN()), norm, INDEX(ColumnMetaData!$I:$I, MATCH(hdr, ColumnMetaData!$C:$C, 0)), patName, INDEX(ColumnMetaData!$D:$D, MATCH(hdr, ColumnMetaData!$C:$C, 0)),"&" rx, INDEX(RegexPatterns!$B:$B, MATCH(patName, RegexPatterns!$A:$A, 0)), txt, TO_TEXT(raw), normed, SWITCH( norm, ""TRIM"", TRIM(txt), ""LOWERCASE|TRIM"", LOWER(TRIM(txt)), ""UPPERCASE|TRIM"", UPPER(TRIM(txt)), ""DIGITS_ONLY"", R"&"EGEXREPLACE(txt, ""[^0-9]"", """"), ""REMOVE_COMMAS|TRIM"", TRIM(SUBSTITUTE(txt, "","", """")), ""REMOVE_CURRENCY_SYMBOL|REMOVE_COMMAS|TRIM"", TRIM(REGEXREPLACE(SUBSTITUTE(txt, "","", """"), ""[$€£¥]"", """")), ""REMOVE_PERCENT|TRIM"", TRIM(SU"&"BSTITUTE(txt, ""%"", """")), txt ), IF(REGEXMATCH(normed, rx), TRUE, raw) )"),TRUE()) -> TRUE | ... CV6: =IFERROR(__xludf.dummyfunction("LET( raw, INDEX(fakerUSDataset!$A:$CX, ROW(), COLUMN()), hdr, INDEX(fakerUSDataset!$1:$1, COLUMN()), norm, INDEX(ColumnMetaData!$I:$I, MATCH(hdr, ColumnMetaData!$C:$C, 0)), patName, INDEX(ColumnMetaData!$D:$D, MATCH(hdr, ColumnMetaData!$C:$C, 0)),"&" rx, INDEX(RegexPatterns!$B:$B, MATCH(patName, RegexPatterns!$A:$A, 0)), txt, TO_TEXT(raw), normed, SWITCH( norm, ""TRIM"", TRIM(txt), ""LOWERCASE|TRIM"", LOWER(TRIM(txt)), ""UPPERCASE|TRIM"", UPPER(TRIM(txt)), ""DIGITS_ONLY"", R"&"EGEXREPLACE(txt, ""[^0-9]"", """"), ""REMOVE_COMMAS|TRIM"", TRIM(SUBSTITUTE(txt, "","", """")), ""REMOVE_CURRENCY_SYMBOL|REMOVE_COMMAS|TRIM"", TRIM(REGEXREPLACE(SUBSTITUTE(txt, "","", """"), ""[$€£¥]"", """")), ""REMOVE_PERCENT|TRIM"", TRIM(SU"&"BSTITUTE(txt, ""%"", """")), txt ), IF(REGEXMATCH(normed, rx), TRUE, raw) )"),TRUE()) -> TRUE
A7: =IFERROR(__xludf.dummyfunction("LET( raw, INDEX(fakerUSDataset!$A:$CX, ROW(), COLUMN()), hdr, INDEX(fakerUSDataset!$1:$1, COLUMN()), norm, INDEX(ColumnMetaData!$I:$I, MATCH(hdr, ColumnMetaData!$C:$C, 0)), patName, INDEX(ColumnMetaData!$D:$D, MATCH(hdr, ColumnMetaData!$C:$C, 0)),"&" rx, INDEX(RegexPatterns!$B:$B, MATCH(patName, RegexPatterns!$A:$A, 0)), txt, TO_TEXT(raw), normed, SWITCH( norm, ""TRIM"", TRIM(txt), ""LOWERCASE|TRIM"", LOWER(TRIM(txt)), ""UPPERCASE|TRIM"", UPPER(TRIM(txt)), ""DIGITS_ONLY"", R"&"EGEXREPLACE(txt, ""[^0-9]"", """"), ""REMOVE_COMMAS|TRIM"", TRIM(SUBSTITUTE(txt, "","", """")), ""REMOVE_CURRENCY_SYMBOL|REMOVE_COMMAS|TRIM"", TRIM(REGEXREPLACE(SUBSTITUTE(txt, "","", """"), ""[$€£¥]"", """")), ""REMOVE_PERCENT|TRIM"", TRIM(SU"&"BSTITUTE(txt, ""%"", """")), txt ), IF(REGEXMATCH(normed, rx), TRUE, raw) )"),TRUE()) -> TRUE | B7: =IFERROR(__xludf.dummyfunction("LET( raw, INDEX(fakerUSDataset!$A:$CX, ROW(), COLUMN()), hdr, INDEX(fakerUSDataset!$1:$1, COLUMN()), norm, INDEX(ColumnMetaData!$I:$I, MATCH(hdr, ColumnMetaData!$C:$C, 0)), patName, INDEX(ColumnMetaData!$D:$D, MATCH(hdr, ColumnMetaData!$C:$C, 0)),"&" rx, INDEX(RegexPatterns!$B:$B, MATCH(patName, RegexPatterns!$A:$A, 0)), txt, TO_TEXT(raw), normed, SWITCH( norm, ""TRIM"", TRIM(txt), ""LOWERCASE|TRIM"", LOWER(TRIM(txt)), ""UPPERCASE|TRIM"", UPPER(TRIM(txt)), ""DIGITS_ONLY"", R"&"EGEXREPLACE(txt, ""[^0-9]"", """"), ""REMOVE_COMMAS|TRIM"", TRIM(SUBSTITUTE(txt, "","", """")), ""REMOVE_CURRENCY_SYMBOL|REMOVE_COMMAS|TRIM"", TRIM(REGEXREPLACE(SUBSTITUTE(txt, "","", """"), ""[$€£¥]"", """")), ""REMOVE_PERCENT|TRIM"", TRIM(SU"&"BSTITUTE(txt, ""%"", """")), txt ), IF(REGEXMATCH(normed, rx), TRUE, raw) )"),TRUE()) -> TRUE | C7: =IFERROR(__xludf.dummyfunction("LET( raw, INDEX(fakerUSDataset!$A:$CX, ROW(), COLUMN()), hdr, INDEX(fakerUSDataset!$1:$1, COLUMN()), norm, INDEX(ColumnMetaData!$I:$I, MATCH(hdr, ColumnMetaData!$C:$C, 0)), patName, INDEX(ColumnMetaData!$D:$D, MATCH(hdr, ColumnMetaData!$C:$C, 0)),"&" rx, INDEX(RegexPatterns!$B:$B, MATCH(patName, RegexPatterns!$A:$A, 0)), txt, TO_TEXT(raw), normed, SWITCH( norm, ""TRIM"", TRIM(txt), ""LOWERCASE|TRIM"", LOWER(TRIM(txt)), ""UPPERCASE|TRIM"", UPPER(TRIM(txt)), ""DIGITS_ONLY"", R"&"EGEXREPLACE(txt, ""[^0-9]"", """"), ""REMOVE_COMMAS|TRIM"", TRIM(SUBSTITUTE(txt, "","", """")), ""REMOVE_CURRENCY_SYMBOL|REMOVE_COMMAS|TRIM"", TRIM(REGEXREPLACE(SUBSTITUTE(txt, "","", """"), ""[$€£¥]"", """")), ""REMOVE_PERCENT|TRIM"", TRIM(SU"&"BSTITUTE(txt, ""%"", """")), txt ), IF(REGEXMATCH(normed, rx), TRUE, raw) )"),TRUE()) -> TRUE | D7: =IFERROR(__xludf.dummyfunction("LET( raw, INDEX(fakerUSDataset!$A:$CX, ROW(), COLUMN()), hdr, INDEX(fakerUSDataset!$1:$1, COLUMN()), norm, INDEX(ColumnMetaData!$I:$I, MATCH(hdr, ColumnMetaData!$C:$C, 0)), patName, INDEX(ColumnMetaData!$D:$D, MATCH(hdr, ColumnMetaData!$C:$C, 0)),"&" rx, INDEX(RegexPatterns!$B:$B, MATCH(patName, RegexPatterns!$A:$A, 0)), txt, TO_TEXT(raw), normed, SWITCH( norm, ""TRIM"", TRIM(txt), ""LOWERCASE|TRIM"", LOWER(TRIM(txt)), ""UPPERCASE|TRIM"", UPPER(TRIM(txt)), ""DIGITS_ONLY"", R"&"EGEXREPLACE(txt, ""[^0-9]"", """"), ""REMOVE_COMMAS|TRIM"", TRIM(SUBSTITUTE(txt, "","", """")), ""REMOVE_CURRENCY_SYMBOL|REMOVE_COMMAS|TRIM"", TRIM(REGEXREPLACE(SUBSTITUTE(txt, "","", """"), ""[$€£¥]"", """")), ""REMOVE_PERCENT|TRIM"", TRIM(SU"&"BSTITUTE(txt, ""%"", """")), txt ), IF(REGEXMATCH(normed, rx), TRUE, raw) )"),TRUE()) -> TRUE | E7: =IFERROR(__xludf.dummyfunction("LET( raw, INDEX(fakerUSDataset!$A:$CX, ROW(), COLUMN()), hdr, INDEX(fakerUSDataset!$1:$1, COLUMN()), norm, INDEX(ColumnMetaData!$I:$I, MATCH(hdr, ColumnMetaData!$C:$C, 0)), patName, INDEX(ColumnMetaData!$D:$D, MATCH(hdr, ColumnMetaData!$C:$C, 0)),"&" rx, INDEX(RegexPatterns!$B:$B, MATCH(patName, RegexPatterns!$A:$A, 0)), txt, TO_TEXT(raw), normed, SWITCH( norm, ""TRIM"", TRIM(txt), ""LOWERCASE|TRIM"", LOWER(TRIM(txt)), ""UPPERCASE|TRIM"", UPPER(TRIM(txt)), ""DIGITS_ONLY"", R"&"EGEXREPLACE(txt, ""[^0-9]"", """"), ""REMOVE_COMMAS|TRIM"", TRIM(SUBSTITUTE(txt, "","", """")), ""REMOVE_CURRENCY_SYMBOL|REMOVE_COMMAS|TRIM"", TRIM(REGEXREPLACE(SUBSTITUTE(txt, "","", """"), ""[$€£¥]"", """")), ""REMOVE_PERCENT|TRIM"", TRIM(SU"&"BSTITUTE(txt, ""%"", """")), txt ), IF(REGEXMATCH(normed, rx), TRUE, raw) )"),TRUE()) -> TRUE | F7: =IFERROR(__xludf.dummyfunction("LET( raw, INDEX(fakerUSDataset!$A:$CX, ROW(), COLUMN()), hdr, INDEX(fakerUSDataset!$1:$1, COLUMN()), norm, INDEX(ColumnMetaData!$I:$I, MATCH(hdr, ColumnMetaData!$C:$C, 0)), patName, INDEX(ColumnMetaData!$D:$D, MATCH(hdr, ColumnMetaData!$C:$C, 0)),"&" rx, INDEX(RegexPatterns!$B:$B, MATCH(patName, RegexPatterns!$A:$A, 0)), txt, TO_TEXT(raw), normed, SWITCH( norm, ""TRIM"", TRIM(txt), ""LOWERCASE|TRIM"", LOWER(TRIM(txt)), ""UPPERCASE|TRIM"", UPPER(TRIM(txt)), ""DIGITS_ONLY"", R"&"EGEXREPLACE(txt, ""[^0-9]"", """"), ""REMOVE_COMMAS|TRIM"", TRIM(SUBSTITUTE(txt, "","", """")), ""REMOVE_CURRENCY_SYMBOL|REMOVE_COMMAS|TRIM"", TRIM(REGEXREPLACE(SUBSTITUTE(txt, "","", """"), ""[$€£¥]"", """")), ""REMOVE_PERCENT|TRIM"", TRIM(SU"&"BSTITUTE(txt, ""%"", """")), txt ), IF(REGEXMATCH(normed, rx), TRUE, raw) )"),TRUE()) -> TRUE | G7: =IFERROR(__xludf.dummyfunction("LET( raw, INDEX(fakerUSDataset!$A:$CX, ROW(), COLUMN()), hdr, INDEX(fakerUSDataset!$1:$1, COLUMN()), norm, INDEX(ColumnMetaData!$I:$I, MATCH(hdr, ColumnMetaData!$C:$C, 0)), patName, INDEX(ColumnMetaData!$D:$D, MATCH(hdr, ColumnMetaData!$C:$C, 0)),"&" rx, INDEX(RegexPatterns!$B:$B, MATCH(patName, RegexPatterns!$A:$A, 0)), txt, TO_TEXT(raw), normed, SWITCH( norm, ""TRIM"", TRIM(txt), ""LOWERCASE|TRIM"", LOWER(TRIM(txt)), ""UPPERCASE|TRIM"", UPPER(TRIM(txt)), ""DIGITS_ONLY"", R"&"EGEXREPLACE(txt, ""[^0-9]"", """"), ""REMOVE_COMMAS|TRIM"", TRIM(SUBSTITUTE(txt, "","", """")), ""REMOVE_CURRENCY_SYMBOL|REMOVE_COMMAS|TRIM"", TRIM(REGEXREPLACE(SUBSTITUTE(txt, "","", """"), ""[$€£¥]"", """")), ""REMOVE_PERCENT|TRIM"", TRIM(SU"&"BSTITUTE(txt, ""%"", """")), txt ), IF(REGEXMATCH(normed, rx), TRUE, raw) )"),TRUE()) -> TRUE | H7: =IFERROR(__xludf.dummyfunction("LET( raw, INDEX(fakerUSDataset!$A:$CX, ROW(), COLUMN()), hdr, INDEX(fakerUSDataset!$1:$1, COLUMN()), norm, INDEX(ColumnMetaData!$I:$I, MATCH(hdr, ColumnMetaData!$C:$C, 0)), patName, INDEX(ColumnMetaData!$D:$D, MATCH(hdr, ColumnMetaData!$C:$C, 0)),"&" rx, INDEX(RegexPatterns!$B:$B, MATCH(patName, RegexPatterns!$A:$A, 0)), txt, TO_TEXT(raw), normed, SWITCH( norm, ""TRIM"", TRIM(txt), ""LOWERCASE|TRIM"", LOWER(TRIM(txt)), ""UPPERCASE|TRIM"", UPPER(TRIM(txt)), ""DIGITS_ONLY"", R"&"EGEXREPLACE(txt, ""[^0-9]"", """"), ""REMOVE_COMMAS|TRIM"", TRIM(SUBSTITUTE(txt, "","", """")), ""REMOVE_CURRENCY_SYMBOL|REMOVE_COMMAS|TRIM"", TRIM(REGEXREPLACE(SUBSTITUTE(txt, "","", """"), ""[$€£¥]"", """")), ""REMOVE_PERCENT|TRIM"", TRIM(SU"&"BSTITUTE(txt, ""%"", """")), txt ), IF(REGEXMATCH(normed, rx), TRUE, raw) )"),TRUE()) -> TRUE | ... CV7: =IFERROR(__xludf.dummyfunction("LET( raw, INDEX(fakerUSDataset!$A:$CX, ROW(), COLUMN()), hdr, INDEX(fakerUSDataset!$1:$1, COLUMN()), norm, INDEX(ColumnMetaData!$I:$I, MATCH(hdr, ColumnMetaData!$C:$C, 0)), patName, INDEX(ColumnMetaData!$D:$D, MATCH(hdr, ColumnMetaData!$C:$C, 0)),"&" rx, INDEX(RegexPatterns!$B:$B, MATCH(patName, RegexPatterns!$A:$A, 0)), txt, TO_TEXT(raw), normed, SWITCH( norm, ""TRIM"", TRIM(txt), ""LOWERCASE|TRIM"", LOWER(TRIM(txt)), ""UPPERCASE|TRIM"", UPPER(TRIM(txt)), ""DIGITS_ONLY"", R"&"EGEXREPLACE(txt, ""[^0-9]"", """"), ""REMOVE_COMMAS|TRIM"", TRIM(SUBSTITUTE(txt, "","", """")), ""REMOVE_CURRENCY_SYMBOL|REMOVE_COMMAS|TRIM"", TRIM(REGEXREPLACE(SUBSTITUTE(txt, "","", """"), ""[$€£¥]"", """")), ""REMOVE_PERCENT|TRIM"", TRIM(SU"&"BSTITUTE(txt, ""%"", """")), txt ), IF(REGEXMATCH(normed, rx), TRUE, raw) )"),TRUE()) -> TRUE
A8: =IFERROR(__xludf.dummyfunction("LET( raw, INDEX(fakerUSDataset!$A:$CX, ROW(), COLUMN()), hdr, INDEX(fakerUSDataset!$1:$1, COLUMN()), norm, INDEX(ColumnMetaData!$I:$I, MATCH(hdr, ColumnMetaData!$C:$C, 0)), patName, INDEX(ColumnMetaData!$D:$D, MATCH(hdr, ColumnMetaData!$C:$C, 0)),"&" rx, INDEX(RegexPatterns!$B:$B, MATCH(patName, RegexPatterns!$A:$A, 0)), txt, TO_TEXT(raw), normed, SWITCH( norm, ""TRIM"", TRIM(txt), ""LOWERCASE|TRIM"", LOWER(TRIM(txt)), ""UPPERCASE|TRIM"", UPPER(TRIM(txt)), ""DIGITS_ONLY"", R"&"EGEXREPLACE(txt, ""[^0-9]"", """"), ""REMOVE_COMMAS|TRIM"", TRIM(SUBSTITUTE(txt, "","", """")), ""REMOVE_CURRENCY_SYMBOL|REMOVE_COMMAS|TRIM"", TRIM(REGEXREPLACE(SUBSTITUTE(txt, "","", """"), ""[$€£¥]"", """")), ""REMOVE_PERCENT|TRIM"", TRIM(SU"&"BSTITUTE(txt, ""%"", """")), txt ), IF(REGEXMATCH(normed, rx), TRUE, raw) )"),TRUE()) -> TRUE | B8: =IFERROR(__xludf.dummyfunction("LET( raw, INDEX(fakerUSDataset!$A:$CX, ROW(), COLUMN()), hdr, INDEX(fakerUSDataset!$1:$1, COLUMN()), norm, INDEX(ColumnMetaData!$I:$I, MATCH(hdr, ColumnMetaData!$C:$C, 0)), patName, INDEX(ColumnMetaData!$D:$D, MATCH(hdr, ColumnMetaData!$C:$C, 0)),"&" rx, INDEX(RegexPatterns!$B:$B, MATCH(patName, RegexPatterns!$A:$A, 0)), txt, TO_TEXT(raw), normed, SWITCH( norm, ""TRIM"", TRIM(txt), ""LOWERCASE|TRIM"", LOWER(TRIM(txt)), ""UPPERCASE|TRIM"", UPPER(TRIM(txt)), ""DIGITS_ONLY"", R"&"EGEXREPLACE(txt, ""[^0-9]"", """"), ""REMOVE_COMMAS|TRIM"", TRIM(SUBSTITUTE(txt, "","", """")), ""REMOVE_CURRENCY_SYMBOL|REMOVE_COMMAS|TRIM"", TRIM(REGEXREPLACE(SUBSTITUTE(txt, "","", """"), ""[$€£¥]"", """")), ""REMOVE_PERCENT|TRIM"", TRIM(SU"&"BSTITUTE(txt, ""%"", """")), txt ), IF(REGEXMATCH(normed, rx), TRUE, raw) )"),TRUE()) -> TRUE | C8: =IFERROR(__xludf.dummyfunction("LET( raw, INDEX(fakerUSDataset!$A:$CX, ROW(), COLUMN()), hdr, INDEX(fakerUSDataset!$1:$1, COLUMN()), norm, INDEX(ColumnMetaData!$I:$I, MATCH(hdr, ColumnMetaData!$C:$C, 0)), patName, INDEX(ColumnMetaData!$D:$D, MATCH(hdr, ColumnMetaData!$C:$C, 0)),"&" rx, INDEX(RegexPatterns!$B:$B, MATCH(patName, RegexPatterns!$A:$A, 0)), txt, TO_TEXT(raw), normed, SWITCH( norm, ""TRIM"", TRIM(txt), ""LOWERCASE|TRIM"", LOWER(TRIM(txt)), ""UPPERCASE|TRIM"", UPPER(TRIM(txt)), ""DIGITS_ONLY"", R"&"EGEXREPLACE(txt, ""[^0-9]"", """"), ""REMOVE_COMMAS|TRIM"", TRIM(SUBSTITUTE(txt, "","", """")), ""REMOVE_CURRENCY_SYMBOL|REMOVE_COMMAS|TRIM"", TRIM(REGEXREPLACE(SUBSTITUTE(txt, "","", """"), ""[$€£¥]"", """")), ""REMOVE_PERCENT|TRIM"", TRIM(SU"&"BSTITUTE(txt, ""%"", """")), txt ), IF(REGEXMATCH(normed, rx), TRUE, raw) )"),TRUE()) -> TRUE | D8: =IFERROR(__xludf.dummyfunction("LET( raw, INDEX(fakerUSDataset!$A:$CX, ROW(), COLUMN()), hdr, INDEX(fakerUSDataset!$1:$1, COLUMN()), norm, INDEX(ColumnMetaData!$I:$I, MATCH(hdr, ColumnMetaData!$C:$C, 0)), patName, INDEX(ColumnMetaData!$D:$D, MATCH(hdr, ColumnMetaData!$C:$C, 0)),"&" rx, INDEX(RegexPatterns!$B:$B, MATCH(patName, RegexPatterns!$A:$A, 0)), txt, TO_TEXT(raw), normed, SWITCH( norm, ""TRIM"", TRIM(txt), ""LOWERCASE|TRIM"", LOWER(TRIM(txt)), ""UPPERCASE|TRIM"", UPPER(TRIM(txt)), ""DIGITS_ONLY"", R"&"EGEXREPLACE(txt, ""[^0-9]"", """"), ""REMOVE_COMMAS|TRIM"", TRIM(SUBSTITUTE(txt, "","", """")), ""REMOVE_CURRENCY_SYMBOL|REMOVE_COMMAS|TRIM"", TRIM(REGEXREPLACE(SUBSTITUTE(txt, "","", """"), ""[$€£¥]"", """")), ""REMOVE_PERCENT|TRIM"", TRIM(SU"&"BSTITUTE(txt, ""%"", """")), txt ), IF(REGEXMATCH(normed, rx), TRUE, raw) )"),TRUE()) -> TRUE | E8: =IFERROR(__xludf.dummyfunction("LET( raw, INDEX(fakerUSDataset!$A:$CX, ROW(), COLUMN()), hdr, INDEX(fakerUSDataset!$1:$1, COLUMN()), norm, INDEX(ColumnMetaData!$I:$I, MATCH(hdr, ColumnMetaData!$C:$C, 0)), patName, INDEX(ColumnMetaData!$D:$D, MATCH(hdr, ColumnMetaData!$C:$C, 0)),"&" rx, INDEX(RegexPatterns!$B:$B, MATCH(patName, RegexPatterns!$A:$A, 0)), txt, TO_TEXT(raw), normed, SWITCH( norm, ""TRIM"", TRIM(txt), ""LOWERCASE|TRIM"", LOWER(TRIM(txt)), ""UPPERCASE|TRIM"", UPPER(TRIM(txt)), ""DIGITS_ONLY"", R"&"EGEXREPLACE(txt, ""[^0-9]"", """"), ""REMOVE_COMMAS|TRIM"", TRIM(SUBSTITUTE(txt, "","", """")), ""REMOVE_CURRENCY_SYMBOL|REMOVE_COMMAS|TRIM"", TRIM(REGEXREPLACE(SUBSTITUTE(txt, "","", """"), ""[$€£¥]"", """")), ""REMOVE_PERCENT|TRIM"", TRIM(SU"&"BSTITUTE(txt, ""%"", """")), txt ), IF(REGEXMATCH(normed, rx), TRUE, raw) )"),TRUE()) -> TRUE | F8: =IFERROR(__xludf.dummyfunction("LET( raw, INDEX(fakerUSDataset!$A:$CX, ROW(), COLUMN()), hdr, INDEX(fakerUSDataset!$1:$1, COLUMN()), norm, INDEX(ColumnMetaData!$I:$I, MATCH(hdr, ColumnMetaData!$C:$C, 0)), patName, INDEX(ColumnMetaData!$D:$D, MATCH(hdr, ColumnMetaData!$C:$C, 0)),"&" rx, INDEX(RegexPatterns!$B:$B, MATCH(patName, RegexPatterns!$A:$A, 0)), txt, TO_TEXT(raw), normed, SWITCH( norm, ""TRIM"", TRIM(txt), ""LOWERCASE|TRIM"", LOWER(TRIM(txt)), ""UPPERCASE|TRIM"", UPPER(TRIM(txt)), ""DIGITS_ONLY"", R"&"EGEXREPLACE(txt, ""[^0-9]"", """"), ""REMOVE_COMMAS|TRIM"", TRIM(SUBSTITUTE(txt, "","", """")), ""REMOVE_CURRENCY_SYMBOL|REMOVE_COMMAS|TRIM"", TRIM(REGEXREPLACE(SUBSTITUTE(txt, "","", """"), ""[$€£¥]"", """")), ""REMOVE_PERCENT|TRIM"", TRIM(SU"&"BSTITUTE(txt, ""%"", """")), txt ), IF(REGEXMATCH(normed, rx), TRUE, raw) )"),TRUE()) -> TRUE | G8: =IFERROR(__xludf.dummyfunction("LET( raw, INDEX(fakerUSDataset!$A:$CX, ROW(), COLUMN()), hdr, INDEX(fakerUSDataset!$1:$1, COLUMN()), norm, INDEX(ColumnMetaData!$I:$I, MATCH(hdr, ColumnMetaData!$C:$C, 0)), patName, INDEX(ColumnMetaData!$D:$D, MATCH(hdr, ColumnMetaData!$C:$C, 0)),"&" rx, INDEX(RegexPatterns!$B:$B, MATCH(patName, RegexPatterns!$A:$A, 0)), txt, TO_TEXT(raw), normed, SWITCH( norm, ""TRIM"", TRIM(txt), ""LOWERCASE|TRIM"", LOWER(TRIM(txt)), ""UPPERCASE|TRIM"", UPPER(TRIM(txt)), ""DIGITS_ONLY"", R"&"EGEXREPLACE(txt, ""[^0-9]"", """"), ""REMOVE_COMMAS|TRIM"", TRIM(SUBSTITUTE(txt, "","", """")), ""REMOVE_CURRENCY_SYMBOL|REMOVE_COMMAS|TRIM"", TRIM(REGEXREPLACE(SUBSTITUTE(txt, "","", """"), ""[$€£¥]"", """")), ""REMOVE_PERCENT|TRIM"", TRIM(SU"&"BSTITUTE(txt, ""%"", """")), txt ), IF(REGEXMATCH(normed, rx), TRUE, raw) )"),TRUE()) -> TRUE | H8: =IFERROR(__xludf.dummyfunction("LET( raw, INDEX(fakerUSDataset!$A:$CX, ROW(), COLUMN()), hdr, INDEX(fakerUSDataset!$1:$1, COLUMN()), norm, INDEX(ColumnMetaData!$I:$I, MATCH(hdr, ColumnMetaData!$C:$C, 0)), patName, INDEX(ColumnMetaData!$D:$D, MATCH(hdr, ColumnMetaData!$C:$C, 0)),"&" rx, INDEX(RegexPatterns!$B:$B, MATCH(patName, RegexPatterns!$A:$A, 0)), txt, TO_TEXT(raw), normed, SWITCH( norm, ""TRIM"", TRIM(txt), ""LOWERCASE|TRIM"", LOWER(TRIM(txt)), ""UPPERCASE|TRIM"", UPPER(TRIM(txt)), ""DIGITS_ONLY"", R"&"EGEXREPLACE(txt, ""[^0-9]"", """"), ""REMOVE_COMMAS|TRIM"", TRIM(SUBSTITUTE(txt, "","", """")), ""REMOVE_CURRENCY_SYMBOL|REMOVE_COMMAS|TRIM"", TRIM(REGEXREPLACE(SUBSTITUTE(txt, "","", """"), ""[$€£¥]"", """")), ""REMOVE_PERCENT|TRIM"", TRIM(SU"&"BSTITUTE(txt, ""%"", """")), txt ), IF(REGEXMATCH(normed, rx), TRUE, raw) )"),TRUE()) -> TRUE | ... Z8: =IFERROR(__xludf.dummyfunction("LET( raw, INDEX(fakerUSDataset!$A:$CX, ROW(), COLUMN()), hdr, INDEX(fakerUSDataset!$1:$1, COLUMN()), norm, INDEX(ColumnMetaData!$I:$I, MATCH(hdr, ColumnMetaData!$C:$C, 0)), patName, INDEX(ColumnMetaData!$D:$D, MATCH(hdr, ColumnMetaData!$C:$C, 0)),"&" rx, INDEX(RegexPatterns!$B:$B, MATCH(patName, RegexPatterns!$A:$A, 0)), txt, TO_TEXT(raw), normed, SWITCH( norm, ""TRIM"", TRIM(txt), ""LOWERCASE|TRIM"", LOWER(TRIM(txt)), ""UPPERCASE|TRIM"", UPPER(TRIM(txt)), ""DIGITS_ONLY"", R"&"EGEXREPLACE(txt, ""[^0-9]"", """"), ""REMOVE_COMMAS|TRIM"", TRIM(SUBSTITUTE(txt, "","", """")), ""REMOVE_CURRENCY_SYMBOL|REMOVE_COMMAS|TRIM"", TRIM(REGEXREPLACE(SUBSTITUTE(txt, "","", """"), ""[$€£¥]"", """")), ""REMOVE_PERCENT|TRIM"", TRIM(SU"&"BSTITUTE(txt, ""%"", """")), txt ), IF(REGEXMATCH(normed, rx), TRUE, raw) )"),TRUE()) -> TRUE | AA8: =IFERROR(__xludf.dummyfunction("LET( raw, INDEX(fakerUSDataset!$A:$CX, ROW(), COLUMN()), hdr, INDEX(fakerUSDataset!$1:$1, COLUMN()), norm, INDEX(ColumnMetaData!$I:$I, MATCH(hdr, ColumnMetaData!$C:$C, 0)), patName, INDEX(ColumnMetaData!$D:$D, MATCH(hdr, ColumnMetaData!$C:$C, 0)),"&" rx, INDEX(RegexPatterns!$B:$B, MATCH(patName, RegexPatterns!$A:$A, 0)), txt, TO_TEXT(raw), normed, SWITCH( norm, ""TRIM"", TRIM(txt), ""LOWERCASE|TRIM"", LOWER(TRIM(txt)), ""UPPERCASE|TRIM"", UPPER(TRIM(txt)), ""DIGITS_ONLY"", R"&"EGEXREPLACE(txt, ""[^0-9]"", """"), ""REMOVE_COMMAS|TRIM"", TRIM(SUBSTITUTE(txt, "","", """")), ""REMOVE_CURRENCY_SYMBOL|REMOVE_COMMAS|TRIM"", TRIM(REGEXREPLACE(SUBSTITUTE(txt, "","", """"), ""[$€£¥]"", """")), ""REMOVE_PERCENT|TRIM"", TRIM(SU"&"BSTITUTE(txt, ""%"", """")), txt ), IF(REGEXMATCH(normed, rx), TRUE, raw) )"),6878) -> 6878 | AB8: =IFERROR(__xludf.dummyfunction("LET( raw, INDEX(fakerUSDataset!$A:$CX, ROW(), COLUMN()), hdr, INDEX(fakerUSDataset!$1:$1, COLUMN()), norm, INDEX(ColumnMetaData!$I:$I, MATCH(hdr, ColumnMetaData!$C:$C, 0)), patName, INDEX(ColumnMetaData!$D:$D, MATCH(hdr, ColumnMetaData!$C:$C, 0)),"&" rx, INDEX(RegexPatterns!$B:$B, MATCH(patName, RegexPatterns!$A:$A, 0)), txt, TO_TEXT(raw), normed, SWITCH( norm, ""TRIM"", TRIM(txt), ""LOWERCASE|TRIM"", LOWER(TRIM(txt)), ""UPPERCASE|TRIM"", UPPER(TRIM(txt)), ""DIGITS_ONLY"", R"&"EGEXREPLACE(txt, ""[^0-9]"", """"), ""REMOVE_COMMAS|TRIM"", TRIM(SUBSTITUTE(txt, "","", """")), ""REMOVE_CURRENCY_SYMBOL|REMOVE_COMMAS|TRIM"", TRIM(REGEXREPLACE(SUBSTITUTE(txt, "","", """"), ""[$€£¥]"", """")), ""REMOVE_PERCENT|TRIM"", TRIM(SU"&"BSTITUTE(txt, ""%"", """")), txt ), IF(REGEXMATCH(normed, rx), TRUE, raw) )"),7125) -> 7125 | AC8: =IFERROR(__xludf.dummyfunction("LET( raw, INDEX(fakerUSDataset!$A:$CX, ROW(), COLUMN()), hdr, INDEX(fakerUSDataset!$1:$1, COLUMN()), norm, INDEX(ColumnMetaData!$I:$I, MATCH(hdr, ColumnMetaData!$C:$C, 0)), patName, INDEX(ColumnMetaData!$D:$D, MATCH(hdr, ColumnMetaData!$C:$C, 0)),"&" rx, INDEX(RegexPatterns!$B:$B, MATCH(patName, RegexPatterns!$A:$A, 0)), txt, TO_TEXT(raw), normed, SWITCH( norm, ""TRIM"", TRIM(txt), ""LOWERCASE|TRIM"", LOWER(TRIM(txt)), ""UPPERCASE|TRIM"", UPPER(TRIM(txt)), ""DIGITS_ONLY"", R"&"EGEXREPLACE(txt, ""[^0-9]"", """"), ""REMOVE_COMMAS|TRIM"", TRIM(SUBSTITUTE(txt, "","", """")), ""REMOVE_CURRENCY_SYMBOL|REMOVE_COMMAS|TRIM"", TRIM(REGEXREPLACE(SUBSTITUTE(txt, "","", """"), ""[$€£¥]"", """")), ""REMOVE_PERCENT|TRIM"", TRIM(SU"&"BSTITUTE(txt, ""%"", """")), txt ), IF(REGEXMATCH(normed, rx), TRUE, raw) )"),TRUE()) -> TRUE | AD8: =IFERROR(__xludf.dummyfunction("LET( raw, INDEX(fakerUSDataset!$A:$CX, ROW(), COLUMN()), hdr, INDEX(fakerUSDataset!$1:$1, COLUMN()), norm, INDEX(ColumnMetaData!$I:$I, MATCH(hdr, ColumnMetaData!$C:$C, 0)), patName, INDEX(ColumnMetaData!$D:$D, MATCH(hdr, ColumnMetaData!$C:$C, 0)),"&" rx, INDEX(RegexPatterns!$B:$B, MATCH(patName, RegexPatterns!$A:$A, 0)), txt, TO_TEXT(raw), normed, SWITCH( norm, ""TRIM"", TRIM(txt), ""LOWERCASE|TRIM"", LOWER(TRIM(txt)), ""UPPERCASE|TRIM"", UPPER(TRIM(txt)), ""DIGITS_ONLY"", R"&"EGEXREPLACE(txt, ""[^0-9]"", """"), ""REMOVE_COMMAS|TRIM"", TRIM(SUBSTITUTE(txt, "","", """")), ""REMOVE_CURRENCY_SYMBOL|REMOVE_COMMAS|TRIM"", TRIM(REGEXREPLACE(SUBSTITUTE(txt, "","", """"), ""[$€£¥]"", """")), ""REMOVE_PERCENT|TRIM"", TRIM(SU"&"BSTITUTE(txt, ""%"", """")), txt ), IF(REGEXMATCH(normed, rx), TRUE, raw) )"),TRUE()) -> TRUE | AE8: =IFERROR(__xludf.dummyfunction("LET( raw, INDEX(fakerUSDataset!$A:$CX, ROW(), COLUMN()), hdr, INDEX(fakerUSDataset!$1:$1, COLUMN()), norm, INDEX(ColumnMetaData!$I:$I, MATCH(hdr, ColumnMetaData!$C:$C, 0)), patName, INDEX(ColumnMetaData!$D:$D, MATCH(hdr, ColumnMetaData!$C:$C, 0)),"&" rx, INDEX(RegexPatterns!$B:$B, MATCH(patName, RegexPatterns!$A:$A, 0)), txt, TO_TEXT(raw), normed, SWITCH( norm, ""TRIM"", TRIM(txt), ""LOWERCASE|TRIM"", LOWER(TRIM(txt)), ""UPPERCASE|TRIM"", UPPER(TRIM(txt)), ""DIGITS_ONLY"", R"&"EGEXREPLACE(txt, ""[^0-9]"", """"), ""REMOVE_COMMAS|TRIM"", TRIM(SUBSTITUTE(txt, "","", """")), ""REMOVE_CURRENCY_SYMBOL|REMOVE_COMMAS|TRIM"", TRIM(REGEXREPLACE(SUBSTITUTE(txt, "","", """"), ""[$€£¥]"", """")), ""REMOVE_PERCENT|TRIM"", TRIM(SU"&"BSTITUTE(txt, ""%"", """")), txt ), IF(REGEXMATCH(normed, rx), TRUE, raw) )"),TRUE()) -> TRUE | AF8: =IFERROR(__xludf.dummyfunction("LET( raw, INDEX(fakerUSDataset!$A:$CX, ROW(), COLUMN()), hdr, INDEX(fakerUSDataset!$1:$1, COLUMN()), norm, INDEX(ColumnMetaData!$I:$I, MATCH(hdr, ColumnMetaData!$C:$C, 0)), patName, INDEX(ColumnMetaData!$D:$D, MATCH(hdr, ColumnMetaData!$C:$C, 0)),"&" rx, INDEX(RegexPatterns!$B:$B, MATCH(patName, RegexPatterns!$A:$A, 0)), txt, TO_TEXT(raw), normed, SWITCH( norm, ""TRIM"", TRIM(txt), ""LOWERCASE|TRIM"", LOWER(TRIM(txt)), ""UPPERCASE|TRIM"", UPPER(TRIM(txt)), ""DIGITS_ONLY"", R"&"EGEXREPLACE(txt, ""[^0-9]"", """"), ""REMOVE_COMMAS|TRIM"", TRIM(SUBSTITUTE(txt, "","", """")), ""REMOVE_CURRENCY_SYMBOL|REMOVE_COMMAS|TRIM"", TRIM(REGEXREPLACE(SUBSTITUTE(txt, "","", """"), ""[$€£¥]"", """")), ""REMOVE_PERCENT|TRIM"", TRIM(SU"&"BSTITUTE(txt, ""%"", """")), txt ), IF(REGEXMATCH(normed, rx), TRUE, raw) )"),TRUE()) -> TRUE | AG8: =IFERROR(__xludf.dummyfunction("LET( raw, INDEX(fakerUSDataset!$A:$CX, ROW(), COLUMN()), hdr, INDEX(fakerUSDataset!$1:$1, COLUMN()), norm, INDEX(ColumnMetaData!$I:$I, MATCH(hdr, ColumnMetaData!$C:$C, 0)), patName, INDEX(ColumnMetaData!$D:$D, MATCH(hdr, ColumnMetaData!$C:$C, 0)),"&" rx, INDEX(RegexPatterns!$B:$B, MATCH(patName, RegexPatterns!$A:$A, 0)), txt, TO_TEXT(raw), normed, SWITCH( norm, ""TRIM"", TRIM(txt), ""LOWERCASE|TRIM"", LOWER(TRIM(txt)), ""UPPERCASE|TRIM"", UPPER(TRIM(txt)), ""DIGITS_ONLY"", R"&"EGEXREPLACE(txt, ""[^0-9]"", """"), ""REMOVE_COMMAS|TRIM"", TRIM(SUBSTITUTE(txt, "","", """")), ""REMOVE_CURRENCY_SYMBOL|REMOVE_COMMAS|TRIM"", TRIM(REGEXREPLACE(SUBSTITUTE(txt, "","", """"), ""[$€£¥]"", """")), ""REMOVE_PERCENT|TRIM"", TRIM(SU"&"BSTITUTE(txt, ""%"", """")), txt ), IF(REGEXMATCH(normed, rx), TRUE, raw) )"),TRUE()) -> TRUE | AH8: =IFERROR(__xludf.dummyfunction("LET( raw, INDEX(fakerUSDataset!$A:$CX, ROW(), COLUMN()), hdr, INDEX(fakerUSDataset!$1:$1, COLUMN()), norm, INDEX(ColumnMetaData!$I:$I, MATCH(hdr, ColumnMetaData!$C:$C, 0)), patName, INDEX(ColumnMetaData!$D:$D, MATCH(hdr, ColumnMetaData!$C:$C, 0)),"&" rx, INDEX(RegexPatterns!$B:$B, MATCH(patName, RegexPatterns!$A:$A, 0)), txt, TO_TEXT(raw), normed, SWITCH( norm, ""TRIM"", TRIM(txt), ""LOWERCASE|TRIM"", LOWER(TRIM(txt)), ""UPPERCASE|TRIM"", UPPER(TRIM(txt)), ""DIGITS_ONLY"", R"&"EGEXREPLACE(txt, ""[^0-9]"", """"), ""REMOVE_COMMAS|TRIM"", TRIM(SUBSTITUTE(txt, "","", """")), ""REMOVE_CURRENCY_SYMBOL|REMOVE_COMMAS|TRIM"", TRIM(REGEXREPLACE(SUBSTITUTE(txt, "","", """"), ""[$€£¥]"", """")), ""REMOVE_PERCENT|TRIM"", TRIM(SU"&"BSTITUTE(txt, ""%"", """")), txt ), IF(REGEXMATCH(normed, rx), TRUE, raw) )"),TRUE()) -> TRUE | AI8: =IFERROR(__xludf.dummyfunction("LET( raw, INDEX(fakerUSDataset!$A:$CX, ROW(), COLUMN()), hdr, INDEX(fakerUSDataset!$1:$1, COLUMN()), norm, INDEX(ColumnMetaData!$I:$I, MATCH(hdr, ColumnMetaData!$C:$C, 0)), patName, INDEX(ColumnMetaData!$D:$D, MATCH(hdr, ColumnMetaData!$C:$C, 0)),"&" rx, INDEX(RegexPatterns!$B:$B, MATCH(patName, RegexPatterns!$A:$A, 0)), txt, TO_TEXT(raw), normed, SWITCH( norm, ""TRIM"", TRIM(txt), ""LOWERCASE|TRIM"", LOWER(TRIM(txt)), ""UPPERCASE|TRIM"", UPPER(TRIM(txt)), ""DIGITS_ONLY"", R"&"EGEXREPLACE(txt, ""[^0-9]"", """"), ""REMOVE_COMMAS|TRIM"", TRIM(SUBSTITUTE(txt, "","", """")), ""REMOVE_CURRENCY_SYMBOL|REMOVE_COMMAS|TRIM"", TRIM(REGEXREPLACE(SUBSTITUTE(txt, "","", """"), ""[$€£¥]"", """")), ""REMOVE_PERCENT|TRIM"", TRIM(SU"&"BSTITUTE(txt, ""%"", """")), txt ), IF(REGEXMATCH(normed, rx), TRUE, raw) )"),TRUE()) -> TRUE | AJ8: =IFERROR(__xludf.dummyfunction("LET( raw, INDEX(fakerUSDataset!$A:$CX, ROW(), COLUMN()), hdr, INDEX(fakerUSDataset!$1:$1, COLUMN()), norm, INDEX(ColumnMetaData!$I:$I, MATCH(hdr, ColumnMetaData!$C:$C, 0)), patName, INDEX(ColumnMetaData!$D:$D, MATCH(hdr, ColumnMetaData!$C:$C, 0)),"&" rx, INDEX(RegexPatterns!$B:$B, MATCH(patName, RegexPatterns!$A:$A, 0)), txt, TO_TEXT(raw), normed, SWITCH( norm, ""TRIM"", TRIM(txt), ""LOWERCASE|TRIM"", LOWER(TRIM(txt)), ""UPPERCASE|TRIM"", UPPER(TRIM(txt)), ""DIGITS_ONLY"", R"&"EGEXREPLACE(txt, ""[^0-9]"", """"), ""REMOVE_COMMAS|TRIM"", TRIM(SUBSTITUTE(txt, "","", """")), ""REMOVE_CURRENCY_SYMBOL|REMOVE_COMMAS|TRIM"", TRIM(REGEXREPLACE(SUBSTITUTE(txt, "","", """"), ""[$€£¥]"", """")), ""REMOVE_PERCENT|TRIM"", TRIM(SU"&"BSTITUTE(txt, ""%"", """")), txt ), IF(REGEXMATCH(normed, rx), TRUE, raw) )"),TRUE()) -> TRUE | ... CV8: =IFERROR(__xludf.dummyfunction("LET( raw, INDEX(fakerUSDataset!$A:$CX, ROW(), COLUMN()), hdr, INDEX(fakerUSDataset!$1:$1, COLUMN()), norm, INDEX(ColumnMetaData!$I:$I, MATCH(hdr, ColumnMetaData!$C:$C, 0)), patName, INDEX(ColumnMetaData!$D:$D, MATCH(hdr, ColumnMetaData!$C:$C, 0)),"&" rx, INDEX(RegexPatterns!$B:$B, MATCH(patName, RegexPatterns!$A:$A, 0)), txt, TO_TEXT(raw), normed, SWITCH( norm, ""TRIM"", TRIM(txt), ""LOWERCASE|TRIM"", LOWER(TRIM(txt)), ""UPPERCASE|TRIM"", UPPER(TRIM(txt)), ""DIGITS_ONLY"", R"&"EGEXREPLACE(txt, ""[^0-9]"", """"), ""REMOVE_COMMAS|TRIM"", TRIM(SUBSTITUTE(txt, "","", """")), ""REMOVE_CURRENCY_SYMBOL|REMOVE_COMMAS|TRIM"", TRIM(REGEXREPLACE(SUBSTITUTE(txt, "","", """"), ""[$€£¥]"", """")), ""REMOVE_PERCENT|TRIM"", TRIM(SU"&"BSTITUTE(txt, ""%"", """")), txt ), IF(REGEXMATCH(normed, rx), TRUE, raw) )"),TRUE()) -> TRUE
A9: =IFERROR(__xludf.dummyfunction("LET( raw, INDEX(fakerUSDataset!$A:$CX, ROW(), COLUMN()), hdr, INDEX(fakerUSDataset!$1:$1, COLUMN()), norm, INDEX(ColumnMetaData!$I:$I, MATCH(hdr, ColumnMetaData!$C:$C, 0)), patName, INDEX(ColumnMetaData!$D:$D, MATCH(hdr, ColumnMetaData!$C:$C, 0)),"&" rx, INDEX(RegexPatterns!$B:$B, MATCH(patName, RegexPatterns!$A:$A, 0)), txt, TO_TEXT(raw), normed, SWITCH( norm, ""TRIM"", TRIM(txt), ""LOWERCASE|TRIM"", LOWER(TRIM(txt)), ""UPPERCASE|TRIM"", UPPER(TRIM(txt)), ""DIGITS_ONLY"", R"&"EGEXREPLACE(txt, ""[^0-9]"", """"), ""REMOVE_COMMAS|TRIM"", TRIM(SUBSTITUTE(txt, "","", """")), ""REMOVE_CURRENCY_SYMBOL|REMOVE_COMMAS|TRIM"", TRIM(REGEXREPLACE(SUBSTITUTE(txt, "","", """"), ""[$€£¥]"", """")), ""REMOVE_PERCENT|TRIM"", TRIM(SU"&"BSTITUTE(txt, ""%"", """")), txt ), IF(REGEXMATCH(normed, rx), TRUE, raw) )"),TRUE()) -> TRUE | B9: =IFERROR(__xludf.dummyfunction("LET( raw, INDEX(fakerUSDataset!$A:$CX, ROW(), COLUMN()), hdr, INDEX(fakerUSDataset!$1:$1, COLUMN()), norm, INDEX(ColumnMetaData!$I:$I, MATCH(hdr, ColumnMetaData!$C:$C, 0)), patName, INDEX(ColumnMetaData!$D:$D, MATCH(hdr, ColumnMetaData!$C:$C, 0)),"&" rx, INDEX(RegexPatterns!$B:$B, MATCH(patName, RegexPatterns!$A:$A, 0)), txt, TO_TEXT(raw), normed, SWITCH( norm, ""TRIM"", TRIM(txt), ""LOWERCASE|TRIM"", LOWER(TRIM(txt)), ""UPPERCASE|TRIM"", UPPER(TRIM(txt)), ""DIGITS_ONLY"", R"&"EGEXREPLACE(txt, ""[^0-9]"", """"), ""REMOVE_COMMAS|TRIM"", TRIM(SUBSTITUTE(txt, "","", """")), ""REMOVE_CURRENCY_SYMBOL|REMOVE_COMMAS|TRIM"", TRIM(REGEXREPLACE(SUBSTITUTE(txt, "","", """"), ""[$€£¥]"", """")), ""REMOVE_PERCENT|TRIM"", TRIM(SU"&"BSTITUTE(txt, ""%"", """")), txt ), IF(REGEXMATCH(normed, rx), TRUE, raw) )"),TRUE()) -> TRUE | C9: =IFERROR(__xludf.dummyfunction("LET( raw, INDEX(fakerUSDataset!$A:$CX, ROW(), COLUMN()), hdr, INDEX(fakerUSDataset!$1:$1, COLUMN()), norm, INDEX(ColumnMetaData!$I:$I, MATCH(hdr, ColumnMetaData!$C:$C, 0)), patName, INDEX(ColumnMetaData!$D:$D, MATCH(hdr, ColumnMetaData!$C:$C, 0)),"&" rx, INDEX(RegexPatterns!$B:$B, MATCH(patName, RegexPatterns!$A:$A, 0)), txt, TO_TEXT(raw), normed, SWITCH( norm, ""TRIM"", TRIM(txt), ""LOWERCASE|TRIM"", LOWER(TRIM(txt)), ""UPPERCASE|TRIM"", UPPER(TRIM(txt)), ""DIGITS_ONLY"", R"&"EGEXREPLACE(txt, ""[^0-9]"", """"), ""REMOVE_COMMAS|TRIM"", TRIM(SUBSTITUTE(txt, "","", """")), ""REMOVE_CURRENCY_SYMBOL|REMOVE_COMMAS|TRIM"", TRIM(REGEXREPLACE(SUBSTITUTE(txt, "","", """"), ""[$€£¥]"", """")), ""REMOVE_PERCENT|TRIM"", TRIM(SU"&"BSTITUTE(txt, ""%"", """")), txt ), IF(REGEXMATCH(normed, rx), TRUE, raw) )"),TRUE()) -> TRUE | D9: =IFERROR(__xludf.dummyfunction("LET( raw, INDEX(fakerUSDataset!$A:$CX, ROW(), COLUMN()), hdr, INDEX(fakerUSDataset!$1:$1, COLUMN()), norm, INDEX(ColumnMetaData!$I:$I, MATCH(hdr, ColumnMetaData!$C:$C, 0)), patName, INDEX(ColumnMetaData!$D:$D, MATCH(hdr, ColumnMetaData!$C:$C, 0)),"&" rx, INDEX(RegexPatterns!$B:$B, MATCH(patName, RegexPatterns!$A:$A, 0)), txt, TO_TEXT(raw), normed, SWITCH( norm, ""TRIM"", TRIM(txt), ""LOWERCASE|TRIM"", LOWER(TRIM(txt)), ""UPPERCASE|TRIM"", UPPER(TRIM(txt)), ""DIGITS_ONLY"", R"&"EGEXREPLACE(txt, ""[^0-9]"", """"), ""REMOVE_COMMAS|TRIM"", TRIM(SUBSTITUTE(txt, "","", """")), ""REMOVE_CURRENCY_SYMBOL|REMOVE_COMMAS|TRIM"", TRIM(REGEXREPLACE(SUBSTITUTE(txt, "","", """"), ""[$€£¥]"", """")), ""REMOVE_PERCENT|TRIM"", TRIM(SU"&"BSTITUTE(txt, ""%"", """")), txt ), IF(REGEXMATCH(normed, rx), TRUE, raw) )"),TRUE()) -> TRUE | E9: =IFERROR(__xludf.dummyfunction("LET( raw, INDEX(fakerUSDataset!$A:$CX, ROW(), COLUMN()), hdr, INDEX(fakerUSDataset!$1:$1, COLUMN()), norm, INDEX(ColumnMetaData!$I:$I, MATCH(hdr, ColumnMetaData!$C:$C, 0)), patName, INDEX(ColumnMetaData!$D:$D, MATCH(hdr, ColumnMetaData!$C:$C, 0)),"&" rx, INDEX(RegexPatterns!$B:$B, MATCH(patName, RegexPatterns!$A:$A, 0)), txt, TO_TEXT(raw), normed, SWITCH( norm, ""TRIM"", TRIM(txt), ""LOWERCASE|TRIM"", LOWER(TRIM(txt)), ""UPPERCASE|TRIM"", UPPER(TRIM(txt)), ""DIGITS_ONLY"", R"&"EGEXREPLACE(txt, ""[^0-9]"", """"), ""REMOVE_COMMAS|TRIM"", TRIM(SUBSTITUTE(txt, "","", """")), ""REMOVE_CURRENCY_SYMBOL|REMOVE_COMMAS|TRIM"", TRIM(REGEXREPLACE(SUBSTITUTE(txt, "","", """"), ""[$€£¥]"", """")), ""REMOVE_PERCENT|TRIM"", TRIM(SU"&"BSTITUTE(txt, ""%"", """")), txt ), IF(REGEXMATCH(normed, rx), TRUE, raw) )"),TRUE()) -> TRUE | F9: =IFERROR(__xludf.dummyfunction("LET( raw, INDEX(fakerUSDataset!$A:$CX, ROW(), COLUMN()), hdr, INDEX(fakerUSDataset!$1:$1, COLUMN()), norm, INDEX(ColumnMetaData!$I:$I, MATCH(hdr, ColumnMetaData!$C:$C, 0)), patName, INDEX(ColumnMetaData!$D:$D, MATCH(hdr, ColumnMetaData!$C:$C, 0)),"&" rx, INDEX(RegexPatterns!$B:$B, MATCH(patName, RegexPatterns!$A:$A, 0)), txt, TO_TEXT(raw), normed, SWITCH( norm, ""TRIM"", TRIM(txt), ""LOWERCASE|TRIM"", LOWER(TRIM(txt)), ""UPPERCASE|TRIM"", UPPER(TRIM(txt)), ""DIGITS_ONLY"", R"&"EGEXREPLACE(txt, ""[^0-9]"", """"), ""REMOVE_COMMAS|TRIM"", TRIM(SUBSTITUTE(txt, "","", """")), ""REMOVE_CURRENCY_SYMBOL|REMOVE_COMMAS|TRIM"", TRIM(REGEXREPLACE(SUBSTITUTE(txt, "","", """"), ""[$€£¥]"", """")), ""REMOVE_PERCENT|TRIM"", TRIM(SU"&"BSTITUTE(txt, ""%"", """")), txt ), IF(REGEXMATCH(normed, rx), TRUE, raw) )"),TRUE()) -> TRUE | G9: =IFERROR(__xludf.dummyfunction("LET( raw, INDEX(fakerUSDataset!$A:$CX, ROW(), COLUMN()), hdr, INDEX(fakerUSDataset!$1:$1, COLUMN()), norm, INDEX(ColumnMetaData!$I:$I, MATCH(hdr, ColumnMetaData!$C:$C, 0)), patName, INDEX(ColumnMetaData!$D:$D, MATCH(hdr, ColumnMetaData!$C:$C, 0)),"&" rx, INDEX(RegexPatterns!$B:$B, MATCH(patName, RegexPatterns!$A:$A, 0)), txt, TO_TEXT(raw), normed, SWITCH( norm, ""TRIM"", TRIM(txt), ""LOWERCASE|TRIM"", LOWER(TRIM(txt)), ""UPPERCASE|TRIM"", UPPER(TRIM(txt)), ""DIGITS_ONLY"", R"&"EGEXREPLACE(txt, ""[^0-9]"", """"), ""REMOVE_COMMAS|TRIM"", TRIM(SUBSTITUTE(txt, "","", """")), ""REMOVE_CURRENCY_SYMBOL|REMOVE_COMMAS|TRIM"", TRIM(REGEXREPLACE(SUBSTITUTE(txt, "","", """"), ""[$€£¥]"", """")), ""REMOVE_PERCENT|TRIM"", TRIM(SU"&"BSTITUTE(txt, ""%"", """")), txt ), IF(REGEXMATCH(normed, rx), TRUE, raw) )"),TRUE()) -> TRUE | H9: =IFERROR(__xludf.dummyfunction("LET( raw, INDEX(fakerUSDataset!$A:$CX, ROW(), COLUMN()), hdr, INDEX(fakerUSDataset!$1:$1, COLUMN()), norm, INDEX(ColumnMetaData!$I:$I, MATCH(hdr, ColumnMetaData!$C:$C, 0)), patName, INDEX(ColumnMetaData!$D:$D, MATCH(hdr, ColumnMetaData!$C:$C, 0)),"&" rx, INDEX(RegexPatterns!$B:$B, MATCH(patName, RegexPatterns!$A:$A, 0)), txt, TO_TEXT(raw), normed, SWITCH( norm, ""TRIM"", TRIM(txt), ""LOWERCASE|TRIM"", LOWER(TRIM(txt)), ""UPPERCASE|TRIM"", UPPER(TRIM(txt)), ""DIGITS_ONLY"", R"&"EGEXREPLACE(txt, ""[^0-9]"", """"), ""REMOVE_COMMAS|TRIM"", TRIM(SUBSTITUTE(txt, "","", """")), ""REMOVE_CURRENCY_SYMBOL|REMOVE_COMMAS|TRIM"", TRIM(REGEXREPLACE(SUBSTITUTE(txt, "","", """"), ""[$€£¥]"", """")), ""REMOVE_PERCENT|TRIM"", TRIM(SU"&"BSTITUTE(txt, ""%"", """")), txt ), IF(REGEXMATCH(normed, rx), TRUE, raw) )"),TRUE()) -> TRUE | ... CV9: =IFERROR(__xludf.dummyfunction("LET( raw, INDEX(fakerUSDataset!$A:$CX, ROW(), COLUMN()), hdr, INDEX(fakerUSDataset!$1:$1, COLUMN()), norm, INDEX(ColumnMetaData!$I:$I, MATCH(hdr, ColumnMetaData!$C:$C, 0)), patName, INDEX(ColumnMetaData!$D:$D, MATCH(hdr, ColumnMetaData!$C:$C, 0)),"&" rx, INDEX(RegexPatterns!$B:$B, MATCH(patName, RegexPatterns!$A:$A, 0)), txt, TO_TEXT(raw), normed, SWITCH( norm, ""TRIM"", TRIM(txt), ""LOWERCASE|TRIM"", LOWER(TRIM(txt)), ""UPPERCASE|TRIM"", UPPER(TRIM(txt)), ""DIGITS_ONLY"", R"&"EGEXREPLACE(txt, ""[^0-9]"", """"), ""REMOVE_COMMAS|TRIM"", TRIM(SUBSTITUTE(txt, "","", """")), ""REMOVE_CURRENCY_SYMBOL|REMOVE_COMMAS|TRIM"", TRIM(REGEXREPLACE(SUBSTITUTE(txt, "","", """"), ""[$€£¥]"", """")), ""REMOVE_PERCENT|TRIM"", TRIM(SU"&"BSTITUTE(txt, ""%"", """")), txt ), IF(REGEXMATCH(normed, rx), TRUE, raw) )"),TRUE()) -> TRUE
A10: =IFERROR(__xludf.dummyfunction("LET( raw, INDEX(fakerUSDataset!$A:$CX, ROW(), COLUMN()), hdr, INDEX(fakerUSDataset!$1:$1, COLUMN()), norm, INDEX(ColumnMetaData!$I:$I, MATCH(hdr, ColumnMetaData!$C:$C, 0)), patName, INDEX(ColumnMetaData!$D:$D, MATCH(hdr, ColumnMetaData!$C:$C, 0)),"&" rx, INDEX(RegexPatterns!$B:$B, MATCH(patName, RegexPatterns!$A:$A, 0)), txt, TO_TEXT(raw), normed, SWITCH( norm, ""TRIM"", TRIM(txt), ""LOWERCASE|TRIM"", LOWER(TRIM(txt)), ""UPPERCASE|TRIM"", UPPER(TRIM(txt)), ""DIGITS_ONLY"", R"&"EGEXREPLACE(txt, ""[^0-9]"", """"), ""REMOVE_COMMAS|TRIM"", TRIM(SUBSTITUTE(txt, "","", """")), ""REMOVE_CURRENCY_SYMBOL|REMOVE_COMMAS|TRIM"", TRIM(REGEXREPLACE(SUBSTITUTE(txt, "","", """"), ""[$€£¥]"", """")), ""REMOVE_PERCENT|TRIM"", TRIM(SU"&"BSTITUTE(txt, ""%"", """")), txt ), IF(REGEXMATCH(normed, rx), TRUE, raw) )"),TRUE()) -> TRUE | B10: =IFERROR(__xludf.dummyfunction("LET( raw, INDEX(fakerUSDataset!$A:$CX, ROW(), COLUMN()), hdr, INDEX(fakerUSDataset!$1:$1, COLUMN()), norm, INDEX(ColumnMetaData!$I:$I, MATCH(hdr, ColumnMetaData!$C:$C, 0)), patName, INDEX(ColumnMetaData!$D:$D, MATCH(hdr, ColumnMetaData!$C:$C, 0)),"&" rx, INDEX(RegexPatterns!$B:$B, MATCH(patName, RegexPatterns!$A:$A, 0)), txt, TO_TEXT(raw), normed, SWITCH( norm, ""TRIM"", TRIM(txt), ""LOWERCASE|TRIM"", LOWER(TRIM(txt)), ""UPPERCASE|TRIM"", UPPER(TRIM(txt)), ""DIGITS_ONLY"", R"&"EGEXREPLACE(txt, ""[^0-9]"", """"), ""REMOVE_COMMAS|TRIM"", TRIM(SUBSTITUTE(txt, "","", """")), ""REMOVE_CURRENCY_SYMBOL|REMOVE_COMMAS|TRIM"", TRIM(REGEXREPLACE(SUBSTITUTE(txt, "","", """"), ""[$€£¥]"", """")), ""REMOVE_PERCENT|TRIM"", TRIM(SU"&"BSTITUTE(txt, ""%"", """")), txt ), IF(REGEXMATCH(normed, rx), TRUE, raw) )"),TRUE()) -> TRUE | C10: =IFERROR(__xludf.dummyfunction("LET( raw, INDEX(fakerUSDataset!$A:$CX, ROW(), COLUMN()), hdr, INDEX(fakerUSDataset!$1:$1, COLUMN()), norm, INDEX(ColumnMetaData!$I:$I, MATCH(hdr, ColumnMetaData!$C:$C, 0)), patName, INDEX(ColumnMetaData!$D:$D, MATCH(hdr, ColumnMetaData!$C:$C, 0)),"&" rx, INDEX(RegexPatterns!$B:$B, MATCH(patName, RegexPatterns!$A:$A, 0)), txt, TO_TEXT(raw), normed, SWITCH( norm, ""TRIM"", TRIM(txt), ""LOWERCASE|TRIM"", LOWER(TRIM(txt)), ""UPPERCASE|TRIM"", UPPER(TRIM(txt)), ""DIGITS_ONLY"", R"&"EGEXREPLACE(txt, ""[^0-9]"", """"), ""REMOVE_COMMAS|TRIM"", TRIM(SUBSTITUTE(txt, "","", """")), ""REMOVE_CURRENCY_SYMBOL|REMOVE_COMMAS|TRIM"", TRIM(REGEXREPLACE(SUBSTITUTE(txt, "","", """"), ""[$€£¥]"", """")), ""REMOVE_PERCENT|TRIM"", TRIM(SU"&"BSTITUTE(txt, ""%"", """")), txt ), IF(REGEXMATCH(normed, rx), TRUE, raw) )"),TRUE()) -> TRUE | D10: =IFERROR(__xludf.dummyfunction("LET( raw, INDEX(fakerUSDataset!$A:$CX, ROW(), COLUMN()), hdr, INDEX(fakerUSDataset!$1:$1, COLUMN()), norm, INDEX(ColumnMetaData!$I:$I, MATCH(hdr, ColumnMetaData!$C:$C, 0)), patName, INDEX(ColumnMetaData!$D:$D, MATCH(hdr, ColumnMetaData!$C:$C, 0)),"&" rx, INDEX(RegexPatterns!$B:$B, MATCH(patName, RegexPatterns!$A:$A, 0)), txt, TO_TEXT(raw), normed, SWITCH( norm, ""TRIM"", TRIM(txt), ""LOWERCASE|TRIM"", LOWER(TRIM(txt)), ""UPPERCASE|TRIM"", UPPER(TRIM(txt)), ""DIGITS_ONLY"", R"&"EGEXREPLACE(txt, ""[^0-9]"", """"), ""REMOVE_COMMAS|TRIM"", TRIM(SUBSTITUTE(txt, "","", """")), ""REMOVE_CURRENCY_SYMBOL|REMOVE_COMMAS|TRIM"", TRIM(REGEXREPLACE(SUBSTITUTE(txt, "","", """"), ""[$€£¥]"", """")), ""REMOVE_PERCENT|TRIM"", TRIM(SU"&"BSTITUTE(txt, ""%"", """")), txt ), IF(REGEXMATCH(normed, rx), TRUE, raw) )"),TRUE()) -> TRUE | E10: =IFERROR(__xludf.dummyfunction("LET( raw, INDEX(fakerUSDataset!$A:$CX, ROW(), COLUMN()), hdr, INDEX(fakerUSDataset!$1:$1, COLUMN()), norm, INDEX(ColumnMetaData!$I:$I, MATCH(hdr, ColumnMetaData!$C:$C, 0)), patName, INDEX(ColumnMetaData!$D:$D, MATCH(hdr, ColumnMetaData!$C:$C, 0)),"&" rx, INDEX(RegexPatterns!$B:$B, MATCH(patName, RegexPatterns!$A:$A, 0)), txt, TO_TEXT(raw), normed, SWITCH( norm, ""TRIM"", TRIM(txt), ""LOWERCASE|TRIM"", LOWER(TRIM(txt)), ""UPPERCASE|TRIM"", UPPER(TRIM(txt)), ""DIGITS_ONLY"", R"&"EGEXREPLACE(txt, ""[^0-9]"", """"), ""REMOVE_COMMAS|TRIM"", TRIM(SUBSTITUTE(txt, "","", """")), ""REMOVE_CURRENCY_SYMBOL|REMOVE_COMMAS|TRIM"", TRIM(REGEXREPLACE(SUBSTITUTE(txt, "","", """"), ""[$€£¥]"", """")), ""REMOVE_PERCENT|TRIM"", TRIM(SU"&"BSTITUTE(txt, ""%"", """")), txt ), IF(REGEXMATCH(normed, rx), TRUE, raw) )"),TRUE()) -> TRUE | F10: =IFERROR(__xludf.dummyfunction("LET( raw, INDEX(fakerUSDataset!$A:$CX, ROW(), COLUMN()), hdr, INDEX(fakerUSDataset!$1:$1, COLUMN()), norm, INDEX(ColumnMetaData!$I:$I, MATCH(hdr, ColumnMetaData!$C:$C, 0)), patName, INDEX(ColumnMetaData!$D:$D, MATCH(hdr, ColumnMetaData!$C:$C, 0)),"&" rx, INDEX(RegexPatterns!$B:$B, MATCH(patName, RegexPatterns!$A:$A, 0)), txt, TO_TEXT(raw), normed, SWITCH( norm, ""TRIM"", TRIM(txt), ""LOWERCASE|TRIM"", LOWER(TRIM(txt)), ""UPPERCASE|TRIM"", UPPER(TRIM(txt)), ""DIGITS_ONLY"", R"&"EGEXREPLACE(txt, ""[^0-9]"", """"), ""REMOVE_COMMAS|TRIM"", TRIM(SUBSTITUTE(txt, "","", """")), ""REMOVE_CURRENCY_SYMBOL|REMOVE_COMMAS|TRIM"", TRIM(REGEXREPLACE(SUBSTITUTE(txt, "","", """"), ""[$€£¥]"", """")), ""REMOVE_PERCENT|TRIM"", TRIM(SU"&"BSTITUTE(txt, ""%"", """")), txt ), IF(REGEXMATCH(normed, rx), TRUE, raw) )"),TRUE()) -> TRUE | G10: =IFERROR(__xludf.dummyfunction("LET( raw, INDEX(fakerUSDataset!$A:$CX, ROW(), COLUMN()), hdr, INDEX(fakerUSDataset!$1:$1, COLUMN()), norm, INDEX(ColumnMetaData!$I:$I, MATCH(hdr, ColumnMetaData!$C:$C, 0)), patName, INDEX(ColumnMetaData!$D:$D, MATCH(hdr, ColumnMetaData!$C:$C, 0)),"&" rx, INDEX(RegexPatterns!$B:$B, MATCH(patName, RegexPatterns!$A:$A, 0)), txt, TO_TEXT(raw), normed, SWITCH( norm, ""TRIM"", TRIM(txt), ""LOWERCASE|TRIM"", LOWER(TRIM(txt)), ""UPPERCASE|TRIM"", UPPER(TRIM(txt)), ""DIGITS_ONLY"", R"&"EGEXREPLACE(txt, ""[^0-9]"", """"), ""REMOVE_COMMAS|TRIM"", TRIM(SUBSTITUTE(txt, "","", """")), ""REMOVE_CURRENCY_SYMBOL|REMOVE_COMMAS|TRIM"", TRIM(REGEXREPLACE(SUBSTITUTE(txt, "","", """"), ""[$€£¥]"", """")), ""REMOVE_PERCENT|TRIM"", TRIM(SU"&"BSTITUTE(txt, ""%"", """")), txt ), IF(REGEXMATCH(normed, rx), TRUE, raw) )"),TRUE()) -> TRUE | H10: =IFERROR(__xludf.dummyfunction("LET( raw, INDEX(fakerUSDataset!$A:$CX, ROW(), COLUMN()), hdr, INDEX(fakerUSDataset!$1:$1, COLUMN()), norm, INDEX(ColumnMetaData!$I:$I, MATCH(hdr, ColumnMetaData!$C:$C, 0)), patName, INDEX(ColumnMetaData!$D:$D, MATCH(hdr, ColumnMetaData!$C:$C, 0)),"&" rx, INDEX(RegexPatterns!$B:$B, MATCH(patName, RegexPatterns!$A:$A, 0)), txt, TO_TEXT(raw), normed, SWITCH( norm, ""TRIM"", TRIM(txt), ""LOWERCASE|TRIM"", LOWER(TRIM(txt)), ""UPPERCASE|TRIM"", UPPER(TRIM(txt)), ""DIGITS_ONLY"", R"&"EGEXREPLACE(txt, ""[^0-9]"", """"), ""REMOVE_COMMAS|TRIM"", TRIM(SUBSTITUTE(txt, "","", """")), ""REMOVE_CURRENCY_SYMBOL|REMOVE_COMMAS|TRIM"", TRIM(REGEXREPLACE(SUBSTITUTE(txt, "","", """"), ""[$€£¥]"", """")), ""REMOVE_PERCENT|TRIM"", TRIM(SU"&"BSTITUTE(txt, ""%"", """")), txt ), IF(REGEXMATCH(normed, rx), TRUE, raw) )"),TRUE()) -> TRUE | ... CV10: =IFERROR(__xludf.dummyfunction("LET( raw, INDEX(fakerUSDataset!$A:$CX, ROW(), COLUMN()), hdr, INDEX(fakerUSDataset!$1:$1, COLUMN()), norm, INDEX(ColumnMetaData!$I:$I, MATCH(hdr, ColumnMetaData!$C:$C, 0)), patName, INDEX(ColumnMetaData!$D:$D, MATCH(hdr, ColumnMetaData!$C:$C, 0)),"&" rx, INDEX(RegexPatterns!$B:$B, MATCH(patName, RegexPatterns!$A:$A, 0)), txt, TO_TEXT(raw), normed, SWITCH( norm, ""TRIM"", TRIM(txt), ""LOWERCASE|TRIM"", LOWER(TRIM(txt)), ""UPPERCASE|TRIM"", UPPER(TRIM(txt)), ""DIGITS_ONLY"", R"&"EGEXREPLACE(txt, ""[^0-9]"", """"), ""REMOVE_COMMAS|TRIM"", TRIM(SUBSTITUTE(txt, "","", """")), ""REMOVE_CURRENCY_SYMBOL|REMOVE_COMMAS|TRIM"", TRIM(REGEXREPLACE(SUBSTITUTE(txt, "","", """"), ""[$€£¥]"", """")), ""REMOVE_PERCENT|TRIM"", TRIM(SU"&"BSTITUTE(txt, ""%"", """")), txt ), IF(REGEXMATCH(normed, rx), TRUE, raw) )"),TRUE()) -> TRUE
A11: =IFERROR(__xludf.dummyfunction("LET( raw, INDEX(fakerUSDataset!$A:$CX, ROW(), COLUMN()), hdr, INDEX(fakerUSDataset!$1:$1, COLUMN()), norm, INDEX(ColumnMetaData!$I:$I, MATCH(hdr, ColumnMetaData!$C:$C, 0)), patName, INDEX(ColumnMetaData!$D:$D, MATCH(hdr, ColumnMetaData!$C:$C, 0)),"&" rx, INDEX(RegexPatterns!$B:$B, MATCH(patName, RegexPatterns!$A:$A, 0)), txt, TO_TEXT(raw), normed, SWITCH( norm, ""TRIM"", TRIM(txt), ""LOWERCASE|TRIM"", LOWER(TRIM(txt)), ""UPPERCASE|TRIM"", UPPER(TRIM(txt)), ""DIGITS_ONLY"", R"&"EGEXREPLACE(txt, ""[^0-9]"", """"), ""REMOVE_COMMAS|TRIM"", TRIM(SUBSTITUTE(txt, "","", """")), ""REMOVE_CURRENCY_SYMBOL|REMOVE_COMMAS|TRIM"", TRIM(REGEXREPLACE(SUBSTITUTE(txt, "","", """"), ""[$€£¥]"", """")), ""REMOVE_PERCENT|TRIM"", TRIM(SU"&"BSTITUTE(txt, ""%"", """")), txt ), IF(REGEXMATCH(normed, rx), TRUE, raw) )"),TRUE()) -> TRUE | B11: =IFERROR(__xludf.dummyfunction("LET( raw, INDEX(fakerUSDataset!$A:$CX, ROW(), COLUMN()), hdr, INDEX(fakerUSDataset!$1:$1, COLUMN()), norm, INDEX(ColumnMetaData!$I:$I, MATCH(hdr, ColumnMetaData!$C:$C, 0)), patName, INDEX(ColumnMetaData!$D:$D, MATCH(hdr, ColumnMetaData!$C:$C, 0)),"&" rx, INDEX(RegexPatterns!$B:$B, MATCH(patName, RegexPatterns!$A:$A, 0)), txt, TO_TEXT(raw), normed, SWITCH( norm, ""TRIM"", TRIM(txt), ""LOWERCASE|TRIM"", LOWER(TRIM(txt)), ""UPPERCASE|TRIM"", UPPER(TRIM(txt)), ""DIGITS_ONLY"", R"&"EGEXREPLACE(txt, ""[^0-9]"", """"), ""REMOVE_COMMAS|TRIM"", TRIM(SUBSTITUTE(txt, "","", """")), ""REMOVE_CURRENCY_SYMBOL|REMOVE_COMMAS|TRIM"", TRIM(REGEXREPLACE(SUBSTITUTE(txt, "","", """"), ""[$€£¥]"", """")), ""REMOVE_PERCENT|TRIM"", TRIM(SU"&"BSTITUTE(txt, ""%"", """")), txt ), IF(REGEXMATCH(normed, rx), TRUE, raw) )"),TRUE()) -> TRUE | C11: =IFERROR(__xludf.dummyfunction("LET( raw, INDEX(fakerUSDataset!$A:$CX, ROW(), COLUMN()), hdr, INDEX(fakerUSDataset!$1:$1, COLUMN()), norm, INDEX(ColumnMetaData!$I:$I, MATCH(hdr, ColumnMetaData!$C:$C, 0)), patName, INDEX(ColumnMetaData!$D:$D, MATCH(hdr, ColumnMetaData!$C:$C, 0)),"&" rx, INDEX(RegexPatterns!$B:$B, MATCH(patName, RegexPatterns!$A:$A, 0)), txt, TO_TEXT(raw), normed, SWITCH( norm, ""TRIM"", TRIM(txt), ""LOWERCASE|TRIM"", LOWER(TRIM(txt)), ""UPPERCASE|TRIM"", UPPER(TRIM(txt)), ""DIGITS_ONLY"", R"&"EGEXREPLACE(txt, ""[^0-9]"", """"), ""REMOVE_COMMAS|TRIM"", TRIM(SUBSTITUTE(txt, "","", """")), ""REMOVE_CURRENCY_SYMBOL|REMOVE_COMMAS|TRIM"", TRIM(REGEXREPLACE(SUBSTITUTE(txt, "","", """"), ""[$€£¥]"", """")), ""REMOVE_PERCENT|TRIM"", TRIM(SU"&"BSTITUTE(txt, ""%"", """")), txt ), IF(REGEXMATCH(normed, rx), TRUE, raw) )"),TRUE()) -> TRUE | D11: =IFERROR(__xludf.dummyfunction("LET( raw, INDEX(fakerUSDataset!$A:$CX, ROW(), COLUMN()), hdr, INDEX(fakerUSDataset!$1:$1, COLUMN()), norm, INDEX(ColumnMetaData!$I:$I, MATCH(hdr, ColumnMetaData!$C:$C, 0)), patName, INDEX(ColumnMetaData!$D:$D, MATCH(hdr, ColumnMetaData!$C:$C, 0)),"&" rx, INDEX(RegexPatterns!$B:$B, MATCH(patName, RegexPatterns!$A:$A, 0)), txt, TO_TEXT(raw), normed, SWITCH( norm, ""TRIM"", TRIM(txt), ""LOWERCASE|TRIM"", LOWER(TRIM(txt)), ""UPPERCASE|TRIM"", UPPER(TRIM(txt)), ""DIGITS_ONLY"", R"&"EGEXREPLACE(txt, ""[^0-9]"", """"), ""REMOVE_COMMAS|TRIM"", TRIM(SUBSTITUTE(txt, "","", """")), ""REMOVE_CURRENCY_SYMBOL|REMOVE_COMMAS|TRIM"", TRIM(REGEXREPLACE(SUBSTITUTE(txt, "","", """"), ""[$€£¥]"", """")), ""REMOVE_PERCENT|TRIM"", TRIM(SU"&"BSTITUTE(txt, ""%"", """")), txt ), IF(REGEXMATCH(normed, rx), TRUE, raw) )"),TRUE()) -> TRUE | E11: =IFERROR(__xludf.dummyfunction("LET( raw, INDEX(fakerUSDataset!$A:$CX, ROW(), COLUMN()), hdr, INDEX(fakerUSDataset!$1:$1, COLUMN()), norm, INDEX(ColumnMetaData!$I:$I, MATCH(hdr, ColumnMetaData!$C:$C, 0)), patName, INDEX(ColumnMetaData!$D:$D, MATCH(hdr, ColumnMetaData!$C:$C, 0)),"&" rx, INDEX(RegexPatterns!$B:$B, MATCH(patName, RegexPatterns!$A:$A, 0)), txt, TO_TEXT(raw), normed, SWITCH( norm, ""TRIM"", TRIM(txt), ""LOWERCASE|TRIM"", LOWER(TRIM(txt)), ""UPPERCASE|TRIM"", UPPER(TRIM(txt)), ""DIGITS_ONLY"", R"&"EGEXREPLACE(txt, ""[^0-9]"", """"), ""REMOVE_COMMAS|TRIM"", TRIM(SUBSTITUTE(txt, "","", """")), ""REMOVE_CURRENCY_SYMBOL|REMOVE_COMMAS|TRIM"", TRIM(REGEXREPLACE(SUBSTITUTE(txt, "","", """"), ""[$€£¥]"", """")), ""REMOVE_PERCENT|TRIM"", TRIM(SU"&"BSTITUTE(txt, ""%"", """")), txt ), IF(REGEXMATCH(normed, rx), TRUE, raw) )"),TRUE()) -> TRUE | F11: =IFERROR(__xludf.dummyfunction("LET( raw, INDEX(fakerUSDataset!$A:$CX, ROW(), COLUMN()), hdr, INDEX(fakerUSDataset!$1:$1, COLUMN()), norm, INDEX(ColumnMetaData!$I:$I, MATCH(hdr, ColumnMetaData!$C:$C, 0)), patName, INDEX(ColumnMetaData!$D:$D, MATCH(hdr, ColumnMetaData!$C:$C, 0)),"&" rx, INDEX(RegexPatterns!$B:$B, MATCH(patName, RegexPatterns!$A:$A, 0)), txt, TO_TEXT(raw), normed, SWITCH( norm, ""TRIM"", TRIM(txt), ""LOWERCASE|TRIM"", LOWER(TRIM(txt)), ""UPPERCASE|TRIM"", UPPER(TRIM(txt)), ""DIGITS_ONLY"", R"&"EGEXREPLACE(txt, ""[^0-9]"", """"), ""REMOVE_COMMAS|TRIM"", TRIM(SUBSTITUTE(txt, "","", """")), ""REMOVE_CURRENCY_SYMBOL|REMOVE_COMMAS|TRIM"", TRIM(REGEXREPLACE(SUBSTITUTE(txt, "","", """"), ""[$€£¥]"", """")), ""REMOVE_PERCENT|TRIM"", TRIM(SU"&"BSTITUTE(txt, ""%"", """")), txt ), IF(REGEXMATCH(normed, rx), TRUE, raw) )"),TRUE()) -> TRUE | G11: =IFERROR(__xludf.dummyfunction("LET( raw, INDEX(fakerUSDataset!$A:$CX, ROW(), COLUMN()), hdr, INDEX(fakerUSDataset!$1:$1, COLUMN()), norm, INDEX(ColumnMetaData!$I:$I, MATCH(hdr, ColumnMetaData!$C:$C, 0)), patName, INDEX(ColumnMetaData!$D:$D, MATCH(hdr, ColumnMetaData!$C:$C, 0)),"&" rx, INDEX(RegexPatterns!$B:$B, MATCH(patName, RegexPatterns!$A:$A, 0)), txt, TO_TEXT(raw), normed, SWITCH( norm, ""TRIM"", TRIM(txt), ""LOWERCASE|TRIM"", LOWER(TRIM(txt)), ""UPPERCASE|TRIM"", UPPER(TRIM(txt)), ""DIGITS_ONLY"", R"&"EGEXREPLACE(txt, ""[^0-9]"", """"), ""REMOVE_COMMAS|TRIM"", TRIM(SUBSTITUTE(txt, "","", """")), ""REMOVE_CURRENCY_SYMBOL|REMOVE_COMMAS|TRIM"", TRIM(REGEXREPLACE(SUBSTITUTE(txt, "","", """"), ""[$€£¥]"", """")), ""REMOVE_PERCENT|TRIM"", TRIM(SU"&"BSTITUTE(txt, ""%"", """")), txt ), IF(REGEXMATCH(normed, rx), TRUE, raw) )"),TRUE()) -> TRUE | H11: =IFERROR(__xludf.dummyfunction("LET( raw, INDEX(fakerUSDataset!$A:$CX, ROW(), COLUMN()), hdr, INDEX(fakerUSDataset!$1:$1, COLUMN()), norm, INDEX(ColumnMetaData!$I:$I, MATCH(hdr, ColumnMetaData!$C:$C, 0)), patName, INDEX(ColumnMetaData!$D:$D, MATCH(hdr, ColumnMetaData!$C:$C, 0)),"&" rx, INDEX(RegexPatterns!$B:$B, MATCH(patName, RegexPatterns!$A:$A, 0)), txt, TO_TEXT(raw), normed, SWITCH( norm, ""TRIM"", TRIM(txt), ""LOWERCASE|TRIM"", LOWER(TRIM(txt)), ""UPPERCASE|TRIM"", UPPER(TRIM(txt)), ""DIGITS_ONLY"", R"&"EGEXREPLACE(txt, ""[^0-9]"", """"), ""REMOVE_COMMAS|TRIM"", TRIM(SUBSTITUTE(txt, "","", """")), ""REMOVE_CURRENCY_SYMBOL|REMOVE_COMMAS|TRIM"", TRIM(REGEXREPLACE(SUBSTITUTE(txt, "","", """"), ""[$€£¥]"", """")), ""REMOVE_PERCENT|TRIM"", TRIM(SU"&"BSTITUTE(txt, ""%"", """")), txt ), IF(REGEXMATCH(normed, rx), TRUE, raw) )"),TRUE()) -> TRUE | ... CV11: =IFERROR(__xludf.dummyfunction("LET( raw, INDEX(fakerUSDataset!$A:$CX, ROW(), COLUMN()), hdr, INDEX(fakerUSDataset!$1:$1, COLUMN()), norm, INDEX(ColumnMetaData!$I:$I, MATCH(hdr, ColumnMetaData!$C:$C, 0)), patName, INDEX(ColumnMetaData!$D:$D, MATCH(hdr, ColumnMetaData!$C:$C, 0)),"&" rx, INDEX(RegexPatterns!$B:$B, MATCH(patName, RegexPatterns!$A:$A, 0)), txt, TO_TEXT(raw), normed, SWITCH( norm, ""TRIM"", TRIM(txt), ""LOWERCASE|TRIM"", LOWER(TRIM(txt)), ""UPPERCASE|TRIM"", UPPER(TRIM(txt)), ""DIGITS_ONLY"", R"&"EGEXREPLACE(txt, ""[^0-9]"", """"), ""REMOVE_COMMAS|TRIM"", TRIM(SUBSTITUTE(txt, "","", """")), ""REMOVE_CURRENCY_SYMBOL|REMOVE_COMMAS|TRIM"", TRIM(REGEXREPLACE(SUBSTITUTE(txt, "","", """"), ""[$€£¥]"", """")), ""REMOVE_PERCENT|TRIM"", TRIM(SU"&"BSTITUTE(txt, ""%"", """")), txt ), IF(REGEXMATCH(normed, rx), TRUE, raw) )"),TRUE()) -> TRUE
